Workbook

Sheet About

Sheet Workflow

Sheet PFD

Sheet PythonUnitOps
A1: UnitClass | B1: PartitioningType | C1: Reference date | D1: Reference currency | E1: Notes
A2: MyDehulling | B2: Overall, Component | C2: 2025 | D2: USD
A3: MyImpactMilling | B3: None | C3: 2004 | D3: NZD
A4: MyCombine | B4: None
A5: MyClarifier | B5: Overall, Component | C5: 2004 | D5: NZD
A6: MyUltrafiltration | B6: MCF, RC | C6: 2004 | D6: NZD
A7: MyDiafiltration | B7: DF, RC | C7: 2004 | D7: NZD
A8: MySprayDryer | B8: Drying | C8: 2026 | D8: NZD
A9: MySplitter | B9: Overall
A10: MyAirClassification | B10: Overall, Component | C10: 2004 | D10: NZD
A11: MyFiltration | B11: Overall, Component
A12: MyWetExtraction | B12: None | C12: 2008 | D12: USD
A13: MyPasteurisation | B13: None | C13: 2004 | D13: NZD
A14: MyReverseOsmosis | B14: MCF, RC | C14: 2004 | D14: NZD
A15: MyCyclone | B15: Overall, Component | C15: 2004 | D15: NZD
A16: MyCooling | B16: None | C16: 2004 | D16: NZD
A17: MyMixingTank | B17: None | C17: 2008 | D17: USD
A18: MyDrumDryer | B18: Drying | C18: 2008 | D18: USD
A19: MyDecanterCentrifuge | B19: Overall, Component | C19: 2004 | D19: NZD
A20: MyHoldingTube | B20: None | C20: 2002 | D20: USD

Sheet fc
A1: https://www.xe.com/currencytables/?from=NZD&date=2004-07-02 | B1: =YEAR(TODAY()) -> 2026 | C1: 1981 | D1: 1982 | E1: 1982 | F1: 1983 | G1: 1984 | H1: 1985 | I1: 1986 | J1: 1987 | K1: 1988 | L1: 1989 | M1: 1990 | N1: 1991 | O1: 1992 | P1: 1993 | Q1: 1994 | R1: 1995 | S1: 1996 | T1: 1997 | U1: 1998 | V1: 1999 | W1: 2000 | X1: 2001 | Y1: 2002 | Z1: 2003 | AA1: 2004 | AB1: 2005 | AC1: 2006 | AD1: 2007 | AE1: 2008 | AF1: 2009 | AG1: 2010 | AH1: 2011 | AI1: 2012 | AJ1: 2013 | AK1: 2014 | AL1: 2015 | AM1: 2016 | AN1: 2017 | AO1: 2018 | AP1: 2019 | AQ1: 2020 | AR1: 2021 | AS1: 2022 | AT1: 2023 | AU1: 2024 | AV1: 2025
A2: USD | B2: =FORECAST(B$1,INDEX(S2:BE2, 1, COUNTA(S2:BE2)-4):INDEX(S2:BE2, 1, COUNTA(S2:BE2)),INDEX($S$1:$BE$1, 1, COUNTA($S$1:$BE$1)-4):INDEX($S$1:$BE$1, 1, COUNTA($S$1:$BE$1))) -> 1.729514 | E2: 1.302423 | F2: 1.532567 | G2: 1.506478 | S2: 1.4602614 | T2: 1.4743096 | U2: 1.9481019 | V2: 1.8748946 | W2: 2.1321962 | X2: 2.469142 | Y2: 2.1243971 | Z2: 2.0501294 | AA2: 1.5460334 | AB2: 1.46305 | AC2: 1.64065 | AD2: 1.2779897 | AE2: 1.3133595 | AF2: 1.5902381 | AG2: 1.4119312 | AH2: 1.3043772 | AI2: 1.2215979 | AJ2: 1.1939389 | AK2: 1.1534053 | AL2: 1.3408423 | AM2: 1.4501745 | AN2: 1.4274499 | AO2: 1.3806302 | AP2: 1.6015821 | AQ2: 1.5012462 | AR2: 1.4410587 | AS2: 1.5763308 | AT2: 1.6067924 | AU2: 1.6572522 | AV2: 1.6419825
A3: EUR | B3: =FORECAST(B$1,INDEX(S3:BE3, 1, COUNTA(S3:BE3)-4):INDEX(S3:BE3, 1, COUNTA(S3:BE3)),INDEX($S$1:$BE$1, 1, COUNTA($S$1:$BE$1)-4):INDEX($S$1:$BE$1, 1, COUNTA($S$1:$BE$1))) -> 1.95686 | S3: #N/A | T3: #N/A | U3: #N/A | V3: 1.9206651 | W3: 2.0298507 | X3: 2.0879052 | Y3: 2.0929892 | Z3: 2.0152917 | AA3: 1.9027802 | AB3: 1.7494425 | AC3: 2.0965032 | AD3: 1.7413752 | AE3: 2.0837026 | AF3: 2.2288263 | AG3: 1.9172353 | AH3: 1.8535631 | AI3: 1.6301012 | AJ3: 1.534909 | AK3: 1.5922028 | AL3: 1.4436432 | AM3: 1.6502044 | AN3: 1.5209585 | AO3: 1.7010998 | AP3: 1.7510663 | AQ3: 1.7858355 | AR3: 1.6711454 | AS3: 1.6185502 | AT3: 1.7229279 | AU3: 1.7928259 | AV3: 1.9327183
A4: GBP | B4: =FORECAST(B$1,INDEX(S4:BE4, 1, COUNTA(S4:BE4)-4):INDEX(S4:BE4, 1, COUNTA(S4:BE4)),INDEX($S$1:$BE$1, 1, COUNTA($S$1:$BE$1)-4):INDEX($S$1:$BE$1, 1, COUNTA($S$1:$BE$1))) -> 2.2602739 | E4: =E2/0.560214 -> 2.3248669 | F4: =F2/0.675341 -> 2.2693232 | G4: =G2/0.692699 -> 2.1747945 | S4: 2.2761354 | T4: 2.4566474 | U4: 3.2259092 | V4: 2.9602599 | W4: 3.2324094 | X4: 3.4977738 | Y4: 3.3362844 | Z4: 3.1354555 | AA4: 2.829505 | AB4: 2.5875685 | AC4: 3.0330733 | AD4: 2.5762655 | AE4: 2.6165925 | AF4: 2.6070832 | AG4: 2.1589885 | AH4: 2.1035517 | AI4: 1.9561446 | AJ4: 1.8182947 | AK4: 1.919046 | AL4: 1.9880679 | AM4: 2.0599034 | AN4: 1.7905931 | AO4: 1.9340349 | AP4: 1.9608316 | AQ4: 1.9727422 | AR4: 1.9551362 | AS4: 1.9349268 | AT4: 1.9517247 | AU4: 2.0861394 | AV4: 2.2530079
A5: INR | B5: =FORECAST(B$1,INDEX(S5:BE5, 1, COUNTA(S5:BE5)-4):INDEX(S5:BE5, 1, COUNTA(S5:BE5)),INDEX($S$1:$BE$1, 1, COUNTA($S$1:$BE$1)-4):INDEX($S$1:$BE$1, 1, COUNTA($S$1:$BE$1))) -> 0.019383695 | S5: 0.042020137 | T5: 0.041243845 | U5: 0.04588532 | V5: 0.043210293 | W5: 0.047753553 | X5: 0.052389378 | Y5: 0.043955945 | Z5: 0.042007524 | AA5: 0.033774623 | AB5: 0.033606294 | AC5: 0.03575959 | AD5: 0.031617755 | AE5: 0.030422968 | AF5: 0.032965636 | AG5: 0.031519782 | AH5: 0.029341513 | AI5: 0.024011161 | AJ5: 0.021993704 | AK5: 0.019263695 | AL5: 0.021582808 | AM5: 0.021857209 | AN5: 0.02202627 | AO5: 0.021193702 | AP5: 0.022517702 | AQ5: 0.020064876 | AR5: 0.019426296 | AS5: 0.019966144 | AT5: 0.01952656 | AU5: 0.019845854 | AV5: 0.019153236
A6: AUD | B6: =FORECAST(B$1,INDEX(S6:BE6, 1, COUNTA(S6:BE6)-4):INDEX(S6:BE6, 1, COUNTA(S6:BE6)),INDEX($S$1:$BE$1, 1, COUNTA($S$1:$BE$1)-4):INDEX($S$1:$BE$1, 1, COUNTA($S$1:$BE$1))) -> 1.0963295 | E6: =E2/0.95057 -> 1.3701495 | F6: =F2/1.156738 -> 1.3249042 | G6: =G2/1.068148 -> 1.4103645 | S6: 1.1434233 | T6: 1.108435 | U6: 1.1924608 | V6: 1.2560977 | W6: 1.271855 | X6: 1.2611425 | Y6: 1.1514901 | Z6: 1.1525748 | AA6: 1.1018511 | AB6: 1.1001617 | AC6: 1.2178221 | AD6: 1.0983596 | AE6: 1.2650396 | AF6: 1.2635552 | AG6: 1.3009979 | AH6: 1.3544692 | AI6: 1.2639873 | AJ6: 1.2441207 | AK6: 1.0669946 | AL6: 1.0208187 | AM6: 1.1124207 | AN6: 1.0892156 | AO6: 1.0604228 | AP6: 1.0732723 | AQ6: 1.0830494 | AR6: 1.0475789 | AS6: 1.1085582 | AT6: 1.0706008 | AU6: 1.0975694 | AV6: 1.0791401
A7: CAD | B7: =FORECAST(B$1,INDEX(S7:BE7, 1, COUNTA(S7:BE7)-4):INDEX(S7:BE7, 1, COUNTA(S7:BE7)),INDEX($S$1:$BE$1, 1, COUNTA($S$1:$BE$1)-4):INDEX($S$1:$BE$1, 1, COUNTA($S$1:$BE$1))) -> 1.2283516 | S7: 1.0711225 | T7: 1.0704346 | U7: 1.3273162 | V7: 1.280713 | W7: 1.4403811 | X7: 1.6296247 | Y7: 1.339726 | Z7: 1.3435035 | AA7: 1.1669751 | AB7: 1.1781213 | AC7: 1.468498 | AD7: 1.210957 | AE7: 1.2967015 | AF7: 1.3709488 | AG7: 1.4014241 | AH7: 1.3542335 | AI7: 1.2233717 | AJ7: 1.1740537 | AK7: 1.0459297 | AL7: 1.0627571 | AM7: 1.111491 | AN7: 1.0715826 | AO7: 1.0708129 | AP7: 1.2101142 | AQ7: 1.1325686 | AR7: 1.1380993 | AS7: 1.2280045 | AT7: 1.174834 | AU7: 1.2139318 | AV7: 1.2055738
A8: SGD | B8: =FORECAST(B$1,INDEX(S8:BE8, 1, COUNTA(S8:BE8)-4):INDEX(S8:BE8, 1, COUNTA(S8:BE8)),INDEX($S$1:$BE$1, 1, COUNTA($S$1:$BE$1)-4):INDEX($S$1:$BE$1, 1, COUNTA($S$1:$BE$1))) -> 1.3444073 | S8: 1.0347044 | T8: 1.0312567 | U8: 1.1418901 | V8: 1.1058536 | W8: 1.234267 | X8: 1.3551079 | Y8: 1.189932 | Z8: 1.1576377 | AA8: 0.90300623 | AB8: 0.8633601 | AC8: 1.0365819 | AD8: 0.83906041 | AE8: 0.96776327 | AF8: 1.095809 | AG8: 1.0109357 | AH8: 1.0346263 | AI8: 0.97137234 | AJ8: 0.96247469 | AK8: 0.91618139 | AL8: 0.98315968 | AM8: 1.0749534 | AN8: 1.02176 | AO8: 1.0528619 | AP8: 1.1559953 | AQ8: 1.0975982 | AR8: 1.0633676 | AS8: 1.1453873 | AT8: 1.1950031 | AU8: 1.2255059 | AV8: 1.2906743
A9: CHF | B9: =FORECAST(B$1,INDEX(S9:BE9, 1, COUNTA(S9:BE9)-4):INDEX(S9:BE9, 1, COUNTA(S9:BE9)),INDEX($S$1:$BE$1, 1, COUNTA($S$1:$BE$1)-4):INDEX($S$1:$BE$1, 1, COUNTA($S$1:$BE$1))) -> 2.1342037 | S9: 1.167952 | T9: 1.0010704 | U9: 1.2693125 | V9: 1.1961937 | W9: 1.3059326 | X9: 1.3717362 | Y9: 1.4359352 | Z9: 1.3759239 | AA9: 1.2538096 | AB9: 1.1283742 | AC9: 1.3411673 | AD9: 1.0550912 | AE9: 1.294018 | AF9: 1.4673726 | AG9: 1.3380699 | AH9: 1.4111457 | AI9: 1.3543213 | AJ9: 1.2619681 | AK9: 1.3068652 | AL9: 1.3864412 | AM9: 1.5120282 | AN9: 1.4226839 | AO9: 1.4475065 | AP9: 1.6123949 | AQ9: 1.6580872 | AR9: 1.549675 | AS9: 1.6612247 | AT9: 1.7589667 | AU9: 1.8278083 | AV9: 2.0681234
A10: MYR | B10: =FORECAST(B$1,INDEX(S10:BE10, 1, COUNTA(S10:BE10)-4):INDEX(S10:BE10, 1, COUNTA(S10:BE10)),INDEX($S$1:$BE$1, 1, COUNTA($S$1:$BE$1)-4):INDEX($S$1:$BE$1, 1, COUNTA($S$1:$BE$1))) -> 0.3855428 | S10: 0.58526135 | T10: 0.58413616 | U10: 0.46495885 | V10: 0.49339332 | W10: 0.56125195 | X10: 0.64977422 | Y10: 0.55920075 | Z10: 0.53950823 | AA10: 0.40685089 | AB10: 0.38578473 | AC10: 0.44646575 | AD10: 0.37211234 | AE10: 0.40111919 | AF10: 0.45167532 | AG10: 0.43524391 | AH10: 0.43112782 | AI10: 0.39827137 | AJ10: 0.38591967 | AK10: 0.35339496 | AL10: 0.36429584 | AM10: 0.37404253 | AN10: 0.3224418 | AO10: 0.35724395 | AP10: 0.38198565 | AQ10: 0.35789047 | AR10: 0.34468464 | AS10: 0.35399664 | AT10: 0.35795804 | AU10: 0.35082215 | AV10: 0.38976705
A11: JPY | B11: =FORECAST(B$1,INDEX(S11:BE11, 1, COUNTA(S11:BE11)-4):INDEX(S11:BE11, 1, COUNTA(S11:BE11)),INDEX($S$1:$BE$1, 1, COUNTA($S$1:$BE$1)-4):INDEX($S$1:$BE$1, 1, COUNTA($S$1:$BE$1))) -> 0.010407641 | S11: 0.013260497 | T11: 0.012877328 | U11: 0.013750995 | V11: 0.015483399 | W11: 0.020134053 | X11: 0.01986968 | Y11: 0.017312967 | Z11: 0.017052954 | AA11: 0.014236693 | AB11: 0.013089242 | AC11: 0.014338213 | AD11: 0.010447973 | AE11: 0.012405691 | AF11: 0.016581968 | AG11: 0.015046689 | AH11: 0.015516411 | AI11: 0.014750925 | AJ11: 0.012755595 | AK11: 0.011142068 | AL11: 0.011209681 | AM11: 0.012937628 | AN11: 0.012816609 | AO11: 0.012988191 | AP11: 0.014869677 | AQ11: 0.014235031 | AR11: 0.012986184 | AS11: 0.011962164 | AT11: 0.01196317 | AU11: 0.010589067 | AV11: 0.011388954
A12: CNY | B12: =FORECAST(B$1,INDEX(S12:BE12, 1, COUNTA(S12:BE12)-4):INDEX(S12:BE12, 1, COUNTA(S12:BE12)),INDEX($S$1:$BE$1, 1, COUNTA($S$1:$BE$1)-4):INDEX($S$1:$BE$1, 1, COUNTA($S$1:$BE$1))) -> 0.23198266 | S12: 0.17544987 | T12: 0.17779919 | U12: 0.23533316 | V12: 0.22647758 | W12: 0.25787912 | X12: 0.29831364 | Y12: 0.25670289 | Z12: 0.24768991 | AA12: 0.18668068 | AB12: 0.1767714 | AC12: 0.20527369 | AD12: 0.16803493 | AE12: 0.19161943 | AF12: 0.23275637 | AG12: 0.20680364 | AH12: 0.19917805 | AI12: 0.1939968 | AJ12: 0.19255175 | AK12: 0.18580415 | AL12: 0.2164343 | AM12: 0.22403036 | AN12: 0.20718607 | AO12: 0.2200436 | AP12: 0.22404539 | AQ12: 0.21645058 | AR12: 0.2235055 | AS12: 0.23290319 | AT12: 0.23379456 | AU12: 0.22910311 | AV12: 0.22920588
A13: NZD | B13: =FORECAST(B$1,INDEX(S13:BE13, 1, COUNTA(S13:BE13)-4):INDEX(S13:BE13, 1, COUNTA(S13:BE13)),INDEX($S$1:$BE$1, 1, COUNTA($S$1:$BE$1)-4):INDEX($S$1:$BE$1, 1, COUNTA($S$1:$BE$1))) -> 1 | S13: 1 | T13: 1 | U13: 1 | V13: 1 | W13: 1 | X13: 1 | Y13: 1 | Z13: 1 | AA13: 1 | AB13: 1 | AC13: 1 | AD13: 1 | AE13: 1 | AF13: 1 | AG13: 1 | AH13: 1 | AI13: 1 | AJ13: 1 | AK13: 1 | AL13: 1 | AM13: 1 | AN13: 1 | AO13: 1 | AP13: 1 | AQ13: 1 | AR13: 1 | AS13: 1 | AT13: 1 | AU13: 1 | AV13: 1
A14: THB | B14: =FORECAST(B$1,INDEX(S14:BE14, 1, COUNTA(S14:BE14)-4):INDEX(S14:BE14, 1, COUNTA(S14:BE14)),INDEX($S$1:$BE$1, 1, COUNTA($S$1:$BE$1)-4):INDEX($S$1:$BE$1, 1, COUNTA($S$1:$BE$1))) -> 0.050886919 | S14: 0.05751928 | T14: 0.050845643 | U14: 0.046164056 | V14: 0.050823926 | W14: 0.054462226 | X14: 0.054506331 | Y14: 0.048944004 | Z14: 0.049376897 | AA14: 0.038221228 | AB14: 0.035346492 | AC14: 0.043017337 | AD14: 0.040418042 | AE14: 0.039325077 | AF14: 0.046593977 | AG14: 0.043630643 | AH14: 0.04307573 | AI14: 0.039617249 | AJ14: 0.040727954 | AK14: 0.035655849 | AL14: 0.041280416 | AM14: 0.041191491 | AN14: 0.041556037 | AO14: 0.044207171 | AP14: 0.052312974 | AQ14: 0.048390832 | AR14: 0.042823803 | AS14: 0.043639135 | AT14: 0.046494276 | AU14: 0.045274618 | AV14: 0.050555238
A15: HUF | B15: =FORECAST(B$1,INDEX(S15:BE15, 1, COUNTA(S15:BE15)-4):INDEX(S15:BE15, 1, COUNTA(S15:BE15)),INDEX($S$1:$BE$1, 1, COUNTA($S$1:$BE$1)-4):INDEX($S$1:$BE$1, 1, COUNTA($S$1:$BE$1))) -> 0.0047961561 | S15: 0.0097257926 | T15: 0.0078355812 | U15: 0.0088797452 | V15: 0.0077258761 | W15: 0.0078675922 | X15: 0.0086150401 | Y15: 0.0086036675 | Z15: 0.0082458163 | AA15: 0.007590007 | AB15: 0.0070697526 | AC15: 0.0074013173 | AD15: 0.00709352 | AE15: 0.0088335612 | AF15: 0.0082175514 | AG15: 0.0072351937 | AH15: 0.0069836287 | AI15: 0.0055338521 | AJ15: 0.0050498846 | AK15: 0.0051854004 | AL15: 0.0048329056 | AM15: 0.0052644274 | AN15: 0.0049304271 | AO15: 0.0054185009 | AP15: 0.005215081 | AQ15: 0.0051795734 | AR15: 0.0046819262 | AS15: 0.0040522874 | AT15: 0.0044105638 | AU15: 0.0046484661 | AV15: 0.0048347619
A16: AED | B16: =FORECAST(B$1,INDEX(S16:BE16, 1, COUNTA(S16:BE16)-4):INDEX(S16:BE16, 1, COUNTA(S16:BE16)),INDEX($S$1:$BE$1, 1, COUNTA($S$1:$BE$1)-4):INDEX($S$1:$BE$1, 1, COUNTA($S$1:$BE$1))) -> 0.47093643 | S16: #N/A | T16: #N/A | U16: #N/A | V16: 0.51055051 | W16: 0.58074252 | X16: 0.67224123 | Y16: 0.57842072 | Z16: 0.55821625 | AA16: 0.42091843 | AB16: 0.39832562 | AC16: 0.44675144 | AD16: 0.3479568 | AE16: 0.35756161 | AF16: 0.43318934 | AG16: 0.38443431 | AH16: 0.35514518 | AI16: 0.33257046 | AJ16: 0.32505824 | AK16: 0.31400987 | AL16: 0.36502541 | AM16: 0.39484707 | AN16: 0.3886491 | AO16: 0.37593743 | AP16: 0.43610132 | AQ16: 0.40878046 | AR16: 0.39239174 | AS16: 0.42922554 | AT16: 0.43752006 | AU16: 0.45125997 | AV16: 0.44710211
A17: HKD | B17: =FORECAST(B$1,INDEX(S17:BE17, 1, COUNTA(S17:BE17)-4):INDEX(S17:BE17, 1, COUNTA(S17:BE17)),INDEX($S$1:$BE$1, 1, COUNTA($S$1:$BE$1)-4):INDEX($S$1:$BE$1, 1, COUNTA($S$1:$BE$1))) -> 0.22022436 | S17: 0.18862468 | T17: 0.19032327 | U17: 0.25139368 | V17: 0.24168102 | W17: 0.27353382 | X17: 0.31658485 | Y17: 0.27238667 | Z17: 0.26284502 | AA17: 0.19821907 | AB17: 0.18823174 | AC17: 0.21122526 | AD17: 0.16349834 | AE17: 0.16842496 | AF17: 0.20519466 | AG17: 0.18177994 | AH17: 0.16768493 | AI17: 0.15730584 | AJ17: 0.15379249 | AK17: 0.14869477 | AL17: 0.17295404 | AM17: 0.18702384 | AN17: 0.18369454 | AO17: 0.17590652 | AP17: 0.20420923 | AQ17: 0.19370738 | AR17: 0.1851058 | AS17: 0.20080629 | AT17: 0.20473972 | AU17: 0.21213179 | AV17: 0.20916684
A18: MXN | B18: =FORECAST(B$1,INDEX(S18:BE18, 1, COUNTA(S18:BE18)-4):INDEX(S18:BE18, 1, COUNTA(S18:BE18)),INDEX($S$1:$BE$1, 1, COUNTA($S$1:$BE$1)-4):INDEX($S$1:$BE$1, 1, COUNTA($S$1:$BE$1))) -> 0.10019324 | S18: #N/A | T18: #N/A | U18: #N/A | V18: #N/A | W18: #N/A | X18: #N/A | Y18: 0.20923453 | Z18: 0.20583982 | AA18: 0.13482101 | AB18: 0.1363577 | AC18: 0.14458888 | AD18: 0.11865952 | AE18: 0.12663971 | AF18: 0.1208466 | AG18: 0.11479367 | AH18: 0.11023695 | AI18: 0.095390382 | AJ18: 0.096744944 | AK18: 0.088534881 | AL18: 0.088708322 | AM18: 0.083579855 | AN18: 0.076257267 | AO18: 0.07574632 | AP18: 0.080973542 | AQ18: 0.066956538 | AR18: 0.07031468 | AS18: 0.077803995 | AT18: 0.085845763 | AU18: 0.098375976 | AV18: 0.087177968
A19: ZAR | B19: =FORECAST(B$1,INDEX(S19:BE19, 1, COUNTA(S19:BE19)-4):INDEX(S19:BE19, 1, COUNTA(S19:BE19)),INDEX($S$1:$BE$1, 1, COUNTA($S$1:$BE$1)-4):INDEX($S$1:$BE$1, 1, COUNTA($S$1:$BE$1))) -> 0.088452156 | S19: 0.3374036 | T19: 0.32541212 | U19: 0.30780462 | V19: 0.31285517 | W19: 0.3147153 | X19: 0.30789205 | Y19: 0.20402223 | Z19: 0.20291755 | AA19: 0.25309161 | AB19: 0.21390871 | AC19: 0.22901951 | AD19: 0.18341639 | AE19: 0.16761026 | AF19: 0.20315058 | AG19: 0.19437318 | AH19: 0.19454019 | AI19: 0.15929224 | AJ19: 0.12984973 | AK19: 0.10917217 | AL19: 0.11206744 | AM19: 0.098220734 | AN19: 0.10634037 | AO19: 0.11646985 | AP19: 0.10427852 | AQ19: 0.086688361 | AR19: 0.096887583 | AS19: 0.095759089 | AT19: 0.088355312 | AU19: 0.089952549 | AV19: 0.092669701
A20: PHP | B20: =FORECAST(B$1,INDEX(S20:BE20, 1, COUNTA(S20:BE20)-4):INDEX(S20:BE20, 1, COUNTA(S20:BE20)),INDEX($S$1:$BE$1, 1, COUNTA($S$1:$BE$1)-4):INDEX($S$1:$BE$1, 1, COUNTA($S$1:$BE$1))) -> 0.029284208 | S20: 0.055837618 | T20: 0.055951616 | U20: 0.047172817 | V20: 0.049313378 | W20: 0.049701542 | X20: 0.04680838 | Y20: 0.040549552 | Z20: 0.040412584 | AA20: 0.027620069 | AB20: 0.026139896 | AC20: 0.030920947 | AD20: 0.027638185 | AE20: 0.02915014 | AF20: 0.03306105 | AG20: 0.031389699 | AH20: 0.030117233 | AI20: 0.028462207 | AJ20: 0.029238151 | AK20: 0.025774779 | AL20: 0.030082104 | AM20: 0.031462522 | AN20: 0.028435256 | AO20: 0.02644888 | AP20: 0.030805751 | AQ20: 0.030614498 | AR20: 0.028425603 | AS20: 0.028460107 | AT20: 0.029219716 | AU20: 0.028710901 | AV20: 0.029126333
A21: SEK | B21: =FORECAST(B$1,INDEX(S21:BE21, 1, COUNTA(S21:BE21)-4):INDEX(S21:BE21, 1, COUNTA(S21:BE21)),INDEX($S$1:$BE$1, 1, COUNTA($S$1:$BE$1)-4):INDEX($S$1:$BE$1, 1, COUNTA($S$1:$BE$1))) -> 0.16418811 | S21: 0.21818766 | T21: 0.18957397 | U21: 0.24077515 | V21: 0.22067895 | W21: 0.24237765 | X21: 0.22551561 | Y21: 0.23038418 | Z21: 0.22231361 | AA21: 0.20718154 | AB21: 0.18440257 | AC21: 0.22798521 | AD21: 0.18806365 | AE21: 0.22001165 | AF21: 0.20501018 | AG21: 0.19708937 | AH21: 0.20718925 | AI21: 0.18469601 | AJ21: 0.18342829 | AK21: 0.17874747 | AL21: 0.15503029 | AM21: 0.17859289 | AN21: 0.15912703 | AO21: 0.16515448 | AP21: 0.16213591 | AQ21: 0.17342931 | AR21: 0.16463448 | AS21: 0.15600538 | AT21: 0.1533533 | AU21: 0.15305418 | AV21: 0.17305586
A22: IDR | B22: =FORECAST(B$1,INDEX(S22:BE22, 1, COUNTA(S22:BE22)-4):INDEX(S22:BE22, 1, COUNTA(S22:BE22)),INDEX($S$1:$BE$1, 1, COUNTA($S$1:$BE$1)-4):INDEX($S$1:$BE$1, 1, COUNTA($S$1:$BE$1))) -> 0.00010252091 | S22: 0.00062767781 | T22: 0.00060586598 | U22: 0.00013538625 | V22: 0.0002769416 | W22: 0.00024409802 | X22: 0.00021812209 | Y22: 0.0002362157 | Z22: 0.00023270947 | AA22: 0.00016903929 | AB22: 0.00014951432 | AC22: 0.0001764145 | AD22: 0.00014174957 | AE22: 0.0001425434 | AF22: 0.00015570724 | AG22: 0.0001557563 | AH22: 0.0001501874 | AI22: 0.0001336833 | AJ22: 0.0001227574 | AK22: 0.0001023308 | AL22: 0.0001031814 | AM22: 0.0001101334 | AN22: 0.000107057 | AO22: 0.0001002798 | AP22: 0.0001127121 | AQ22: 0.0001031238 | AR22: 0.0001008107 | AS22: 0.00010618761 | AT22: 0.00010451423 | AU22: 0.00010291874 | AV22: 0.00010137717
A23: SAR | B23: =FORECAST(B$1,INDEX(S23:BE23, 1, COUNTA(S23:BE23)-4):INDEX(S23:BE23, 1, COUNTA(S23:BE23)),INDEX($S$1:$BE$1, 1, COUNTA($S$1:$BE$1)-4):INDEX($S$1:$BE$1, 1, COUNTA($S$1:$BE$1))) -> 0.46120375 | S23: 0.38935304 | T23: 0.39306358 | U23: 0.51937882 | V23: 0.49990525 | W23: 0.56850984 | X23: 0.65836765 | Y23: 0.56646801 | Z23: 0.54669187 | AA23: 0.41225358 | AB23: 0.39013626 | AC23: 0.43750667 | AD23: 0.34075847 | AE23: 0.35026118 | AF23: 0.42403716 | AG23: 0.376495 | AH23: 0.347813 | AI23: 0.32575074 | AJ23: 0.31835827 | AK23: 0.30749805 | AL23: 0.35744185 | AM23: 0.38670633 | AN23: 0.38064315 | AO23: 0.36816805 | AP23: 0.42708856 | AQ23: 0.40033233 | AR23: 0.38428231 | AS23: 0.42035488 | AT23: 0.42847798 | AU23: 0.44193393 | AV23: 0.437862
A24: BRL | B24: =FORECAST(B$1,INDEX(S24:BE24, 1, COUNTA(S24:BE24)-4):INDEX(S24:BE24, 1, COUNTA(S24:BE24)),INDEX($S$1:$BE$1, 1, COUNTA($S$1:$BE$1)-4):INDEX($S$1:$BE$1, 1, COUNTA($S$1:$BE$1))) -> 0.32649699 | S24: #N/A | T24: #N/A | U24: 1.6843642 | V24: #N/A | W24: 1.1838957 | X24: 1.0633687 | Y24: 0.57442602 | Z24: 0.70569947 | AA24: 0.508315 | AB24: 0.62132724 | AC24: 0.75806861 | AD24: 0.66691873 | AE24: 0.82062403 | AF24: 0.81342 | AG24: 0.79882012 | AH24: 0.80667488 | AI24: 0.66852618 | AJ24: 0.59195397 | AK24: 0.50970564 | AL24: 0.42506382 | AM24: 0.40912187 | AN24: 0.4571936 | AO24: 0.41775432 | AP24: 0.38454181 | AQ24: 0.28362956 | AR24: 0.26843373 | AS24: 0.30602428 | AT24: 0.30559553 | AU24: 0.32276642 | AV24: 0.30246325
A25: TRY | B25: =FORECAST(B$1,INDEX(S25:BE25, 1, COUNTA(S25:BE25)-4):INDEX(S25:BE25, 1, COUNTA(S25:BE25)),INDEX($S$1:$BE$1, 1, COUNTA($S$1:$BE$1)-4):INDEX($S$1:$BE$1, 1, COUNTA($S$1:$BE$1))) -> 0.0017914315 | S25: #N/A | T25: #N/A | U25: #N/A | V25: #N/A | W25: #N/A | X25: #N/A | Y25: #N/A | Z25: #N/A | AA25: #N/A | AB25: #N/A | AC25: 1.034784 | AD25: 0.98625267 | AE25: 1.0591441 | AF25: 1.036546 | AG25: 0.93061287 | AH25: 0.85128247 | AI25: 0.68490574 | AJ25: 0.66062001 | AK25: 0.53896433 | AL25: 0.51653982 | AM25: 0.51254866 | AN25: 0.39248704 | AO25: 0.34871119 | AP25: 0.27959933 | AQ25: 0.21292894 | AR25: 0.1625766 | AS25: 0.087868213 | AT25: 0.084680802 | AU25: 0.051357138 | AV25: 0.041242706
A26: KES | B26: =FORECAST(B$1,INDEX(S26:BE26, 1, COUNTA(S26:BE26)-4):INDEX(S26:BE26, 1, COUNTA(S26:BE26)),INDEX($S$1:$BE$1, 1, COUNTA($S$1:$BE$1)-4):INDEX($S$1:$BE$1, 1, COUNTA($S$1:$BE$1))) -> 0.012434772 | S26: #N/A | T26: #N/A | U26: #N/A | V26: 0.02586349 | W26: 0.027476755 | X26: 0.031183911 | Y26: 0.026875029 | Z26: 0.02601357 | AA26: 0.019454302 | AB26: 0.019174968 | AC26: 0.022382827 | AD26: 0.019174639 | AE26: 0.020097315 | AF26: 0.020951753 | AG26: 0.018265604 | AH26: 0.01565879 | AI26: 0.0147358 | AJ26: 0.013964202 | AK26: 0.013334166 | AL26: 0.014501497 | AM26: 0.014290225 | AN26: 0.013843952 | AO26: 0.013655682 | AP26: 0.015417089 | AQ26: 0.013927395 | AR26: 0.013041031 | AS26: 0.013247082 | AT26: 0.012421424 | AU26: 0.012651537 | AV26: 0.012707299
A27: KRW | B27: =FORECAST(B$1,INDEX(S27:BE27, 1, COUNTA(S27:BE27)-4):INDEX(S27:BE27, 1, COUNTA(S27:BE27)),INDEX($S$1:$BE$1, 1, COUNTA($S$1:$BE$1)-4):INDEX($S$1:$BE$1, 1, COUNTA($S$1:$BE$1))) -> 0.0012141216 | S27: 0.0017973436 | T27: 0.0016645258 | U27: 0.0014255376 | V27: 0.0016065935 | W27: 0.0019124551 | X27: 0.00189934 | Y27: 0.0017338396 | Z27: 0.0017144256 | AA27: 0.0013384122 | AB27: 0.0014213338 | AC27: 0.0017300777 | AD27: 0.0013867217 | AE27: 0.0012665749 | AF27: 0.0012451565 | AG27: 0.001253434 | AH27: 0.0012000625 | AI27: 0.0010780073 | AJ27: 0.0010745408 | AK27: 0.0010913743 | AL27: 0.0012206268 | AM27: 0.001261786 | AN27: 0.0012771201 | AO27: 0.0013019565 | AP27: 0.001331427 | AQ27: 0.0012676971 | AR27: 0.0012201922 | AS27: 0.0012076733 | AT27: 0.0012302705 | AU27: 0.0012129083 | AV27: 0.0012130719
A28: EGP | B28: =FORECAST(B$1,INDEX(S28:BE28, 1, COUNTA(S28:BE28)-4):INDEX(S28:BE28, 1, COUNTA(S28:BE28)),INDEX($S$1:$BE$1, 1, COUNTA($S$1:$BE$1)-4):INDEX($S$1:$BE$1, 1, COUNTA($S$1:$BE$1))) -> 0.0096032358 | S28: 0.42994859 | T28: 0.43523871 | U28: 0.57167507 | V28: 0.55024492 | W28: 0.61763402 | X28: 0.63731307 | Y28: 0.45985905 | Z28: 0.44255357 | AA28: 0.2460743 | AB28: 0.25233702 | AC28: 0.28656391 | AD28: 0.22468708 | AE28: 0.246397 | AF28: 0.28447908 | AG28: 0.25657483 | AH28: 0.21896547 | AI28: 0.20231829 | AJ28: 0.17544252 | AK28: 0.16548377 | AL28: 0.17576613 | AM28: 0.16330614 | AN28: 0.078539195 | AO28: 0.078313653 | AP28: 0.098252556 | AQ28: 0.093863071 | AR28: 0.091657684 | AS28: 0.083079536 | AT28: 0.051996278 | AU28: 0.035372461 | AV28: 0.033110971
A29: IQD | B29: =FORECAST(B$1,INDEX(S29:BE29, 1, COUNTA(S29:BE29)-4):INDEX(S29:BE29, 1, COUNTA(S29:BE29)),INDEX($S$1:$BE$1, 1, COUNTA($S$1:$BE$1)-4):INDEX($S$1:$BE$1, 1, COUNTA($S$1:$BE$1))) -> 0.0013531243 | S29: #N/A | T29: #N/A | U29: #N/A | V29: #N/A | W29: #N/A | X29: 7.9419171 | Y29: 6.8330561 | Z29: 6.5941763 | AA29: 0.0010578047 | AB29: 0.00099880531 | AC29: 0.0011168482 | AD29: 0.0010236201 | AE29: 0.0010984941 | AF29: 0.0013624384 | AG29: 0.0012082762 | AH29: 0.0011068114 | AI29: 0.001048132 | AJ29: 0.0010267803 | AK29: 0.0009900471 | AL29: 0.0011519951 | AM29: 0.0013107547 | AN29: 0.0012071458 | AO29: 0.0011652609 | AP29: 0.0013394202 | AQ29: 0.0012618839 | AR29: 0.0009870817 | AS29: 0.0010799742 | AT29: 0.0011012111 | AU29: 0.0012656139 | AV29: 0.0012536315
A30: NOK | B30: =FORECAST(B$1,INDEX(S30:BE30, 1, COUNTA(S30:BE30)-4):INDEX(S30:BE30, 1, COUNTA(S30:BE30)),INDEX($S$1:$BE$1, 1, COUNTA($S$1:$BE$1)-4):INDEX($S$1:$BE$1, 1, COUNTA($S$1:$BE$1))) -> 0.15393851 | S30: 0.22440017 | T30: 0.20070649 | U30: 0.25059729 | V30: 0.23775006 | W30: 0.24836298 | X30: 0.26271605 | Y30: 0.286362 | Z30: 0.27391722 | AA30: 0.22326833 | AB30: 0.22222982 | AC30: 0.26392709 | AD30: 0.21979698 | AE30: 0.25950486 | AF30: 0.24813295 | AG30: 0.2389867 | AH30: 0.23718504 | AI30: 0.21465811 | AJ30: 0.2049976 | AK30: 0.19275602 | AL30: 0.167417 | AM30: 0.17444274 | AN30: 0.1658807 | AO30: 0.17606777 | AP30: 0.17560159 | AQ30: 0.16782648 | AR30: 0.16701888 | AS30: 0.16387087 | AT30: 0.15229282 | AU30: 0.15314631 | AV30: 0.16262679
A31: KWD | B31: =FORECAST(B$1,INDEX(S31:BE31, 1, COUNTA(S31:BE31)-4):INDEX(S31:BE31, 1, COUNTA(S31:BE31)),INDEX($S$1:$BE$1, 1, COUNTA($S$1:$BE$1)-4):INDEX($S$1:$BE$1, 1, COUNTA($S$1:$BE$1))) -> 5.6130191 | S31: #N/A | T31: #N/A | U31: #N/A | V31: 6.1101341 | W31: 6.9679613 | X31: 8.0140929 | Y31: 7.0394496 | Z31: 6.7915118 | AA31: 5.2454142 | AB31: 5.0095874 | AC31: 5.6738484 | AD31: 4.4357746 | AE31: 4.9581468 | AF31: 5.529532 | AG31: 4.8931975 | AH31: 4.7040182 | AI31: 4.3981918 | AJ31: 4.1807644 | AK31: 4.0930443 | AL31: 4.4602665 | AM31: 4.805484 | AN31: 4.6805471 | AO31: 4.5938013 | AP31: 5.2574406 | AQ31: 4.9100735 | AR31: 4.7826471 | AS31: 5.1414684 | AT31: 5.2375716 | AU31: 5.389742 | AV31: 5.3722993
A32: RUB | B32: =FORECAST(B$1,INDEX(S32:BE32, 1, COUNTA(S32:BE32)-4):INDEX(S32:BE32, 1, COUNTA(S32:BE32)),INDEX($S$1:$BE$1, 1, COUNTA($S$1:$BE$1)-4):INDEX($S$1:$BE$1, 1, COUNTA($S$1:$BE$1))) -> 0.01968363 | S32: #N/A | T32: #N/A | U32: #N/A | V32: #N/A | W32: #N/A | X32: #N/A | Y32: #N/A | Z32: #N/A | AA32: #N/A | AB32: 0.051101099 | AC32: 0.061086082 | AD32: 0.049825131 | AE32: 0.056172249 | AF32: 0.05089006 | AG32: 0.048246386 | AH32: 0.04619742 | AI32: 0.04166432 | AJ32: 0.0383855 | AK32: 0.032849758 | AL32: 0.023319004 | AM32: 0.021351076 | AN32: 0.025374631 | AO32: 0.024132977 | AP32: 0.024492656 | AQ32: 0.020624964 | AR32: 0.019821757 | AS32: 0.025250649 | AT32: 0.021322485 | AU32: 0.018156005 | AV32: 0.020993623
A33: DKK | B33: =FORECAST(B$1,INDEX(S33:BE33, 1, COUNTA(S33:BE33)-4):INDEX(S33:BE33, 1, COUNTA(S33:BE33)),INDEX($S$1:$BE$1, 1, COUNTA($S$1:$BE$1)-4):INDEX($S$1:$BE$1, 1, COUNTA($S$1:$BE$1))) -> 0.26203966 | S33: 0.24850043 | T33: 0.22061657 | U33: 0.28059464 | V33: 0.25843939 | W33: 0.27279889 | X33: 0.28045301 | Y33: 0.28188923 | Z33: 0.27138511 | AA33: 0.25595696 | AB33: 0.23469257 | AC33: 0.28122938 | AD33: 0.23403106 | AE33: 0.27958206 | AF33: 0.2994656 | AG33: 0.25747931 | AH33: 0.24857955 | AI33: 0.21906175 | AJ33: 0.20570481 | AK33: 0.21329303 | AL33: 0.19323253 | AM33: 0.22154525 | AN33: 0.20464644 | AO33: 0.22828601 | AP33: 0.23456053 | AQ33: 0.23970491 | AR33: 0.22471017 | AS33: 0.21741504 | AT33: 0.23141764 | AU33: 0.24028952 | AV33: 0.25904617
A34: PKR | B34: =FORECAST(B$1,INDEX(S34:BE34, 1, COUNTA(S34:BE34)-4):INDEX(S34:BE34, 1, COUNTA(S34:BE34)),INDEX($S$1:$BE$1, 1, COUNTA($S$1:$BE$1)-4):INDEX($S$1:$BE$1, 1, COUNTA($S$1:$BE$1))) -> 0.0047151148 | S34: 0.041645244 | T34: 0.036480411 | U34: 0.042115742 | V34: 0.036476549 | W34: 0.04092507 | X34: 0.038762041 | Y34: 0.03598629 | Z34: 0.034140347 | AA34: 0.026692565 | AB34: 0.024609756 | AC34: 0.02722461 | AD34: 0.021130781 | AE34: 0.019103411 | AF34: 0.019488212 | AG34: 0.016748888 | AH34: 0.015289852 | AI34: 0.013473753 | AJ34: 0.01212735 | AK34: 0.01174308 | AL34: 0.013161514 | AM34: 0.013842505 | AN34: 0.013614209 | AO34: 0.011928886 | AP34: 0.010212618 | AQ34: 0.0089262542 | AR34: 0.008441056 | AS34: 0.0065670918 | AT34: 0.0057055713 | AU34: 0.005958152 | AV34: 0.0057850702
A35: ILS | B35: =FORECAST(B$1,INDEX(S35:BE35, 1, COUNTA(S35:BE35)-4):INDEX(S35:BE35, 1, COUNTA(S35:BE35)),INDEX($S$1:$BE$1, 1, COUNTA($S$1:$BE$1)-4):INDEX($S$1:$BE$1, 1, COUNTA($S$1:$BE$1))) -> 0.47699379 | S35: 0.45565553 | T35: 0.42057375 | U35: 0.52999735 | V35: 0.46054892 | W35: 0.52298164 | X35: 0.59141127 | Y35: 0.4385411 | Z35: 0.43065372 | AA35: 0.34598951 | AB35: 0.31805436 | AC35: 0.37060086 | AD35: 0.30416582 | AE35: 0.40182299 | AF35: 0.41060864 | AG35: 0.38260319 | AH35: 0.37614095 | AI35: 0.32928053 | AJ35: 0.32780057 | AK35: 0.33173403 | AL35: 0.33797406 | AM35: 0.38383534 | AN35: 0.39315565 | AO35: 0.39506031 | AP35: 0.45994166 | AQ35: 0.44093824 | AR35: 0.44778854 | AS35: 0.46852884 | AT35: 0.44304896 | AU35: 0.44825838 | AV35: 0.48777888
A36: PLN | B36: =FORECAST(B$1,INDEX(S36:BE36, 1, COUNTA(S36:BE36)-4):INDEX(S36:BE36, 1, COUNTA(S36:BE36)),INDEX($S$1:$BE$1, 1, COUNTA($S$1:$BE$1)-4):INDEX($S$1:$BE$1, 1, COUNTA($S$1:$BE$1))) -> 0.46727406 | S36: #N/A | T36: #N/A | U36: #N/A | V36: #N/A | W36: #N/A | X36: #N/A | Y36: 0.51400192 | Z36: 0.50216419 | AA36: 0.42119369 | AB36: 0.43550932 | AC36: 0.51460072 | AD36: 0.46427832 | AE36: 0.62184292 | AF36: 0.51069208 | AG36: 0.49916872 | AH36: 0.46074547 | AI36: 0.39251907 | AJ36: 0.36700479 | AK36: 0.38134146 | AL36: 0.35538873 | AM36: 0.38856399 | AN36: 0.35936454 | AO36: 0.40322647 | AP36: 0.3993854 | AQ36: 0.40554158 | AR36: 0.36511962 | AS36: 0.34322447 | AT36: 0.36677501 | AU36: 0.41980645 | AV36: 0.45548266
A37: QAR | B37: =FORECAST(B$1,INDEX(S37:BE37, 1, COUNTA(S37:BE37)-4):INDEX(S37:BE37, 1, COUNTA(S37:BE37)),INDEX($S$1:$BE$1, 1, COUNTA($S$1:$BE$1)-4):INDEX($S$1:$BE$1, 1, COUNTA($S$1:$BE$1))) -> 0.47514122 | S37: #N/A | T37: #N/A | U37: #N/A | V37: 0.51564759 | W37: 0.58584865 | X37: 0.67828788 | Y37: 0.58358246 | Z37: 0.56321742 | AA37: 0.42475779 | AB37: 0.40196442 | AC37: 0.45299299 | AD37: 0.35110595 | AE37: 0.3607391 | AF37: 0.4367586 | AG37: 0.38780257 | AH37: 0.35819778 | AI37: 0.3354794 | AJ37: 0.32793328 | AK37: 0.31672168 | AL37: 0.3682821 | AM37: 0.3982603 | AN37: 0.39203808 | AO37: 0.37929401 | AP37: 0.43999508 | AQ37: 0.41243028 | AR37: 0.39589524 | AS37: 0.43305791 | AT37: 0.44142649 | AU37: 0.45528907 | AV37: 0.45109409
A38: XAU | B38: =FORECAST(B$1,INDEX(S38:BE38, 1, COUNTA(S38:BE38)-4):INDEX(S38:BE38, 1, COUNTA(S38:BE38)),INDEX($S$1:$BE$1, 1, COUNTA($S$1:$BE$1)-4):INDEX($S$1:$BE$1, 1, COUNTA($S$1:$BE$1))) -> 5584.9573 | S38: #N/A | T38: 489.69171 | U38: 572.84311 | V38: 493.56601 | W38: 615.45842 | X38: 668.14984 | Y38: 683.33201 | Z38: 643.71124 | AA38: 615.50273 | AB38: 625.16127 | AC38: 1007.6872 | AD38: 839.91313 | AE38: 1238.091 | AF38: 1477.2845 | AG38: 1590.8765 | AH38: 1861.6634 | AI38: 2038.4864 | AJ38: 1909.3915 | AK38: 1477.2962 | AL38: 1611.422 | AM38: 1760.2708 | AN38: 1783.0277 | AO38: 1829.6938 | AP38: 2377.9566 | AQ38: 3070.0426 | AR38: 2539.0845 | AS38: 2787.4036 | AT38: 3059.9015 | AU38: 3892.059 | AV38: 5401.652
A39: OMR | B39: =FORECAST(B$1,INDEX(S39:BE39, 1, COUNTA(S39:BE39)-4):INDEX(S39:BE39, 1, COUNTA(S39:BE39)),INDEX($S$1:$BE$1, 1, COUNTA($S$1:$BE$1)-4):INDEX($S$1:$BE$1, 1, COUNTA($S$1:$BE$1))) -> 4.4924475 | S39: #N/A | T39: #N/A | U39: #N/A | V39: 4.9339332 | W39: 5.5410503 | X39: 6.4150222 | Y39: 5.5318035 | Z39: 5.325149 | AA39: 4.0149411 | AB39: 3.8006235 | AC39: 4.2611519 | AD39: 3.3193688 | AE39: 3.4113235 | AF39: 4.1303812 | AG39: 3.6668776 | AH39: 3.3875529 | AI39: 3.1729815 | AJ39: 3.1015429 | AK39: 2.9966366 | AL39: 3.4827435 | AM39: 3.7657106 | AN39: 3.7045518 | AO39: 3.5907157 | AP39: 4.165363 | AQ39: 3.9044115 | AR39: 3.7478769 | AS39: 4.09969 | AT39: 4.1736305 | AU39: 4.3057092 | AV39: 4.2674832
A40: COP | B40: =FORECAST(B$1,INDEX(S40:BE40, 1, COUNTA(S40:BE40)-4):INDEX(S40:BE40, 1, COUNTA(S40:BE40)),INDEX($S$1:$BE$1, 1, COUNTA($S$1:$BE$1)-4):INDEX($S$1:$BE$1, 1, COUNTA($S$1:$BE$1))) -> 0.00041601814 | S40: #N/A | T40: #N/A | U40: #N/A | V40: 0.0010735154 | W40: 0.001037565 | X40: 0.0010927793 | Y40: 0.0007551835 | Z40: 0.00086741249 | AA40: 0.00057655543 | AB40: 0.00062948165 | AC40: 0.0006257485 | AD40: 0.00064691959 | AE40: 0.00072261873 | AF40: 0.00076033377 | AG40: 0.0007373009 | AH40: 0.0006973415 | AI40: 0.0006824569 | AJ40: 0.0006554844 | AK40: 0.0005867056 | AL40: 0.0005203316 | AM40: 0.0004804412 | AN40: 0.0004966771 | AO40: 0.0004948828 | AP40: 0.0004586073 | AQ40: 0.0003965943 | AR40: 0.0003810534 | AS40: 0.00037244087 | AT40: 0.00033933658 | AU40: 0.00042839807 | AV40: 0.00040452155
A41: CLP | B41: =FORECAST(B$1,INDEX(S41:BE41, 1, COUNTA(S41:BE41)-4):INDEX(S41:BE41, 1, COUNTA(S41:BE41)),INDEX($S$1:$BE$1, 1, COUNTA($S$1:$BE$1)-4):INDEX($S$1:$BE$1, 1, COUNTA($S$1:$BE$1))) -> 0.0018184528 | S41: 0.0035507712 | T41: 0.0035495611 | U41: 0.0041717547 | V41: 0.0036229848 | W41: 0.0039713097 | X41: 0.0039084164 | Y41: 0.0028497199 | Z41: 0.0029395925 | AA41: 0.0024373851 | AB41: 0.0025268602 | AC41: 0.0030210932 | AD41: 0.00242227 | AE41: 0.0025354431 | AF41: 0.0029313144 | AG41: 0.0027077023 | AH41: 0.0027388498 | AI41: 0.0025187585 | AJ41: 0.0025282003 | AK41: 0.0020938829 | AL41: 0.0021713329 | AM41: 0.0021682548 | AN41: 0.0021637864 | AO41: 0.0022864469 | AP41: 0.0021980547 | AQ41: 0.0019334024 | AR41: 0.0017943333 | AS41: 0.0017764842 | AT41: 0.0019940459 | AU41: 0.0018109243 | AV41: 0.0017619541
A42: TWD | B42: =FORECAST(B$1,INDEX(S42:BE42, 1, COUNTA(S42:BE42)-4):INDEX(S42:BE42, 1, COUNTA(S42:BE42)),INDEX($S$1:$BE$1, 1, COUNTA($S$1:$BE$1)-4):INDEX($S$1:$BE$1, 1, COUNTA($S$1:$BE$1))) -> 0.055164969 | S42: 0.05323479 | T42: 0.052997217 | U42: 0.056742766 | V42: 0.058093036 | W42: 0.069249632 | X42: 0.071840036 | Y42: 0.060952197 | Z42: 0.061296764 | AA42: 0.045930879 | AB42: 0.046240519 | AC42: 0.050676448 | AD42: 0.038886039 | AE42: 0.043233904 | AF42: 0.048168312 | AG42: 0.044467475 | AH42: 0.044591028 | AI42: 0.041400974 | AJ42: 0.039947231 | AK42: 0.038041251 | AL42: 0.042903436 | AM42: 0.044932569 | AN42: 0.047063959 | AO42: 0.047571311 | AP42: 0.05153067 | AQ42: 0.051141662 | AR42: 0.051809764 | AS42: 0.052361829 | AT42: 0.052618021 | AU42: 0.051224328 | AV42: 0.056236612
A43: ARS | B43: =FORECAST(B$1,INDEX(S43:BE43, 1, COUNTA(S43:BE43)-4):INDEX(S43:BE43, 1, COUNTA(S43:BE43)),INDEX($S$1:$BE$1, 1, COUNTA($S$1:$BE$1)-4):INDEX($S$1:$BE$1, 1, COUNTA($S$1:$BE$1))) -> -0.0033970945 | S43: #N/A | T43: #N/A | U43: #N/A | V43: #N/A | W43: #N/A | X43: #N/A | Y43: 0.56950989 | Z43: 0.55330023 | AA43: 0.52372405 | AB43: 0.50662906 | AC43: 0.53224655 | AD43: 0.41341283 | AE43: 0.43467883 | AF43: 0.41881436 | AG43: 0.36408747 | AH43: 0.32175068 | AI43: 0.27909479 | AJ43: 0.23310037 | AK43: 0.14413064 | AL43: 0.15191895 | AM43: 0.098836074 | AN43: 0.092797001 | AO43: 0.068653793 | AP43: 0.027759652 | AQ43: 0.020671441 | AR43: 0.014589251 | AS43: 0.011947468 | AT43: 0.0079735307 | AU43: 0.0018721602 | AV43: 0.0013782079
A44: CZK | B44: =FORECAST(B$1,INDEX(S44:BE44, 1, COUNTA(S44:BE44)-4):INDEX(S44:BE44, 1, COUNTA(S44:BE44)),INDEX($S$1:$BE$1, 1, COUNTA($S$1:$BE$1)-4):INDEX($S$1:$BE$1, 1, COUNTA($S$1:$BE$1))) -> 0.080173027 | S44: #N/A | T44: #N/A | U44: 0.059729228 | V44: #N/A | W44: 0.057137395 | X44: 0.061791532 | Y44: 0.068917278 | Z44: 0.068613064 | AA44: 0.059896813 | AB44: 0.058300458 | AC44: 0.073433444 | AD44: 0.060531351 | AE44: 0.087514415 | AF44: 0.08622076 | AG44: 0.07556236 | AH44: 0.075765947 | AI44: 0.065833039 | AJ44: 0.059574112 | AK44: 0.057969665 | AL44: 0.052376103 | AM44: 0.061051225 | AN44: 0.056246424 | AO44: 0.067108768 | AP44: 0.067895689 | AQ44: 0.068463974 | AR44: 0.066018668 | AS44: 0.06571066 | AT44: 0.072342443 | AU44: 0.072280454 | AV44: 0.078178555
A45: VND | B45: =FORECAST(B$1,INDEX(S45:BE45, 1, COUNTA(S45:BE45)-4):INDEX(S45:BE45, 1, COUNTA(S45:BE45)),INDEX($S$1:$BE$1, 1, COUNTA($S$1:$BE$1)-4):INDEX($S$1:$BE$1, 1, COUNTA($S$1:$BE$1))) -> 6.4370736e-05 | S45: #N/A | T45: #N/A | U45: #N/A | V45: 0.00013533237 | W45: 0.00015227797 | X45: 0.00016628339 | Y45: 0.0001384874 | Z45: 0.00013501906 | AA45: 9.80902e-05 | AB45: 9.2335122e-05 | AC45: 0.00010311096 | AD45: 7.9230605e-05 | AE45: 7.7886407e-05 | AF45: 8.9339218e-05 | AG45: 7.43122e-05 | AH45: 6.23805e-05 | AI45: 5.86742e-05 | AJ45: 5.70464e-05 | AK45: 5.47156e-05 | AL45: 6.2195e-05 | AM45: 6.5044e-05 | AN45: 6.27588e-05 | AO45: 6.05366e-05 | AP45: 6.90386e-05 | AQ45: 6.45075e-05 | AR45: 6.34172e-05 | AS45: 6.790872e-05 | AT45: 6.8459535e-05 | AU45: 6.5096408e-05 | AV45: 6.2860471e-05
A46: MAD | B46: =FORECAST(B$1,INDEX(S46:BE46, 1, COUNTA(S46:BE46)-4):INDEX(S46:BE46, 1, COUNTA(S46:BE46)),INDEX($S$1:$BE$1, 1, COUNTA($S$1:$BE$1)-4):INDEX($S$1:$BE$1, 1, COUNTA($S$1:$BE$1))) -> 0.18064528 | S46: #N/A | T46: #N/A | U46: #N/A | V46: 0.18642683 | W46: 0.20555251 | X46: 0.20647935 | Y46: 0.19956631 | Z46: 0.19229419 | AA46: 0.17313967 | AB46: 0.16082597 | AC46: 0.18930067 | AD46: 0.15557544 | AE46: 0.18144757 | AF46: 0.19844667 | AG46: 0.17114315 | AH46: 0.1641108 | AI46: 0.14617311 | AJ46: 0.13810544 | AK46: 0.14168757 | AL46: 0.13479045 | AM46: 0.15044824 | AN46: 0.14214089 | AO46: 0.15002704 | AP46: 0.16519433 | AQ46: 0.16254387 | AR46: 0.15910023 | AS46: 0.15321195 | AT46: 0.15506075 | AU46: 0.16532886 | AV46: 0.18241249
A47: JOD | B47: =FORECAST(B$1,INDEX(S47:BE47, 1, COUNTA(S47:BE47)-4):INDEX(S47:BE47, 1, COUNTA(S47:BE47)),INDEX($S$1:$BE$1, 1, COUNTA($S$1:$BE$1)-4):INDEX($S$1:$BE$1, 1, COUNTA($S$1:$BE$1))) -> 2.439371 | S47: #N/A | T47: 2.0823164 | U47: 2.7515264 | V47: 2.6481563 | W47: 3.0286877 | X47: 3.4737508 | Y47: 2.9965612 | Z47: 2.907985 | AA47: 2.1815061 | AB47: 2.0648507 | AC47: 2.3156669 | AD47: 1.803591 | AE47: 1.8550276 | AF47: 2.246099 | AG47: 1.9886354 | AH47: 1.8371509 | AI47: 1.7193495 | AJ47: 1.6851651 | AK47: 1.6278391 | AL47: 1.8919487 | AM47: 2.0455259 | AN47: 2.0108119 | AO47: 1.9472922 | AP47: 2.258931 | AQ47: 2.1174136 | AR47: 2.0325228 | AS47: 2.2233157 | AT47: 2.2662798 | AU47: 2.3374503 | AV47: 2.3159133
A48: BHD | B48: =FORECAST(B$1,INDEX(S48:BE48, 1, COUNTA(S48:BE48)-4):INDEX(S48:BE48, 1, COUNTA(S48:BE48)),INDEX($S$1:$BE$1, 1, COUNTA($S$1:$BE$1)-4):INDEX($S$1:$BE$1, 1, COUNTA($S$1:$BE$1))) -> 4.5997714 | S48: #N/A | T48: #N/A | U48: #N/A | V48: 4.9745148 | W48: 5.6564429 | X48: 6.5494484 | Y48: 5.6412718 | Z48: 5.441675 | AA48: 4.1007755 | AB48: 3.8812841 | AC48: 4.3746 | AD48: 3.3913864 | AE48: 3.4836199 | AF48: 4.2203699 | AG48: 3.7449265 | AH48: 3.4592901 | AI48: 3.2400977 | AJ48: 3.1665323 | AK48: 3.0586195 | AL48: 3.5562428 | AM48: 3.8468756 | AN48: 3.7863392 | AO48: 3.6718888 | AP48: 4.2595268 | AQ48: 3.9926762 | AR48: 3.8326029 | AS48: 4.1923692 | AT48: 4.2733841 | AU48: 4.4075857 | AV48: 4.3669747
A49: XOF | B49: =FORECAST(B$1,INDEX(S49:BE49, 1, COUNTA(S49:BE49)-4):INDEX(S49:BE49, 1, COUNTA(S49:BE49)),INDEX($S$1:$BE$1, 1, COUNTA($S$1:$BE$1)-4):INDEX($S$1:$BE$1, 1, COUNTA($S$1:$BE$1))) -> 0.0029832138 | S49: #N/A | T49: #N/A | U49: #N/A | V49: 0.0029203057 | W49: 0.0030970516 | X49: #N/A | Y49: 0.0031907415 | Z49: 0.0030722924 | AA49: 0.0029007697 | AB49: 0.0026670079 | AC49: 0.0031960985 | AD49: 0.0026547094 | AE49: 0.0031765841 | AF49: 0.0033978237 | AG49: 0.0029228064 | AH49: 0.0028257387 | AI49: 0.0024850733 | AJ49: 0.0023399536 | AK49: 0.0024272975 | AL49: 0.0022008199 | AM49: 0.0025157204 | AN49: 0.0023186863 | AO49: 0.00259331 | AP49: 0.0026694834 | AQ49: 0.0027224886 | AR49: 0.0025476447 | AS49: 0.0024674639 | AT49: 0.0026265867 | AU49: 0.0027331454 | AV49: 0.0029464101
A50: LKR | B50: =FORECAST(B$1,INDEX(S50:BE50, 1, COUNTA(S50:BE50)-4):INDEX(S50:BE50, 1, COUNTA(S50:BE50)),INDEX($S$1:$BE$1, 1, COUNTA($S$1:$BE$1)-4):INDEX($S$1:$BE$1, 1, COUNTA($S$1:$BE$1))) -> 0.0047569308 | S50: #N/A | T50: #N/A | U50: #N/A | V50: 0.026295857 | W50: 0.027127178 | X50: 0.027200683 | Y50: 0.022074767 | Z50: 0.021311117 | AA50: 0.015090981 | AB50: 0.014667168 | AC50: 0.015780033 | AD50: 0.011473089 | AE50: 0.012188952 | AF50: 0.013832969 | AG50: 0.012369668 | AH50: 0.011823579 | AI50: 0.0095236451 | AJ50: 0.0094457282 | AK50: 0.0088248312 | AL50: 0.010078481 | AM50: 0.0099177288 | AN50: 0.009375091 | AO50: 0.0088709488 | AP50: 0.0088057318 | AQ50: 0.0080965471 | AR50: 0.0072157525 | AS50: 0.0043463403 | AT50: 0.004739317 | AU50: 0.0054969763 | AV50: 0.0054768928
A51: UAH | B51: =FORECAST(B$1,INDEX(S51:BE51, 1, COUNTA(S51:BE51)-4):INDEX(S51:BE51, 1, COUNTA(S51:BE51)),INDEX($S$1:$BE$1, 1, COUNTA($S$1:$BE$1)-4):INDEX($S$1:$BE$1, 1, COUNTA($S$1:$BE$1))) -> 0.035161394 | S51: #N/A | T51: #N/A | U51: #N/A | V51: 0.47743688 | W51: 0.3921064 | X51: 0.45954626 | Y51: 0.39864837 | Z51: 0.38507315 | AA51: 0.29058712 | AB51: 0.28971287 | AC51: 0.32965962 | AD51: 0.2543263 | AE51: 0.28501417 | AF51: 0.2088297 | AG51: 0.17827414 | AH51: 0.16355828 | AI51: 0.15207243 | AJ51: 0.14669361 | AK51: 0.10482644 | AL51: 0.057216989 | AM51: 0.055589133 | AN51: 0.05269444 | AO51: 0.05236957 | AP51: 0.065409632 | AQ51: 0.054176308 | AR51: 0.054075209 | AS51: 0.04279176 | AT51: 0.043634171 | AU51: 0.041796741 | AV51: 0.039306811
A52: NGN | B52: =FORECAST(B$1,INDEX(S52:BE52, 1, COUNTA(S52:BE52)-4):INDEX(S52:BE52, 1, COUNTA(S52:BE52)),INDEX($S$1:$BE$1, 1, COUNTA($S$1:$BE$1)-4):INDEX($S$1:$BE$1, 1, COUNTA($S$1:$BE$1))) -> 0.000325873 | S52: #N/A | T52: #N/A | U52: #N/A | V52: 0.019557818 | W52: 0.020345383 | X52: 0.021987017 | Y52: 0.016860295 | Z52: 0.017170263 | AA52: 0.011609171 | AB52: 0.011189247 | AC52: 0.012843667 | AD52: 0.010033679 | AE52: 0.011151902 | AF52: 0.010757935 | AG52: 0.0094103285 | AH52: 0.0084562763 | AI52: 0.0077487973 | AJ52: 0.0075291804 | AK52: 0.0069924545 | AL52: 0.0067360139 | AM52: 0.0072858588 | AN52: 0.0044959051 | AO52: 0.0038404178 | AP52: 0.0044197162 | AQ52: 0.0038857415 | AR52: 0.0035072792 | AS52: 0.0037876468 | AT52: 0.0034892063 | AU52: 0.0011083515 | AV52: 0.0010694154
A53: TND | B53: =FORECAST(B$1,INDEX(S53:BE53, 1, COUNTA(S53:BE53)-4):INDEX(S53:BE53, 1, COUNTA(S53:BE53)),INDEX($S$1:$BE$1, 1, COUNTA($S$1:$BE$1)-4):INDEX($S$1:$BE$1, 1, COUNTA($S$1:$BE$1))) -> 0.56784111 | S53: #N/A | T53: #N/A | U53: #N/A | V53: 1.5400277 | W53: 1.603155 | X53: 1.6410621 | Y53: 1.5330471 | Z53: 1.4783896 | AA53: 1.2231424 | AB53: 1.1147048 | AC53: 1.2442363 | AD53: 0.99089397 | AE53: 1.1331834 | AF53: 1.1824211 | AG53: 1.0088826 | AH53: 0.94104118 | AI53: 0.8182169 | AJ53: 0.74831654 | AK53: 0.73046459 | AL53: 0.68426191 | AM53: 0.72412133 | AN53: 0.60989099 | AO53: 0.57621264 | AP53: 0.55923325 | AQ53: 0.55438483 | AR53: 0.51113848 | AS53: 0.50618635 | AT53: 0.51544485 | AU53: 0.5306169 | AV53: 0.56814714
A54: UGX | B54: =FORECAST(B$1,INDEX(S54:BE54, 1, COUNTA(S54:BE54)-4):INDEX(S54:BE54, 1, COUNTA(S54:BE54)),INDEX($S$1:$BE$1, 1, COUNTA($S$1:$BE$1)-4):INDEX($S$1:$BE$1, 1, COUNTA($S$1:$BE$1))) -> 0.00046817331 | S54: #N/A | T54: #N/A | U54: #N/A | V54: 0.0012995284 | W54: 0.0013736607 | X54: 0.0014481771 | Y54: 0.0011835082 | Z54: 0.0011498202 | AA54: 0.00086240904 | AB54: 0.00084422966 | AC54: 0.00088206989 | AD54: 0.00079575944 | AE54: 0.00081071577 | AF54: 0.00077196024 | AG54: 0.0006830824 | AH54: 0.0005464505 | AI54: 0.0004857248 | AJ54: 0.0004602568 | AK54: 0.0004532045 | AL54: 0.0004484446 | AM54: 0.0004306413 | AN54: 0.0003937049 | AO54: 0.0003743085 | AP54: 0.0004357476 | AQ54: 0.0004067798 | AR54: 0.0004058303 | AS54: 0.00040752606 | AT54: 0.00043004278 | AU54: 0.00043964645 | AV54: 0.00045678282
A55: RON | B55: =FORECAST(B$1,INDEX(S55:BE55, 1, COUNTA(S55:BE55)-4):INDEX(S55:BE55, 1, COUNTA(S55:BE55)),INDEX($S$1:$BE$1, 1, COUNTA($S$1:$BE$1)-4):INDEX($S$1:$BE$1, 1, COUNTA($S$1:$BE$1))) -> 0.38660324 | S55: #N/A | T55: #N/A | U55: #N/A | V55: #N/A | W55: #N/A | X55: #N/A | Y55: #N/A | Z55: #N/A | AA55: #N/A | AB55: #N/A | AC55: #N/A | AD55: 0.55773311 | AE55: 0.57324437 | AF55: 0.53078625 | AG55: 0.4641457 | AH55: 0.4482321 | AI55: 0.37222276 | AJ55: 0.34708122 | AK55: 0.35676625 | AL55: 0.32691948 | AM55: 0.36938724 | AN55: 0.33535766 | AO55: 0.36531923 | AP55: 0.36862141 | AQ55: 0.36942879 | AR55: 0.33790058 | AS55: 0.32848945 | AT55: 0.34997713 | AU55: 0.36029108 | AV55: 0.38058932
A56: BDT | B56: =FORECAST(B$1,INDEX(S56:BE56, 1, COUNTA(S56:BE56)-4):INDEX(S56:BE56, 1, COUNTA(S56:BE56)),INDEX($S$1:$BE$1, 1, COUNTA($S$1:$BE$1)-4):INDEX($S$1:$BE$1, 1, COUNTA($S$1:$BE$1))) -> 0.01244377 | S56: #N/A | T56: #N/A | U56: #N/A | V56: 0.03901154 | W56: 0.041931095 | X56: 0.043016412 | Y56: 0.036881895 | Z56: 0.036024063 | AA56: 0.026195076 | AB56: 0.023131225 | AC56: 0.023642364 | AD56: 0.018575431 | AE56: 0.019173132 | AF56: 0.023113925 | AG56: 0.020418383 | AH56: 0.017954265 | AI56: 0.014941265 | AJ56: 0.015276199 | AK56: 0.014852944 | AL56: 0.017217859 | AM56: 0.018514241 | AN56: 0.017800846 | AO56: 0.016628062 | AP56: 0.018969929 | AQ56: 0.017729569 | AR56: 0.016841298 | AS56: 0.016633771 | AT56: 0.015238884 | AU56: 0.014165996 | AV56: 0.013391114
A57: PEN | B57: =FORECAST(B$1,INDEX(S57:BE57, 1, COUNTA(S57:BE57)-4):INDEX(S57:BE57, 1, COUNTA(S57:BE57)),INDEX($S$1:$BE$1, 1, COUNTA($S$1:$BE$1)-4):INDEX($S$1:$BE$1, 1, COUNTA($S$1:$BE$1))) -> 0.49778268 | S57: #N/A | T57: #N/A | U57: #N/A | V57: 0.56353911 | W57: 0.62896642 | X57: 0.71362326 | Y57: 0.60181222 | Z57: 0.59252296 | AA57: 0.44574829 | AB57: 0.45003076 | AC57: 0.50549197 | AD57: 0.40340583 | AE57: 0.44377751 | AF57: 0.52396645 | AG57: 0.49698388 | AH57: 0.46535043 | AI57: 0.45804193 | AJ57: 0.46080407 | AK57: 0.41053759 | AL57: 0.43370227 | AM57: 0.43538037 | AN57: 0.43941815 | AO57: 0.42487197 | AP57: 0.47125642 | AQ57: 0.42299632 | AR57: 0.34881845 | AS57: 0.40588362 | AT57: 0.42413489 | AU57: 0.44479044 | AV57: 0.46334528
A58: GEL | B58: =FORECAST(B$1,INDEX(S58:BE58, 1, COUNTA(S58:BE58)-4):INDEX(S58:BE58, 1, COUNTA(S58:BE58)),INDEX($S$1:$BE$1, 1, COUNTA($S$1:$BE$1)-4):INDEX($S$1:$BE$1, 1, COUNTA($S$1:$BE$1))) -> 0.67298401 | S58: #N/A | T58: #N/A | U58: #N/A | V58: #N/A | W58: #N/A | X58: 1.1986126 | Y58: 0.97442038 | Z58: 0.92850065 | AA58: 0.80499096 | AB58: 0.8076902 | AC58: 0.90024418 | AD58: 0.76572178 | AE58: 0.9265323 | AF58: 0.96174056 | AG58: 0.80977932 | AH58: 0.76750648 | AI58: 0.73612404 | AJ58: 0.72133432 | AK58: 0.66096478 | AL58: 0.59783083 | AM58: 0.63055833 | AN58: 0.58502043 | AO58: 0.56902698 | AP58: 0.53745693 | AQ58: 0.48867814 | AR58: 0.4589608 | AS58: 0.57579923 | AT58: 0.62205029 | AU58: 0.61392046 | AV58: 0.60347246
A59: XAF | B59: =FORECAST(B$1,INDEX(S59:BE59, 1, COUNTA(S59:BE59)-4):INDEX(S59:BE59, 1, COUNTA(S59:BE59)),INDEX($S$1:$BE$1, 1, COUNTA($S$1:$BE$1)-4):INDEX($S$1:$BE$1, 1, COUNTA($S$1:$BE$1))) -> 0.0029832138 | S59: #N/A | T59: #N/A | U59: #N/A | V59: 0.0029203057 | W59: 0.0030970516 | X59: 0.003182991 | Y59: 0.0031907415 | Z59: 0.0030722924 | AA59: 0.0029007697 | AB59: 0.0026670079 | AC59: 0.0031960985 | AD59: 0.0026547094 | AE59: 0.0031765841 | AF59: 0.0033978237 | AG59: 0.0029228064 | AH59: 0.0028257387 | AI59: 0.0024850733 | AJ59: 0.0023399536 | AK59: 0.0024272975 | AL59: 0.0022008199 | AM59: 0.0025157204 | AN59: 0.0023186863 | AO59: 0.00259331 | AP59: 0.0026694834 | AQ59: 0.0027224886 | AR59: 0.0025476447 | AS59: 0.0024674639 | AT59: 0.0026265867 | AU59: 0.0027331454 | AV59: 0.0029464101
A60: FJD | B60: =FORECAST(B$1,INDEX(S60:BE60, 1, COUNTA(S60:BE60)-4):INDEX(S60:BE60, 1, COUNTA(S60:BE60)),INDEX($S$1:$BE$1, 1, COUNTA($S$1:$BE$1)-4):INDEX($S$1:$BE$1, 1, COUNTA($S$1:$BE$1))) -> 0.75783346 | S60: #N/A | T60: 1.0437808 | U60: 0.96814441 | V60: 0.95755599 | W60: 1.0234705 | X60: 1.0740537 | Y60: 0.99588577 | Z60: 0.98280413 | AA60: 0.85875773 | AB60: 0.85881033 | AC60: 0.93431093 | AD60: 0.80627719 | AE60: 0.87758684 | AF60: 0.77697664 | AG60: 0.73375096 | AH60: 0.71805964 | AI60: 0.68531639 | AJ60: 0.66887859 | AK60: 0.63055652 | AL60: 0.65072435 | AM60: 0.69825772 | AN60: 0.68454615 | AO60: 0.67677952 | AP60: 0.73035413 | AQ60: 0.70479252 | AR60: 0.6796194 | AS60: 0.72319517 | AT60: 0.72465208 | AU60: 0.73861775 | AV60: 0.73470181
A61: VEF | B61: =FORECAST(B$1,INDEX(S61:BE61, 1, COUNTA(S61:BE61)-4):INDEX(S61:BE61, 1, COUNTA(S61:BE61)),INDEX($S$1:$BE$1, 1, COUNTA($S$1:$BE$1)-4):INDEX($S$1:$BE$1, 1, COUNTA($S$1:$BE$1))) -> #N/A | S61: #N/A | T61: #N/A | U61: #N/A | V61: #N/A | W61: #N/A | X61: #N/A | Y61: #N/A | Z61: #N/A | AA61: #N/A | AB61: #N/A | AC61: #N/A | AD61: #N/A | AE61: 0.611633 | AF61: 0.73964562 | AG61: 0.3283561 | AH61: 0.30334354 | AI61: 0.28409252 | AJ61: 0.18969779 | AK61: 0.18343835 | AL61: 0.2112354 | AM61: 0.22838809 | AN61: 0.14295943 | AO61: 0.13823581 | AP61: 0.16035866 | AQ61: 0.15031251 | AR61: 0 | AS61: 2.7953444e-06 | AT61: 6.6777526e-07 | AU61: 4.5321862e-07 | AV61: #N/A
A62: BYN | B62: =FORECAST(B$1,INDEX(S62:BE62, 1, COUNTA(S62:BE62)-4):INDEX(S62:BE62, 1, COUNTA(S62:BE62)),INDEX($S$1:$BE$1, 1, COUNTA($S$1:$BE$1)-4):INDEX($S$1:$BE$1, 1, COUNTA($S$1:$BE$1))) -> 0.49013003 | S62: #N/A | T62: #N/A | U62: #N/A | V62: #N/A | W62: #N/A | X62: #N/A | Y62: #N/A | Z62: #N/A | AA62: #N/A | AB62: #N/A | AC62: #N/A | AD62: #N/A | AE62: #N/A | AF62: #N/A | AG62: #N/A | AH62: #N/A | AI62: #N/A | AJ62: #N/A | AK62: #N/A | AL62: #N/A | AM62: #N/A | AN62: 0.75934623 | AO62: 0.70818259 | AP62: 0.76816495 | AQ62: 0.61642392 | AR62: 0.57445573 | AS62: 0.62430146 | AT62: 0.63926478 | AU62: 0.50678378 | AV62: 0.50137203
A63: HRK | B63: =FORECAST(B$1,INDEX(S63:BE63, 1, COUNTA(S63:BE63)-4):INDEX(S63:BE63, 1, COUNTA(S63:BE63)),INDEX($S$1:$BE$1, 1, COUNTA($S$1:$BE$1)-4):INDEX($S$1:$BE$1, 1, COUNTA($S$1:$BE$1))) -> #N/A | S63: #N/A | T63: #N/A | U63: #N/A | V63: 0.25436096 | W63: 0.26838645 | X63: 0.28632381 | Y63: 0.28446668 | Z63: 0.27693225 | AA63: 0.25529819 | AB63: 0.23911516 | AC63: 0.28967301 | AD63: 0.23853669 | AE63: 0.28813501 | AF63: 0.30633492 | AG63: 0.26388639 | AH63: 0.25132955 | AI63: 0.21770707 | AJ63: 0.20173393 | AK63: 0.20815141 | AL63: 0.18894943 | AM63: 0.21983648 | AN63: 0.20431347 | AO63: 0.22894503 | AP63: 0.23618824 | AQ63: 0.23914992 | AR63: 0.22288399 | AS63: 0.21529614 | AT63: #N/A | AU63: #N/A | AV63: #N/A
A64: UZS | B64: =FORECAST(B$1,INDEX(S64:BE64, 1, COUNTA(S64:BE64)-4):INDEX(S64:BE64, 1, COUNTA(S64:BE64)),INDEX($S$1:$BE$1, 1, COUNTA($S$1:$BE$1)-4):INDEX($S$1:$BE$1, 1, COUNTA($S$1:$BE$1))) -> 0.00012870951 | S64: #N/A | T64: #N/A | U64: #N/A | V64: #N/A | W64: #N/A | X64: 0.0069502394 | Y64: 0.0027802606 | Z64: 0.0027503749 | AA64: 0.001513728 | AB64: 0.0012618005 | AC64: 0.0013466982 | AD64: 0.001013796 | AE64: 0.0010078188 | AF64: 0.0010719394 | AG64: 0.0009119456 | AH64: 0.0007709085 | AI64: 0.0006642729 | AJ64: 0.0005840391 | AK64: 0.0005109701 | AL64: 0.0005384008 | AM64: 0.0005049795 | AN64: 0.0003945957 | AO64: 0.0001697148 | AP64: 0.0001695845 | AQ64: 0.0001471146 | AR64: 0.000134851 | AS64: 0.00014407751 | AT64: 0.00014012682 | AU64: 0.000130402 | AV64: 0.00012978912
A65: BGN | B65: =FORECAST(B$1,INDEX(S65:BE65, 1, COUNTA(S65:BE65)-4):INDEX(S65:BE65, 1, COUNTA(S65:BE65)),INDEX($S$1:$BE$1, 1, COUNTA($S$1:$BE$1)-4):INDEX($S$1:$BE$1, 1, COUNTA($S$1:$BE$1))) -> 1.0005266 | S65: #N/A | T65: #N/A | U65: #N/A | V65: #N/A | W65: #N/A | X65: #N/A | Y65: #N/A | Z65: #N/A | AA65: 0.9618639 | AB65: 0.89801744 | AC65: 1.072075 | AD65: 0.89042065 | AE65: 1.0656315 | AF65: 1.1393757 | AG65: 0.98025687 | AH65: 0.947627 | AI65: 0.83302785 | AJ65: 0.78258605 | AK65: 0.81406786 | AL65: 0.73813492 | AM65: 0.84260593 | AN65: 0.77819657 | AO65: 0.86975854 | AP65: 0.89530599 | AQ65: 0.91308317 | AR65: 0.85444307 | AS65: 0.82755159 | AT65: 0.88091907 | AU65: 0.91665732 | AV65: 0.98818318
A66: DZD | B66: =FORECAST(B$1,INDEX(S66:BE66, 1, COUNTA(S66:BE66)-4):INDEX(S66:BE66, 1, COUNTA(S66:BE66)),INDEX($S$1:$BE$1, 1, COUNTA($S$1:$BE$1)-4):INDEX($S$1:$BE$1, 1, COUNTA($S$1:$BE$1))) -> 0.013383692 | S66: #N/A | T66: 0.026118604 | U66: 0.034244757 | V66: 0.027311119 | W66: 0.029800086 | X66: 0.03204098 | Y66: 0.027638028 | Z66: 0.025651949 | AA66: 0.02122506 | AB66: 0.019889206 | AC66: 0.022459121 | AD66: 0.018667684 | AE66: 0.02124285 | AF66: 0.022182146 | AG66: 0.019320351 | AH66: 0.018044922 | AI66: 0.016515892 | AJ66: 0.015012826 | AK66: 0.014534753 | AL66: 0.013745868 | AM66: 0.013355727 | AN66: 0.012994537 | AO66: 0.012026242 | AP66: 0.0132928 | AQ66: 0.011720351 | AR66: 0.01047487 | AS66: 0.010825315 | AT66: 0.011823245 | AU66: 0.01232807 | AV66: 0.012659359
A67: IRR | B67: =FORECAST(B$1,INDEX(S67:BE67, 1, COUNTA(S67:BE67)-4):INDEX(S67:BE67, 1, COUNTA(S67:BE67)),INDEX($S$1:$BE$1, 1, COUNTA($S$1:$BE$1)-4):INDEX($S$1:$BE$1, 1, COUNTA($S$1:$BE$1))) -> 4.1221162e-05 | S67: #N/A | T67: #N/A | U67: #N/A | V67: 0.0010713684 | W67: 0.0012351035 | X67: 0.0014180284 | Y67: 0.0012200414 | Z67: 0.0011773895 | AA67: 0.00017891652 | AB67: 0.00016278928 | AC67: 0.00017996292 | AD67: 0.00013781836 | AE67: 0.00014333292 | AF67: 0.00016017708 | AG67: 0.0001425761 | AH67: 0.0001250841 | AI67: 0.0001077722 | AJ67: 9.72105e-05 | AK67: 4.52866e-05 | AL67: 4.77482e-05 | AM67: 4.79841e-05 | AN67: 4.39587e-05 | AO67: 3.65579e-05 | AP67: 3.80456e-05 | AQ67: 3.5738e-05 | AR67: 3.429e-05 | AS67: 3.7328843e-05 | AT67: 3.8052589e-05 | AU67: 3.9738604e-05 | AV67: 3.8987783e-05
A68: DOP | B68: =FORECAST(B$1,INDEX(S68:BE68, 1, COUNTA(S68:BE68)-4):INDEX(S68:BE68, 1, COUNTA(S68:BE68)),INDEX($S$1:$BE$1, 1, COUNTA($S$1:$BE$1)-4):INDEX($S$1:$BE$1, 1, COUNTA($S$1:$BE$1))) -> 0.02901132 | S68: #N/A | T68: #N/A | U68: #N/A | V68: 0.12018555 | W68: 0.13368001 | X68: 0.15408035 | Y68: 0.11704667 | Z68: 0.12041876 | AA68: 0.034625608 | AB68: 0.051335088 | AC68: 0.050665493 | AD68: 0.038609959 | AE68: 0.038430418 | AF68: 0.044369863 | AG68: 0.038810644 | AH68: 0.034439003 | AI68: 0.031443961 | AJ68: 0.029014544 | AK68: 0.026917278 | AL68: 0.029993149 | AM68: 0.031644495 | AN68: 0.030169077 | AO68: 0.02780706 | AP68: 0.03069325 | AQ68: 0.025716762 | AR68: 0.02555301 | AS68: 0.028931067 | AT68: 0.029236324 | AU68: 0.028381988 | AV68: 0.027609214
A69: ISK | B69: =FORECAST(B$1,INDEX(S69:BE69, 1, COUNTA(S69:BE69)-4):INDEX(S69:BE69, 1, COUNTA(S69:BE69)),INDEX($S$1:$BE$1, 1, COUNTA($S$1:$BE$1)-4):INDEX($S$1:$BE$1, 1, COUNTA($S$1:$BE$1))) -> 0.013507047 | S69: 0.021786632 | T69: 0.020948405 | U69: 0.02707725 | V69: 0.025124485 | W69: 0.027944904 | X69: 0.023921159 | Y69: 0.024627221 | Z69: 0.023650424 | AA69: 0.021419257 | AB69: 0.022470435 | AC69: 0.021615942 | AD69: 0.02057209 | AE69: 0.016723847 | AF69: 0.012575028 | AG69: 0.011145928 | AH69: 0.011387963 | AI69: 0.0096591907 | AJ69: 0.0095722247 | AK69: 0.010238837 | AL69: 0.0097967703 | AM69: 0.01173947 | AN69: 0.012587741 | AO69: 0.014002335 | AP69: 0.012921622 | AQ69: 0.011147499 | AR69: 0.011119065 | AS69: 0.011669212 | AT69: 0.011462576 | AU69: 0.01191193 | AV69: 0.013591392
A70: XAG | B70: =FORECAST(B$1,INDEX(S70:BE70, 1, COUNTA(S70:BE70)-4):INDEX(S70:BE70, 1, COUNTA(S70:BE70)),INDEX($S$1:$BE$1, 1, COUNTA($S$1:$BE$1)-4):INDEX($S$1:$BE$1, 1, COUNTA($S$1:$BE$1))) -> 61.577107 | S70: #N/A | T70: 6.8486405 | U70: 10.325192 | V70: 9.8994437 | W70: 10.660981 | X70: 10.6331 | Y70: 9.5333237 | Z70: 10.13852 | AA70: 9.263951 | AB70: 10.021893 | AC70: 18.235825 | AD70: 16.055359 | AE70: 23.929833 | AF70: 21.297988 | AG70: 25.306259 | AH70: 49.184041 | AI70: 39.390421 | AJ70: 33.491011 | AK70: 22.831184 | AL70: 22.592849 | AM70: 21.59615 | AN70: 26.100921 | AO70: 22.591655 | AP70: 27.708334 | AQ70: 40.263771 | AR70: 32.50234 | AS70: 32.034622 | AT70: 35.135062 | AU70: 47.04653 | AV70: 59.039035
A71: CRC | B71: =FORECAST(B$1,INDEX(S71:BE71, 1, COUNTA(S71:BE71)-4):INDEX(S71:BE71, 1, COUNTA(S71:BE71)),INDEX($S$1:$BE$1, 1, COUNTA($S$1:$BE$1)-4):INDEX($S$1:$BE$1, 1, COUNTA($S$1:$BE$1))) -> 0.0036521322 | S71: #N/A | T71: #N/A | U71: #N/A | V71: 0.0066241331 | W71: 0.0070038963 | X71: 0.0075193898 | Y71: 0.0057620145 | Z71: 0.0057476504 | AA71: 0.0035281083 | AB71: 0.0030614145 | AC71: 0.0032127716 | AD71: 0.0024598011 | AE71: 0.002536251 | AF71: 0.0027815953 | AG71: 0.0025412839 | AH71: 0.0026401726 | AI71: 0.0024303151 | AJ71: 0.0023912208 | AK71: 0.0021136253 | AL71: 0.0025145269 | AM71: 0.0027064263 | AN71: 0.0025800239 | AO71: 0.0024378437 | AP71: 0.0027582033 | AQ71: 0.0025753938 | AR71: 0.0023022452 | AS71: 0.0023557824 | AT71: 0.0029354854 | AU71: 0.003240812 | AV71: 0.0032513818
A72: SYP | B72: =FORECAST(B$1,INDEX(S72:BE72, 1, COUNTA(S72:BE72)-4):INDEX(S72:BE72, 1, COUNTA(S72:BE72)),INDEX($S$1:$BE$1, 1, COUNTA($S$1:$BE$1)-4):INDEX($S$1:$BE$1, 1, COUNTA($S$1:$BE$1))) -> -0.00022832589 | S72: #N/A | T72: #N/A | U72: #N/A | V72: 0.041664325 | W72: 0.046585016 | X72: 0.046615731 | Y72: 0.041330684 | Z72: 0.040086218 | AA72: 0.031380256 | AB72: 0.028176216 | AC72: 0.031590754 | AD72: 0.024624078 | AE72: 0.025763009 | AF72: 0.034532858 | AG72: 0.030694157 | AH72: 0.027518506 | AI72: 0.021319334 | AJ72: 0.016918639 | AK72: 0.007974869 | AL72: 0.0070970783 | AM72: 0.0076803561 | AN72: 0.0066709499 | AO72: 0.002680068 | AP72: 0.003109856 | AQ72: 0.0029315115 | AR72: 0.0011456416 | AS72: 0.00062738508 | AT72: 0.00063953623 | AU72: 0.00012746439 | AV72: 0.00012628727
A73: LYD | B73: =FORECAST(B$1,INDEX(S73:BE73, 1, COUNTA(S73:BE73)-4):INDEX(S73:BE73, 1, COUNTA(S73:BE73)),INDEX($S$1:$BE$1, 1, COUNTA($S$1:$BE$1)-4):INDEX($S$1:$BE$1, 1, COUNTA($S$1:$BE$1))) -> 0.32044247 | S73: #N/A | T73: #N/A | U73: #N/A | V73: #N/A | W73: #N/A | X73: 4.3927095 | Y73: 1.7087475 | Z73: 1.6456479 | AA73: 1.1583558 | AB73: 1.1025514 | AC73: 1.2705413 | AD73: 1.0051039 | AE73: 1.1134884 | AF73: 1.2730249 | AG73: 1.1080054 | AH73: 1.0651455 | AI73: 0.97790415 | AJ73: 0.93462672 | AK73: 0.92695126 | AL73: 0.97955501 | AM73: 1.056656 | AN73: 1.0052464 | AO73: 1.0385283 | AP73: 1.1313627 | AQ73: 1.0952312 | AR73: 0.31608529 | AS73: 0.32403917 | AT73: 0.33412588 | AU73: 0.33967114 | AV73: 0.3032747
A74: JMD | B74: =FORECAST(B$1,INDEX(S74:BE74, 1, COUNTA(S74:BE74)-4):INDEX(S74:BE74, 1, COUNTA(S74:BE74)),INDEX($S$1:$BE$1, 1, COUNTA($S$1:$BE$1)-4):INDEX($S$1:$BE$1, 1, COUNTA($S$1:$BE$1))) -> 0.010623628 | S74: 0.042952014 | T74: 0.043042175 | U74: 0.054486329 | V74: 0.04999719 | W74: 0.050887737 | X74: 0.054326557 | Y74: 0.043213937 | Z74: 0.042702133 | AA74: 0.025341133 | AB74: 0.023694345 | AC74: 0.02489528 | AD74: 0.018636379 | AE74: 0.018433116 | AF74: 0.017886464 | AG74: 0.015963044 | AH74: 0.015399968 | AI74: 0.014163453 | AJ74: 0.012189591 | AK74: 0.010559419 | AL74: 0.011683583 | AM74: 0.011920937 | AN74: 0.011177276 | AO74: 0.01100757 | AP74: 0.011945979 | AQ74: 0.010204954 | AR74: 0.0098324976 | AS74: 0.010287298 | AT74: 0.010511863 | AU74: 0.01058264 | AV74: 0.01023958
A75: MUR | B75: =FORECAST(B$1,INDEX(S75:BE75, 1, COUNTA(S75:BE75)-4):INDEX(S75:BE75, 1, COUNTA(S75:BE75)),INDEX($S$1:$BE$1, 1, COUNTA($S$1:$BE$1)-4):INDEX($S$1:$BE$1, 1, COUNTA($S$1:$BE$1))) -> 0.036937115 | S75: #N/A | T75: #N/A | U75: #N/A | V75: 0.074548494 | W75: 0.082483411 | X75: 0.084443982 | Y75: 0.071532496 | Z75: 0.068337647 | AA75: 0.055141602 | AB75: 0.049178152 | AC75: 0.053285158 | AD75: 0.040443351 | AE75: 0.048459753 | AF75: 0.04973535 | AG75: 0.047700379 | AH75: 0.046751873 | AI75: 0.04249036 | AJ75: 0.037842849 | AK75: 0.037878766 | AL75: 0.03685093 | AM75: 0.040960328 | AN75: 0.040466332 | AO75: 0.040580277 | AP75: 0.043804283 | AQ75: 0.037820432 | AR75: 0.033751609 | AS75: 0.035262307 | AT75: 0.034094681 | AU75: 0.035971354 | AV75: 0.03644922
A76: GHS | B76: =FORECAST(B$1,INDEX(S76:BE76, 1, COUNTA(S76:BE76)-4):INDEX(S76:BE76, 1, COUNTA(S76:BE76)),INDEX($S$1:$BE$1, 1, COUNTA($S$1:$BE$1)-4):INDEX($S$1:$BE$1, 1, COUNTA($S$1:$BE$1))) -> 0.098576467 | S76: #N/A | T76: #N/A | U76: #N/A | V76: #N/A | W76: #N/A | X76: #N/A | Y76: #N/A | Z76: #N/A | AA76: #N/A | AB76: #N/A | AC76: #N/A | AD76: #N/A | AE76: 1.2062605 | AF76: 1.0646127 | AG76: 0.99344327 | AH76: 0.86669584 | AI76: 0.68919482 | AJ76: 0.61581743 | AK76: 0.43077697 | AL76: 0.35011684 | AM76: 0.37352439 | AN76: 0.33157953 | AO76: 0.30940005 | AP76: 0.29771227 | AQ76: 0.26018198 | AR76: 0.23800755 | AS76: 0.18619628 | AT76: 0.13105856 | AU76: 0.11849312 | AV76: 0.15867605
A77: AOA | B77: =FORECAST(B$1,INDEX(S77:BE77, 1, COUNTA(S77:BE77)-4):INDEX(S77:BE77, 1, COUNTA(S77:BE77)),INDEX($S$1:$BE$1, 1, COUNTA($S$1:$BE$1)-4):INDEX($S$1:$BE$1, 1, COUNTA($S$1:$BE$1))) -> 0.0017219853 | S77: #N/A | T77: #N/A | U77: #N/A | V77: #N/A | W77: #N/A | X77: #N/A | Y77: 0.046004529 | Z77: 0.047881202 | AA77: 0.018439388 | AB77: 0.016443901 | AC77: 0.020463821 | AD77: 0.017092278 | AE77: 0.017554762 | AF77: 0.020438765 | AG77: 0.015290571 | AH77: 0.014019983 | AI77: 0.01284824 | AJ77: 0.012439088 | AK77: 0.01178756 | AL77: 0.012392521 | AM77: 0.0090330353 | AN77: 0.0086467046 | AO77: 0.0064478213 | AP77: 0.0042371721 | AQ77: 0.0025869392 | AR77: 0.0023855154 | AS77: 0.0036824675 | AT77: 0.0031474657 | AU77: 0.0019635978 | AV77: 0.0017914327
A78: UYU | B78: =FORECAST(B$1,INDEX(S78:BE78, 1, COUNTA(S78:BE78)-4):INDEX(S78:BE78, 1, COUNTA(S78:BE78)),INDEX($S$1:$BE$1, 1, COUNTA($S$1:$BE$1)-4):INDEX($S$1:$BE$1, 1, COUNTA($S$1:$BE$1))) -> 0.045275427 | S78: #N/A | T78: #N/A | U78: #N/A | V78: 0.16562673 | W78: 0.17723991 | X78: 0.18102214 | Y78: 0.079864554 | Z78: 0.10928195 | AA78: 0.051950924 | AB78: 0.059716327 | AC78: 0.069162996 | AD78: 0.053685766 | AE78: 0.067901951 | AF78: 0.068648307 | AG78: 0.073347077 | AH78: 0.068292 | AI78: 0.062968963 | AJ78: 0.063406519 | AK78: 0.051058226 | AL78: 0.052102305 | AM78: 0.045664063 | AN78: 0.049651031 | AO78: 0.048665529 | AP78: 0.043521239 | AQ78: 0.035112322 | AR78: 0.033544902 | AS78: 0.038489703 | AT78: 0.040826164 | AU78: 0.042996913 | AV78: 0.041098336
A79: AFN | B79: =FORECAST(B$1,INDEX(S79:BE79, 1, COUNTA(S79:BE79)-4):INDEX(S79:BE79, 1, COUNTA(S79:BE79)),INDEX($S$1:$BE$1, 1, COUNTA($S$1:$BE$1)-4):INDEX($S$1:$BE$1, 1, COUNTA($S$1:$BE$1))) -> 0.024847368 | S79: #N/A | T79: #N/A | U79: #N/A | V79: #N/A | W79: #N/A | X79: #N/A | Y79: #N/A | Z79: #N/A | AA79: #N/A | AB79: #N/A | AC79: 0.03331269 | AD79: 0.025909946 | AE79: 0.028558411 | AF79: 0.033620256 | AG79: 0.03070083 | AH79: 0.030334354 | AI79: 0.025333841 | AJ79: 0.022672613 | AK79: 0.020403421 | AL79: 0.023175484 | AM79: 0.021130336 | AN79: 0.021385017 | AO79: 0.019933258 | AP79: 0.020397893 | AQ79: 0.01955165 | AR79: 0.018028958 | AS79: 0.017567231 | AT79: 0.018236416 | AU79: 0.022924545 | AV79: 0.023382648
A80: LBP | B80: =FORECAST(B$1,INDEX(S80:BE80, 1, COUNTA(S80:BE80)-4):INDEX(S80:BE80, 1, COUNTA(S80:BE80)),INDEX($S$1:$BE$1, 1, COUNTA($S$1:$BE$1)-4):INDEX($S$1:$BE$1, 1, COUNTA($S$1:$BE$1))) -> -0.00044187217 | S80: #N/A | T80: 0.00096017983 | U80: 0.0012901513 | V80: 0.0012617057 | W80: 0.0014120504 | X80: 0.0016495037 | Y80: 0.0014040962 | Z80: 0.0013541145 | AA80: 0.0010211581 | AB80: 0.00097148075 | AC80: 0.0010939855 | AD80: 0.00084467261 | AE80: 0.000871506 | AF80: 0.0010580426 | AG80: 0.0009409718 | AH80: 0.0008675605 | AI80: 0.000811154 | AJ80: 0.00079385 | AK80: 0.0007671469 | AL80: 0.0008870658 | AM80: 0.0009614049 | AN80: 0.0009434566 | AO80: 0.0009158409 | AP80: 0.0010624093 | AQ80: 0.0009958516 | AR80: 0.0009559262 | AS80: 0.0010456589 | AT80: 0.00010682886 | AU80: 1.8117907e-05 | AV80: 1.8299344e-05
A81: XPF | B81: =FORECAST(B$1,INDEX(S81:BE81, 1, COUNTA(S81:BE81)-4):INDEX(S81:BE81, 1, COUNTA(S81:BE81)),INDEX($S$1:$BE$1, 1, COUNTA($S$1:$BE$1)-4):INDEX($S$1:$BE$1, 1, COUNTA($S$1:$BE$1))) -> 0.016398487 | S81: #N/A | T81: #N/A | U81: #N/A | V81: 0.016175435 | W81: 0.016891358 | X81: 0.017508201 | Y81: 0.017550834 | Z81: 0.016899298 | AA81: 0.015945298 | AB81: 0.014660328 | AC81: 0.017568697 | AD81: 0.014592724 | AE81: 0.017461428 | AF81: 0.018677564 | AG81: 0.016066432 | AH81: 0.015532859 | AI81: 0.013660248 | AJ81: 0.012862537 | AK81: 0.013342659 | AL81: 0.01209773 | AM81: 0.013828713 | AN81: 0.012745632 | AO81: 0.014255217 | AP81: 0.014673936 | AQ81: 0.014965301 | AR81: 0.014004198 | AS81: 0.013563451 | AT81: 0.014438136 | AU81: 0.015023881 | AV81: 0.016196179
A82: TTD | B82: =FORECAST(B$1,INDEX(S82:BE82, 1, COUNTA(S82:BE82)-4):INDEX(S82:BE82, 1, COUNTA(S82:BE82)),INDEX($S$1:$BE$1, 1, COUNTA($S$1:$BE$1)-4):INDEX($S$1:$BE$1, 1, COUNTA($S$1:$BE$1))) -> 0.25517469 | S82: 0.25460583 | T82: 0.24020552 | U82: 0.31271569 | V82: 0.30354309 | W82: 0.3416981 | X82: 0.4021404 | Y82: 0.34683936 | Z82: 0.3334717 | AA82: 0.25105284 | AB82: 0.23483383 | AC82: 0.26248902 | AD82: 0.20446199 | AE82: 0.21617308 | AF82: 0.25649002 | AG82: 0.22482981 | AH82: 0.20606276 | AI82: 0.19237762 | AJ82: 0.18628256 | AK82: 0.17838005 | AL82: 0.21038334 | AM82: 0.22065038 | AN82: 0.21275056 | AO82: 0.20664913 | AP82: 0.23649172 | AQ82: 0.22231297 | AR82: 0.21223026 | AS82: 0.23213894 | AT82: 0.23712917 | AU82: 0.24402105 | AV82: 0.24230541
A83: TZS | B83: =FORECAST(B$1,INDEX(S83:BE83, 1, COUNTA(S83:BE83)-4):INDEX(S83:BE83, 1, COUNTA(S83:BE83)),INDEX($S$1:$BE$1, 1, COUNTA($S$1:$BE$1)-4):INDEX($S$1:$BE$1, 1, COUNTA($S$1:$BE$1))) -> 0.00064003793 | S83: #N/A | T83: #N/A | U83: #N/A | V83: 0.0025701092 | W83: 0.0026955704 | X83: 0.0027931471 | Y83: 0.0021968947 | Z83: 0.0022060295 | AA83: 0.0013866031 | AB83: 0.0013174696 | AC83: 0.0013150976 | AD83: 0.0010264977 | AE83: 0.0011163345 | AF83: 0.0012120717 | AG83: 0.0010416313 | AH83: 0.0008684292 | AI83: 0.0007780878 | AJ83: 0.0007377138 | AK83: 0.0007069601 | AL83: 0.0007246726 | AM83: 0.0006634057 | AN83: 0.000637128 | AO83: 0.0006121394 | AP83: 0.0006966428 | AQ83: 0.0006456557 | AR83: 0.0006217275 | AS83: 0.00067612582 | AT83: 0.00068677754 | AU83: 0.00064098587 | AV83: 0.00062311634
A84: ALL | B84: =FORECAST(B$1,INDEX(S84:BE84, 1, COUNTA(S84:BE84)-4):INDEX(S84:BE84, 1, COUNTA(S84:BE84)),INDEX($S$1:$BE$1, 1, COUNTA($S$1:$BE$1)-4):INDEX($S$1:$BE$1, 1, COUNTA($S$1:$BE$1))) -> 0.020821785 | S84: #N/A | T84: #N/A | U84: #N/A | V84: 0.013916973 | W84: 0.015144514 | X84: 0.016582552 | Y84: 0.015413451 | Z84: 0.014828073 | AA84: 0.015241648 | AB84: 0.014201611 | AC84: 0.016997503 | AD84: 0.014164395 | AE84: 0.017008574 | AF84: 0.017066303 | AG84: 0.01370807 | AH84: 0.01312779 | AI84: 0.011612147 | AJ84: 0.01096369 | AK84: 0.011374987 | AL84: 0.01028594 | AM84: 0.011903811 | AN84: 0.011212981 | AO84: 0.013058692 | AP84: 0.014314003 | AQ84: 0.014365956 | AR84: 0.013700566 | AS84: 0.013840364 | AT84: 0.015108368 | AU84: 0.017854215 | AV84: 0.019671584
A85: XCD | B85: =FORECAST(B$1,INDEX(S85:BE85, 1, COUNTA(S85:BE85)-4):INDEX(S85:BE85, 1, COUNTA(S85:BE85)),INDEX($S$1:$BE$1, 1, COUNTA($S$1:$BE$1)-4):INDEX($S$1:$BE$1, 1, COUNTA($S$1:$BE$1))) -> 0.63943309 | S85: #N/A | T85: 0.54602869 | U85: 0.72152907 | V85: 0.69698685 | W85: 0.8015775 | X85: 0.91449705 | Y85: 0.78681376 | Z85: 0.75930719 | AA85: 0.57290248 | AB85: 0.54287569 | AC85: 0.61562852 | AD85: 0.47864781 | AE85: 0.49189496 | AF85: 0.59559477 | AG85: 0.55918066 | AH85: 0.48310267 | AI85: 0.45244364 | AJ85: 0.44219959 | AK85: 0.42718716 | AL85: 0.49660826 | AM85: 0.53710166 | AN85: 0.52868512 | AO85: 0.51165231 | AP85: 0.59263626 | AQ85: 0.55550335 | AR85: 0.53324349 | AS85: 0.58381783 | AT85: 0.59487806 | AU85: 0.61361112 | AV85: 0.60666387
A86: GTQ | B86: =FORECAST(B$1,INDEX(S86:BE86, 1, COUNTA(S86:BE86)-4):INDEX(S86:BE86, 1, COUNTA(S86:BE86)),INDEX($S$1:$BE$1, 1, COUNTA($S$1:$BE$1)-4):INDEX($S$1:$BE$1, 1, COUNTA($S$1:$BE$1))) -> 0.22391433 | S86: #N/A | T86: #N/A | U86: #N/A | V86: 0.25578372 | W86: 0.27690859 | X86: 0.31615135 | Y86: 0.27411576 | Z86: 0.26112972 | AA86: 0.19606029 | AB86: 0.19232943 | AC86: 0.21671048 | AD86: 0.16586498 | AE86: 0.17480346 | AF86: 0.19549302 | AG86: 0.1768008 | AH86: 0.17028424 | AI86: 0.15882439 | AJ86: 0.15376006 | AK86: 0.14919226 | AL86: 0.17546894 | AM86: 0.18803523 | AN86: 0.19450195 | AO86: 0.18825239 | AP86: 0.20738892 | AQ86: 0.1950955 | AR86: 0.18624952 | AS86: 0.20372442 | AT86: 0.20624714 | AU86: 0.21338535 | AV86: 0.2135556
A87: NPR | B87: =FORECAST(B$1,INDEX(S87:BE87, 1, COUNTA(S87:BE87)-4):INDEX(S87:BE87, 1, COUNTA(S87:BE87)),INDEX($S$1:$BE$1, 1, COUNTA($S$1:$BE$1)-4):INDEX($S$1:$BE$1, 1, COUNTA($S$1:$BE$1))) -> 0.012129517 | S87: #N/A | T87: #N/A | U87: #N/A | V87: 0.027180264 | W87: 0.030312712 | X87: 0.033001096 | Y87: 0.02755939 | Z87: 0.026102407 | AA87: 0.021444087 | AB87: 0.020709962 | AC87: 0.022440229 | AD87: 0.019813793 | AE87: 0.019038214 | AF87: 0.021007109 | AG87: 0.019692208 | AH87: 0.018268588 | AI87: 0.014906625 | AJ87: 0.013747598 | AK87: 0.011967595 | AL87: 0.013391018 | AM87: 0.013686747 | AN87: 0.013679443 | AO87: 0.013184263 | AP87: 0.014007901 | AQ87: 0.012482038 | AR87: 0.012084788 | AS87: 0.012472994 | AT87: 0.012198382 | AU87: 0.012397847 | AV87: 0.011965164
A88: BOB | B88: =FORECAST(B$1,INDEX(S88:BE88, 1, COUNTA(S88:BE88)-4):INDEX(S88:BE88, 1, COUNTA(S88:BE88)),INDEX($S$1:$BE$1, 1, COUNTA($S$1:$BE$1)-4):INDEX($S$1:$BE$1, 1, COUNTA($S$1:$BE$1))) -> 0.24994393 | S88: #N/A | T88: #N/A | U88: #N/A | V88: 0.32606863 | W88: 0.34726322 | X88: 0.37468013 | Y88: 0.28930916 | Z88: 0.28838506 | AA88: 0.19449168 | AB88: 0.18093619 | AC88: 0.20627636 | AD88: 0.16204365 | AE88: 0.18248582 | AF88: 0.22652964 | AG88: 0.20257264 | AH88: 0.18741052 | AI88: 0.17807549 | AJ88: 0.17279326 | AK88: 0.16691829 | AL88: 0.19433477 | AM88: 0.21264227 | AN88: 0.20808307 | AO88: 0.2000996 | AP88: 0.2318665 | AQ88: 0.21764002 | AR88: 0.20879028 | AS88: 0.22925995 | AT88: 0.23248312 | AU88: 0.23993254 | AV88: 0.23740393
A89: ZWD | B89: =FORECAST(B$1,INDEX(S89:BE89, 1, COUNTA(S89:BE89)-4):INDEX(S89:BE89, 1, COUNTA(S89:BE89)),INDEX($S$1:$BE$1, 1, COUNTA($S$1:$BE$1)-4):INDEX($S$1:$BE$1, 1, COUNTA($S$1:$BE$1))) -> #N/A | S89: #N/A | T89: #N/A | U89: #N/A | V89: 0.049339332 | W89: 0.055743691 | X89: 0.044975265 | Y89: 0.038660549 | Z89: 0.037500081 | AA89: 0.00029113171 | AB89: 0.00014779776 | AC89: 1.6296822e-05 | AD89: 0.0051119586 | AE89: 9.8373357e-11 | AF89: 0.0042590339 | AG89: 0.0039014403 | AH89: 0.0036042477 | AI89: 0.0033755122 | AJ89: 0.0032990851 | AK89: 0.003187083 | AL89: 0.0037050078 | AM89: 0.0040071138 | AN89: 0.0039443213 | AO89: 0.0038149494 | AP89: 0.0044254824 | AQ89: 0.004148235 | AR89: 0.003981925 | AS89: 0.0043557082 | AT89: 0.0044398796 | AU89: 0.0045793098 | AV89: #N/A
A90: BBD | B90: =FORECAST(B$1,INDEX(S90:BE90, 1, COUNTA(S90:BE90)-4):INDEX(S90:BE90, 1, COUNTA(S90:BE90)),INDEX($S$1:$BE$1, 1, COUNTA($S$1:$BE$1)-4):INDEX($S$1:$BE$1, 1, COUNTA($S$1:$BE$1))) -> 0.86475702 | S90: 0.72600686 | T90: 0.73303361 | U90: 0.96854261 | V90: 0.94691648 | W90: 1.0768667 | X90: 1.2407749 | Y90: 1.0675363 | Z90: 1.0354189 | AA90: 0.77392148 | AB90: 0.73520101 | AC90: 0.82652393 | AD90: 0.64059632 | AE90: 0.65832558 | AF90: 0.79511904 | AG90: 0.70538949 | AH90: 0.65218862 | AI90: 0.61079893 | AJ90: 0.59696945 | AK90: 0.57670267 | AL90: 0.67042115 | AM90: 0.72508724 | AN90: 0.71372493 | AO90: 0.6903151 | AP90: 0.80079105 | AQ90: 0.75062312 | AR90: 0.72052934 | AS90: 0.78816541 | AT90: 0.80339621 | AU90: 0.82862612 | AV90: 0.82099125
A91: CUC | B91: =FORECAST(B$1,INDEX(S91:BE91, 1, COUNTA(S91:BE91)-4):INDEX(S91:BE91, 1, COUNTA(S91:BE91)),INDEX($S$1:$BE$1, 1, COUNTA($S$1:$BE$1)-4):INDEX($S$1:$BE$1, 1, COUNTA($S$1:$BE$1))) -> 1.729514 | S91: #N/A | T91: #N/A | U91: #N/A | V91: #N/A | W91: #N/A | X91: #N/A | Y91: #N/A | Z91: #N/A | AA91: 1.5460334 | AB91: 1.5815205 | AC91: 1.7719516 | AD91: 1.3802675 | AE91: 1.3770574 | AF91: 1.7175052 | AG91: 1.4768801 | AH91: 1.4087669 | AI91: 1.2215979 | AJ91: 1.1939389 | AK91: 1.1534053 | AL91: 1.3408423 | AM91: 1.4501745 | AN91: 1.4274499 | AO91: 1.3806302 | AP91: 1.6015821 | AQ91: 1.5012462 | AR91: 1.4410587 | AS91: 1.5763308 | AT91: 1.6067924 | AU91: 1.6572522 | AV91: 1.6419825
A92: LAK | B92: =FORECAST(B$1,INDEX(S92:BE92, 1, COUNTA(S92:BE92)-4):INDEX(S92:BE92, 1, COUNTA(S92:BE92)),INDEX($S$1:$BE$1, 1, COUNTA($S$1:$BE$1)-4):INDEX($S$1:$BE$1, 1, COUNTA($S$1:$BE$1))) -> 4.9780395e-05 | S92: #N/A | T92: #N/A | U92: #N/A | V92: 0.00044087885 | W92: 0.00028196194 | X92: 0.00032630482 | Y92: 0.0002809306 | Z92: 0.00027110942 | AA92: 0.00014417918 | AB92: 0.00014135749 | AC92: 0.0001624422 | AD92: 0.00013291417 | AE92: 0.00015151992 | AF92: 0.00018674301 | AG92: 0.0001668555 | AH92: 0.0001620848 | AI92: 0.0001536601 | AJ92: 0.0001526136 | AK92: 0.000143503 | AL92: 0.0001652319 | AM92: 0.0001785899 | AN92: 0.0001741005 | AO92: 0.0001664009 | AP92: 0.000181843 | AQ92: 0.0001657981 | AR92: 0.000145633 | AS92: 0.00010440547 | AT92: 9.4686977e-05 | AU92: 7.750432e-05 | AV92: 7.5980733e-05
A93: BND | B93: =FORECAST(B$1,INDEX(S93:BE93, 1, COUNTA(S93:BE93)-4):INDEX(S93:BE93, 1, COUNTA(S93:BE93)),INDEX($S$1:$BE$1, 1, COUNTA($S$1:$BE$1)-4):INDEX($S$1:$BE$1, 1, COUNTA($S$1:$BE$1))) -> 1.3444073 | S93: #N/A | T93: #N/A | U93: #N/A | V93: 1.110062 | W93: 1.2367727 | X93: 1.3551079 | Y93: 1.189932 | Z93: 1.1576377 | AA93: 0.90300623 | AB93: 0.8633601 | AC93: 1.0365819 | AD93: 0.83906041 | AE93: 0.96776327 | AF93: 1.095809 | AG93: 1.0109357 | AH93: 1.0346263 | AI93: 0.97137234 | AJ93: 0.96247469 | AK93: 0.91618139 | AL93: 0.98315968 | AM93: 1.0749534 | AN93: 1.02176 | AO93: 1.0528619 | AP93: 1.1559953 | AQ93: 1.0975982 | AR93: 1.0633676 | AS93: 1.1453873 | AT93: 1.1950031 | AU93: 1.2255059 | AV93: 1.2906743
A94: BWP | B94: =FORECAST(B$1,INDEX(S94:BE94, 1, COUNTA(S94:BE94)-4):INDEX(S94:BE94, 1, COUNTA(S94:BE94)),INDEX($S$1:$BE$1, 1, COUNTA($S$1:$BE$1)-4):INDEX($S$1:$BE$1, 1, COUNTA($S$1:$BE$1))) -> 0.12035137 | S94: #N/A | T94: #N/A | U94: #N/A | V94: 0.40723168 | W94: 0.42030281 | X94: 0.43827293 | Y94: 0.33886807 | Z94: 0.33478457 | AA94: 0.3352488 | AB94: 0.26598269 | AC94: 0.27293673 | AD94: 0.20814672 | AE94: 0.20040521 | AF94: 0.23622776 | AG94: 0.20910702 | AH94: 0.19996103 | AI94: 0.16467139 | AJ94: 0.1447054 | AK94: 0.13160423 | AL94: 0.13508449 | AM94: 0.13385229 | AN94: 0.13597351 | AO94: 0.14482794 | AP94: 0.14491327 | AQ94: 0.13112075 | AR94: 0.12743434 | AS94: 0.12595448 | AT94: 0.12165369 | AU94: 0.12185659 | AV94: 0.1233269
A95: HNL | B95: =FORECAST(B$1,INDEX(S95:BE95, 1, COUNTA(S95:BE95)-4):INDEX(S95:BE95, 1, COUNTA(S95:BE95)),INDEX($S$1:$BE$1, 1, COUNTA($S$1:$BE$1)-4):INDEX($S$1:$BE$1, 1, COUNTA($S$1:$BE$1))) -> 0.066507272 | S95: #N/A | T95: #N/A | U95: #N/A | V95: 0.13166395 | W95: 0.14524497 | X95: 0.15971165 | Y95: 0.12743834 | Z95: 0.12563607 | AA95: 0.084833898 | AB95: 0.077780436 | AC95: 0.087280223 | AD95: 0.067623867 | AE95: 0.068611406 | AF95: 0.084072853 | AG95: 0.074725123 | AH95: 0.069032929 | AI95: 0.064109044 | AJ95: 0.060909024 | AK95: 0.059932731 | AL95: 0.062744234 | AM95: 0.064116183 | AN95: 0.060781344 | AO95: 0.058413347 | AP95: 0.065117362 | AQ95: 0.060820918 | AR95: 0.059825483 | AS95: 0.06409942 | AT95: 0.065210866 | AU95: 0.067059598 | AV95: 0.062844294
A96: PYG | B96: =FORECAST(B$1,INDEX(S96:BE96, 1, COUNTA(S96:BE96)-4):INDEX(S96:BE96, 1, COUNTA(S96:BE96)),INDEX($S$1:$BE$1, 1, COUNTA($S$1:$BE$1)-4):INDEX($S$1:$BE$1, 1, COUNTA($S$1:$BE$1))) -> 0.00021332484 | S96: #N/A | T96: #N/A | U96: #N/A | V96: 0.00058519137 | W96: 0.00061173498 | X96: 0.00061193111 | Y96: 0.0003600673 | Z96: 0.00035586347 | AA96: 0.00026052757 | AB96: 0.00024142739 | AC96: 0.0002960794 | AD96: 0.0002483414 | AE96: 0.0003301267 | AF96: 0.00031552343 | AG96: 0.0003023407 | AH96: 0.0003269116 | AI96: 0.0002840925 | AJ96: 0.0002978997 | AK96: 0.0002610696 | AL96: 0.0002793708 | AM96: 0.0002571876 | AN96: 0.0002537238 | AO96: 0.0002475286 | AP96: 0.0002512483 | AQ96: 0.000216621 | AR96: 0.000208921 | AS96: 0.00022887945 | AT96: 0.0002235043 | AU96: 0.00022079657 | AV96: 0.00020585255
A97: ETB | B97: =FORECAST(B$1,INDEX(S97:BE97, 1, COUNTA(S97:BE97)-4):INDEX(S97:BE97, 1, COUNTA(S97:BE97)),INDEX($S$1:$BE$1, 1, COUNTA($S$1:$BE$1)-4):INDEX($S$1:$BE$1, 1, COUNTA($S$1:$BE$1))) -> 0.014658684 | S97: #N/A | T97: #N/A | U97: #N/A | V97: 0.24192189 | W97: 0.26450765 | X97: 0.29791772 | Y97: 0.25102176 | Z97: 0.24822974 | AA97: 0.17788697 | AB97: 0.16987518 | AC97: 0.18873557 | AD97: 0.14080281 | AE97: 0.1358039 | AF97: 0.14062699 | AG97: 0.10534363 | AH97: 0.078081171 | AI97: 0.070246339 | AJ97: 0.064521927 | AK97: 0.059502901 | AL97: 0.065605879 | AM97: 0.067561615 | AN97: 0.062266079 | AO97: 0.050095436 | AP97: 0.054720884 | AQ97: 0.042681326 | AR97: 0.031192324 | AS97: 0.029931525 | AT97: 0.02986471 | AU97: 0.028854376 | AV97: 0.012160796
A98: NAD | B98: =FORECAST(B$1,INDEX(S98:BE98, 1, COUNTA(S98:BE98)-4):INDEX(S98:BE98, 1, COUNTA(S98:BE98)),INDEX($S$1:$BE$1, 1, COUNTA($S$1:$BE$1)-4):INDEX($S$1:$BE$1, 1, COUNTA($S$1:$BE$1))) -> 0.088452156 | S98: #N/A | T98: #N/A | U98: #N/A | V98: #N/A | W98: #N/A | X98: 0.30844997 | Y98: 0.20279938 | Z98: 0.20444051 | AA98: 0.25309161 | AB98: 0.21390871 | AC98: 0.22901951 | AD98: 0.18341639 | AE98: 0.16761026 | AF98: 0.20315058 | AG98: 0.19437318 | AH98: 0.19454019 | AI98: 0.15929224 | AJ98: 0.12984973 | AK98: 0.10917217 | AL98: 0.11206744 | AM98: 0.098220734 | AN98: 0.10634037 | AO98: 0.11646985 | AP98: 0.10427852 | AQ98: 0.086688361 | AR98: 0.096887583 | AS98: 0.095759089 | AT98: 0.088355312 | AU98: 0.089952549 | AV98: 0.092669701
A99: PGK | B99: =FORECAST(B$1,INDEX(S99:BE99, 1, COUNTA(S99:BE99)-4):INDEX(S99:BE99, 1, COUNTA(S99:BE99)),INDEX($S$1:$BE$1, 1, COUNTA($S$1:$BE$1)-4):INDEX($S$1:$BE$1, 1, COUNTA($S$1:$BE$1))) -> 0.41680515 | S99: #N/A | T99: #N/A | U99: #N/A | V99: 0.71433538 | W99: 0.88273248 | X99: 0.74569402 | Y99: 0.54555653 | Z99: 0.52947557 | AA99: 0.48758677 | AB99: 0.47797252 | AC99: 0.55253764 | AD99: 0.4313234 | AE99: 0.50273098 | AF99: 0.60953184 | AG99: 0.52551858 | AH99: 0.5100115 | AI99: 0.57415099 | AJ99: 0.55548149 | AK99: 0.41666535 | AL99: 0.50107403 | AM99: 0.47130845 | AN99: 0.43437044 | AO99: 0.42743128 | AP99: 0.47087057 | AQ99: 0.432173 | AR99: 0.41070366 | AS99: 0.44768383 | AT99: 0.45633259 | AU99: 0.43197952 | AV99: 0.3982484
A100: SDG | B100: =FORECAST(B$1,INDEX(S100:BE100, 1, COUNTA(S100:BE100)-4):INDEX(S100:BE100, 1, COUNTA(S100:BE100)),INDEX($S$1:$BE$1, 1, COUNTA($S$1:$BE$1)-4):INDEX($S$1:$BE$1, 1, COUNTA($S$1:$BE$1))) -> 0.0025260377 | S100: #N/A | T100: #N/A | U100: #N/A | V100: #N/A | W100: #N/A | X100: #N/A | Y100: #N/A | Z100: #N/A | AA100: #N/A | AB100: #N/A | AC100: #N/A | AD100: 0.63721064 | AE100: 0.63580933 | AF100: 0.66875734 | AG100: 0.63457586 | AH100: 0.46718381 | AI100: 0.45752727 | AJ100: 0.27070416 | AK100: 0.20297499 | AL100: 0.2256861 | AM100: 0.23809295 | AN100: 0.21337068 | AO100: 0.076026164 | AP100: 0.035413285 | AQ100: 0.027149747 | AR100: 0.0032806997 | AS100: 0.0027893642 | AT100: 0.0027529083 | AU100: 0.0027577372 | AV100: 0.0027347547
...

Sheet fi
A1: today: https://tradingeconomics.com/new-zealand/consumer-price-index-cpi | F1: linear, 5 month fit for inflation | K1: today | L1: index estimate for today | M1: Extrapolation of inflation into the future based on the last 5 quarters for which we have data
A2: https://www.stats.govt.nz/large-datasets/csv-files-for-download/ | K2: =YEAR(TODAY()) -> 2026 | L2: =L3*(1+M2)^(K2-K3) -> 1340.3609 | M2: =AVERAGE(OFFSET(H1,COUNT(H:H),0,5,1)) -> 0.024708811
A3: Year | B3: Quarter | C3: YQ | D3: Date | E3: CPI | F3: Inflation (2 quarter central estimate) | G3: CPIY | H3: Inflation (rolling 5 quarter linear fit) | K3: {=MAX(_xlfn._xlws.FILTER(A2:A1000, COUNTIF(A2:A1000, A2:A1000) >= 4))} -> 2024 | L3: =INDEX(G:G,MATCH(K3,A:A,0)) -> 1276.5
A4: 1950 | B4: Q1 | C4: 1950Q1 | D4: 18352 | E4: 27.956111 | F4: 0.066666712 | G4: {=AVERAGE(IF(A1:A7=A4,E1:E7))} -> 29.216877
A5: 1950 | B5: Q2 | C5: =CONCATENATE(A5,B5) -> 1950Q2 | D5: =DATE(YEAR(D4),MONTH(D4)+3,DAY(D4)) -> 18444 | E5: 28.833165 | F5: =SUMPRODUCT(E4:E6,TRANSPOSE({-1,0,1}))/2/E5*4 -> 0.12737644 | G5: {=AVERAGE(IF(A2:A8=A5,E2:E8))} -> 29.216877 | K5: Any year
A6: 1950 | B6: Q3 | C6: =CONCATENATE(A6,B6) -> 1950Q3 | D6: =DATE(YEAR(D5),MONTH(D5)+3,DAY(D5)) -> 18536 | E6: 29.792444 | F6: =SUMPRODUCT(E5:E7,TRANSPOSE({-1,0,1}))/2/E6*4 -> 0.097516068 | G6: {=AVERAGE(IF(A3:A9=A6,E3:E9))} -> 29.216877 | H6: =SUMPRODUCT(E4:E8,TRANSPOSE({-2,-1,0,1,2}))/10/E6*4 -> 0.093836236 | K6: 2004 | L6: =INDEX(G:G,MATCH(K3,A:A,0))*(1+AVERAGE(OFFSET(H1,COUNT(H:H),0,5,1)))^(K6-K3) -> 783.45023
A7: 1950 | B7: Q4 | C7: =CONCATENATE(A7,B7) -> 1950Q4 | D7: =DATE(YEAR(D6),MONTH(D6)+3,DAY(D6)) -> 18627 | E7: 30.285786 | F7: =SUMPRODUCT(E6:E8,TRANSPOSE({-1,0,1}))/2/E7*4 -> 0.061538439 | G7: {=AVERAGE(IF(A4:A10=A7,E4:E10))} -> 29.216877 | H7: =SUMPRODUCT(E5:E9,TRANSPOSE({-2,-1,0,1,2}))/10/E7*4 -> 0.097013589 | I7: =SUMPRODUCT(E6:E8,TRANSPOSE({-1,0,1}))/2/E7*4 -> 0.061538439
A8: =A4+1 -> 1951 | B8: Q1 | C8: =CONCATENATE(A8,B8) -> 1951Q1 | D8: =DATE(YEAR(D7),MONTH(D7)+3,DAY(D7)) -> 18717 | E8: 30.724314 | F8: =SUMPRODUCT(E7:E9,TRANSPOSE({-1,0,1}))/2/E8*4 -> 0.11418383 | G8: {=AVERAGE(IF(A5:A11=A8,E5:E11))} -> 32.437311 | H8: =SUMPRODUCT(E6:E10,TRANSPOSE({-2,-1,0,1,2}))/10/E8*4 -> 0.10847456 | I8: =SUMPRODUCT(E7:E9,TRANSPOSE({-1,0,1}))/2/E8*4 -> 0.11418383
A9: =A5+1 -> 1951 | B9: Q2 | C9: =CONCATENATE(A9,B9) -> 1951Q2 | D9: =DATE(YEAR(D8),MONTH(D8)+3,DAY(D8)) -> 18809 | E9: 32.039896 | F9: =SUMPRODUCT(E8:E10,TRANSPOSE({-1,0,1}))/2/E9*4 -> 0.14713425 | G9: {=AVERAGE(IF(A6:A12=A9,E6:E12))} -> 32.437311 | H9: =SUMPRODUCT(E7:E11,TRANSPOSE({-2,-1,0,1,2}))/10/E9*4 -> 0.11976048
A10: =A6+1 -> 1951 | B10: Q3 | C10: =CONCATENATE(A10,B10) -> 1951Q3 | D10: =DATE(YEAR(D9),MONTH(D9)+3,DAY(D9)) -> 18901 | E10: 33.081397 | F10: =SUMPRODUCT(E9:E11,TRANSPOSE({-1,0,1}))/2/E10*4 -> 0.11267602 | G10: {=AVERAGE(IF(A7:A13=A10,E7:E13))} -> 32.437311 | H10: =SUMPRODUCT(E8:E12,TRANSPOSE({-2,-1,0,1,2}))/10/E10*4 -> 0.11002483
A11: =A7+1 -> 1951 | B11: Q4 | C11: =CONCATENATE(A11,B11) -> 1951Q4 | D11: =DATE(YEAR(D10),MONTH(D10)+3,DAY(D10)) -> 18992 | E11: 33.903636 | F11: =SUMPRODUCT(E10:E12,TRANSPOSE({-1,0,1}))/2/E11*4 -> 0.074373498 | G11: {=AVERAGE(IF(A8:A14=A11,E8:E14))} -> 32.437311 | H11: =SUMPRODUCT(E9:E13,TRANSPOSE({-2,-1,0,1,2}))/10/E11*4 -> 0.080194018
A12: =A8+1 -> 1952 | B12: Q1 | C12: =CONCATENATE(A12,B12) -> 1952Q1 | D12: =DATE(YEAR(D11),MONTH(D11)+3,DAY(D11)) -> 19083 | E12: 34.342163 | F12: =SUMPRODUCT(E11:E13,TRANSPOSE({-1,0,1}))/2/E12*4 -> 0.052673619 | G12: {=AVERAGE(IF(A9:A15=A12,E9:E15))} -> 34.95199 | H12: =SUMPRODUCT(E10:E14,TRANSPOSE({-2,-1,0,1,2}))/10/E12*4 -> 0.059696752
A13: =A9+1 -> 1952 | B13: Q2 | C13: =CONCATENATE(A13,B13) -> 1952Q2 | D13: =DATE(YEAR(D12),MONTH(D12)+3,DAY(D12)) -> 19175 | E13: 34.808099 | F13: =SUMPRODUCT(E12:E14,TRANSPOSE({-1,0,1}))/2/E13*4 -> 0.048818926 | G13: {=AVERAGE(IF(A10:A16=A13,E10:E16))} -> 34.95199 | H13: =SUMPRODUCT(E11:E15,TRANSPOSE({-2,-1,0,1,2}))/10/E13*4 -> 0.045669291
A14: =A10+1 -> 1952 | B14: Q3 | C14: =CONCATENATE(A14,B14) -> 1952Q3 | D14: =DATE(YEAR(D13),MONTH(D13)+3,DAY(D13)) -> 19267 | E14: 35.19181 | F14: =SUMPRODUCT(E13:E15,TRANSPOSE({-1,0,1}))/2/E14*4 -> 0.03738313 | G14: {=AVERAGE(IF(A11:A17=A14,E11:E17))} -> 34.95199 | H14: =SUMPRODUCT(E12:E16,TRANSPOSE({-2,-1,0,1,2}))/10/E14*4 -> 0.041121477
A15: =A11+1 -> 1952 | B15: Q4 | C15: =CONCATENATE(A15,B15) -> 1952Q4 | D15: =DATE(YEAR(D14),MONTH(D14)+3,DAY(D14)) -> 19358 | E15: 35.465889 | F15: =SUMPRODUCT(E14:E16,TRANSPOSE({-1,0,1}))/2/E15*4 -> 0.035548637 | G15: {=AVERAGE(IF(A12:A18=A15,E12:E18))} -> 34.95199 | H15: =SUMPRODUCT(E13:E17,TRANSPOSE({-2,-1,0,1,2}))/10/E15*4 -> 0.039258094
A16: =A12+1 -> 1953 | B16: Q1 | C16: =CONCATENATE(A16,B16) -> 1953Q1 | D16: =DATE(YEAR(D15),MONTH(D15)+3,DAY(D15)) -> 19448 | E16: 35.822192 | F16: =SUMPRODUCT(E15:E17,TRANSPOSE({-1,0,1}))/2/E16*4 -> 0.042846233 | G16: {=AVERAGE(IF(A13:A19=A16,E13:E19))} -> 36.534799 | H16: =SUMPRODUCT(E14:E18,TRANSPOSE({-2,-1,0,1,2}))/10/E16*4 -> 0.041009942
A17: =A13+1 -> 1953 | B17: Q2 | C17: =CONCATENATE(A17,B17) -> 1953Q2 | D17: =DATE(YEAR(D16),MONTH(D16)+3,DAY(D16)) -> 19540 | E17: 36.233312 | F17: =SUMPRODUCT(E16:E18,TRANSPOSE({-1,0,1}))/2/E17*4 -> 0.045385804 | G17: {=AVERAGE(IF(A14:A20=A17,E14:E20))} -> 36.534799 | H17: =SUMPRODUCT(E15:E19,TRANSPOSE({-2,-1,0,1,2}))/10/E17*4 -> 0.052647519
A18: =A14+1 -> 1953 | B18: Q3 | C18: =CONCATENATE(A18,B18) -> 1953Q3 | D18: =DATE(YEAR(D17),MONTH(D17)+3,DAY(D17)) -> 19632 | E18: 36.644431 | F18: =SUMPRODUCT(E17:E19,TRANSPOSE({-1,0,1}))/2/E18*4 -> 0.065819005 | G18: {=AVERAGE(IF(A15:A21=A18,E15:E21))} -> 36.534799 | H18: =SUMPRODUCT(E16:E20,TRANSPOSE({-2,-1,0,1,2}))/10/E18*4 -> 0.055048648
A19: =A15+1 -> 1953 | B19: Q4 | C19: =CONCATENATE(A19,B19) -> 1953Q4 | D19: =DATE(YEAR(D18),MONTH(D18)+3,DAY(D18)) -> 19723 | E19: 37.439262 | F19: =SUMPRODUCT(E18:E20,TRANSPOSE({-1,0,1}))/2/E19*4 -> 0.058565204 | G19: {=AVERAGE(IF(A16:A22=A19,E16:E22))} -> 36.534799 | H19: =SUMPRODUCT(E17:E21,TRANSPOSE({-2,-1,0,1,2}))/10/E19*4 -> 0.057393856
A20: =A16+1 -> 1954 | B20: Q1 | C20: =CONCATENATE(A20,B20) -> 1954Q1 | D20: =DATE(YEAR(D19),MONTH(D19)+3,DAY(D19)) -> 19813 | E20: 37.74075 | F20: =SUMPRODUCT(E19:E21,TRANSPOSE({-1,0,1}))/2/E20*4 -> 0.049382696 | G20: {=AVERAGE(IF(A17:A23=A20,E17:E23))} -> 38.220389 | H20: =SUMPRODUCT(E18:E22,TRANSPOSE({-2,-1,0,1,2}))/10/E20*4 -> 0.047639795
... A291: =A287+1 -> 2021 | B291: Q4 | C291: =CONCATENATE(A291,B291) -> 2021Q4 | D291: =DATE(YEAR(D290),MONTH(D290)+3,DAY(D290)) -> 44560 | E291: 1122 | F291: =SUMPRODUCT(E290:E292,TRANSPOSE({-1,0,1}))/2/E291*4 -> 0.064171123 | G291: {=AVERAGE(IF(A288:A294=A291,E288:E294))} -> 1094.5 | H291: =SUMPRODUCT(E289:E293,TRANSPOSE({-2,-1,0,1,2}))/10/E291*4 -> 0.06916221
A292: =A288+1 -> 2022 | B292: Q1 | C292: =CONCATENATE(A292,B292) -> 2022Q1 | D292: =DATE(YEAR(D291),MONTH(D291)+3,DAY(D291)) -> 44650 | E292: 1142 | F292: =SUMPRODUCT(E291:E293,TRANSPOSE({-1,0,1}))/2/E292*4 -> 0.068301226 | G292: {=AVERAGE(IF(A289:A295=A292,E289:E295))} -> 1173 | H292: =SUMPRODUCT(E290:E294,TRANSPOSE({-2,-1,0,1,2}))/10/E292*4 -> 0.069702277 | J292: =AVERAGE(H288:H292) -> 0.063010253
A293: =A289+1 -> 2022 | B293: Q2 | C293: =CONCATENATE(A293,B293) -> 2022Q2 | D293: =DATE(YEAR(D292),MONTH(D292)+3,DAY(D292)) -> 44742 | E293: 1161 | F293: =SUMPRODUCT(E292:E294,TRANSPOSE({-1,0,1}))/2/E293*4 -> 0.075796727 | G293: {=AVERAGE(IF(A290:A296=A293,E290:E296))} -> 1173 | H293: =SUMPRODUCT(E291:E295,TRANSPOSE({-2,-1,0,1,2}))/10/E293*4 -> 0.070973299 | J293: =AVERAGE(H289:H293) -> 0.067691804
A294: =A290+1 -> 2022 | B294: Q3 | C294: =CONCATENATE(A294,B294) -> 2022Q3 | D294: =DATE(YEAR(D293),MONTH(D293)+3,DAY(D293)) -> 44834 | E294: 1186 | F294: =SUMPRODUCT(E293:E295,TRANSPOSE({-1,0,1}))/2/E294*4 -> 0.070826307 | G294: {=AVERAGE(IF(A291:A297=A294,E291:E297))} -> 1173 | H294: =SUMPRODUCT(E292:E296,TRANSPOSE({-2,-1,0,1,2}))/10/E294*4 -> 0.065430017 | J294: =AVERAGE(H290:H294) -> 0.068652114
A295: =A291+1 -> 2022 | B295: Q4 | C295: =CONCATENATE(A295,B295) -> 2022Q4 | D295: =DATE(YEAR(D294),MONTH(D294)+3,DAY(D294)) -> 44925 | E295: 1203 | F295: =SUMPRODUCT(E294:E296,TRANSPOSE({-1,0,1}))/2/E295*4 -> 0.053200333 | G295: {=AVERAGE(IF(A292:A298=A295,E292:E298))} -> 1173 | H295: =SUMPRODUCT(E293:E297,TRANSPOSE({-2,-1,0,1,2}))/10/E295*4 -> 0.057190357 | J295: =AVERAGE(H291:H295) -> 0.066491632
A296: =A292+1 -> 2023 | B296: Q1 | C296: =CONCATENATE(A296,B296) -> 2023Q1 | D296: =DATE(YEAR(D295),MONTH(D295)+3,DAY(D295)) -> 45015 | E296: 1218 | F296: =SUMPRODUCT(E295:E297,TRANSPOSE({-1,0,1}))/2/E296*4 -> 0.045977011 | G296: {=AVERAGE(IF(A293:A299=A296,E293:E299))} -> 1240.25 | H296: =SUMPRODUCT(E294:E298,TRANSPOSE({-2,-1,0,1,2}))/10/E296*4 -> 0.05320197 | J296: =AVERAGE(H292:H296) -> 0.063299584
A297: =A293+1 -> 2023 | B297: Q2 | C297: =CONCATENATE(A297,B297) -> 2023Q2 | D297: =DATE(YEAR(D296),MONTH(D296)+3,DAY(D296)) -> 45107 | E297: 1231 | F297: =SUMPRODUCT(E296:E298,TRANSPOSE({-1,0,1}))/2/E297*4 -> 0.056864338 | G297: {=AVERAGE(IF(A294:A300=A297,E294:E300))} -> 1240.25 | H297: =SUMPRODUCT(E295:E299,TRANSPOSE({-2,-1,0,1,2}))/10/E297*4 -> 0.047766044 | J297: =AVERAGE(H293:H297) -> 0.058912337
A298: =A294+1 -> 2023 | B298: Q3 | C298: =CONCATENATE(A298,B298) -> 2023Q3 | D298: =DATE(YEAR(D297),MONTH(D297)+3,DAY(D297)) -> 45199 | E298: 1253 | F298: =SUMPRODUCT(E297:E299,TRANSPOSE({-1,0,1}))/2/E298*4 -> 0.044692737 | G298: {=AVERAGE(IF(A295:A301=A298,E295:E301))} -> 1240.25 | H298: =SUMPRODUCT(E294:E298,TRANSPOSE({-2,-1,0,1,2}))/10/E298*4 -> 0.051715882 | J298: =AVERAGE(H294:H298) -> 0.055060854
A299: =A295+1 -> 2023 | B299: Q4 | C299: =CONCATENATE(A299,B299) -> 2023Q4 | D299: =DATE(YEAR(D298),MONTH(D298)+3,DAY(D298)) -> 45290 | E299: 1259 | F299: =SUMPRODUCT(E297:E299,TRANSPOSE({-1,0,1}))/2/E299*4 -> 0.044479746 | G299: {=AVERAGE(IF(A296:A302=A299,E296:E302))} -> 1240.25 | H299: =SUMPRODUCT(E295:E299,TRANSPOSE({-2,-1,0,1,2}))/10/E299*4 -> 0.046703733 | J299: =AVERAGE(H295:H299) -> 0.051315597
A300: =A296+1 -> 2024 | B300: Q1 | C300: =CONCATENATE(A300,B300) -> 2024Q1 | D300: =DATE(YEAR(D299),MONTH(D299)+3,DAY(D299)) -> 45381 | E300: 1267 | F300: =SUMPRODUCT(E298:E300,TRANSPOSE({-1,0,1}))/2/E300*4 -> 0.022099448 | G300: {=AVERAGE(IF(A297:A303=A300,E297:E303))} -> 1276.5 | H300: =SUMPRODUCT(E296:E300,TRANSPOSE({-2,-1,0,1,2}))/10/E300*4 -> 0.039779006 | J300: =AVERAGE(H296:H300) -> 0.047833327
A301: =A297+1 -> 2024 | B301: Q2 | C301: =CONCATENATE(A301,B301) -> 2024Q2 | D301: =DATE(YEAR(D300),MONTH(D300)+3,DAY(D300)) -> 45473 | E301: 1272 | F301: =SUMPRODUCT(E299:E301,TRANSPOSE({-1,0,1}))/2/E301*4 -> 0.020440252 | G301: {=AVERAGE(IF(A298:A304=A301,E298:E304))} -> 1276.5 | H301: =SUMPRODUCT(E297:E301,TRANSPOSE({-2,-1,0,1,2}))/10/E301*4 -> 0.030188679 | J301: =AVERAGE(H297:H301) -> 0.043230669
A302: =A298+1 -> 2024 | B302: Q3 | C302: =CONCATENATE(A302,B302) -> 2024Q3 | D302: =DATE(YEAR(D301),MONTH(D301)+3,DAY(D301)) -> 45565 | E302: 1280 | F302: =SUMPRODUCT(E300:E302,TRANSPOSE({-1,0,1}))/2/E302*4 -> 0.0203125 | G302: {=AVERAGE(IF(A299:A305=A302,E299:E305))} -> 1276.5 | H302: =SUMPRODUCT(E298:E302,TRANSPOSE({-2,-1,0,1,2}))/10/E302*4 -> 0.0209375 | J302: =AVERAGE(H298:H302) -> 0.03786496
A303: =A299+1 -> 2024 | B303: Q4 | C303: =CONCATENATE(A303,B303) -> 2024Q4 | D303: =DATE(YEAR(D302),MONTH(D302)+3,DAY(D302)) -> 45656 | E303: 1287 | F303: =SUMPRODUCT(E301:E303,TRANSPOSE({-1,0,1}))/2/E303*4 -> 0.023310023 | G303: {=AVERAGE(IF(A300:A306=A303,E300:E306))} -> 1276.5 | H303: =SUMPRODUCT(E299:E303,TRANSPOSE({-2,-1,0,1,2}))/10/E303*4 -> 0.021445221 | J303: =AVERAGE(H299:H303) -> 0.031810828
A304: =A300+1 -> 2025 | B304: Q1 | C304: =CONCATENATE(A304,B304) -> 2025Q1 | D304: =DATE(YEAR(D303),MONTH(D303)+3,DAY(D303)) -> 45746 | E304: 1299 | F304: =SUMPRODUCT(E302:E304,TRANSPOSE({-1,0,1}))/2/E304*4 -> 0.029253272 | G304: {=AVERAGE(IF(A301:A307=A304,E301:E307))} -> 1302.5 | H304: =SUMPRODUCT(E300:E304,TRANSPOSE({-2,-1,0,1,2}))/10/E304*4 -> 0.024326405 | J304: =AVERAGE(H300:H304) -> 0.027335362
A305: =A301+1 -> 2025 | B305: Q2 | C305: =CONCATENATE(A305,B305) -> 2025Q2 | D305: =DATE(YEAR(D304),MONTH(D304)+3,DAY(D304)) -> 45838 | E305: 1306 | F305: =SUMPRODUCT(E303:E305,TRANSPOSE({-1,0,1}))/2/E305*4 -> 0.029096478 | G305: {=AVERAGE(IF(A302:A308=A305,E302:E308))} -> 1302.5 | H305: =SUMPRODUCT(E301:E305,TRANSPOSE({-2,-1,0,1,2}))/10/E305*4 -> 0.026646248 | J305: =AVERAGE(H301:H305) -> 0.024708811

Sheet EXCH CALC
A1: USD | B1: US Dollar | C1: 0.60901989 | D1: 1.6419825 | E1: USD | F1: US Dollar | G1: =1/INDEX(C:C,MATCH(E1,A:A,0)) -> 1.6419825
A2: EUR | B2: Euro | C2: 0.51740598 | D2: 1.9327183 | E2: EUR | F2: Euro | G2: =1/INDEX(C:C,MATCH(E2,A:A,0)) -> 1.9327183
A3: GBP | B3: British Pound | C3: 0.44385107 | D3: 2.2530079 | E3: GBP | F3: British Pound | G3: =1/INDEX(C:C,MATCH(E3,A:A,0)) -> 2.2530079
A4: INR | B4: Indian Rupee | C4: 52.210498 | D4: 0.019153236 | E4: INR | F4: Indian Rupee | G4: =1/INDEX(C:C,MATCH(E4,A:A,0)) -> 0.019153236
A5: AUD | B5: Australian Dollar | C5: 0.92666376 | D5: 1.0791401 | E5: AUD | F5: Australian Dollar | G5: =1/INDEX(C:C,MATCH(E5,A:A,0)) -> 1.0791401
A6: CAD | B6: Canadian Dollar | C6: 0.82948054 | D6: 1.2055738 | E6: CAD | F6: Canadian Dollar | G6: =1/INDEX(C:C,MATCH(E6,A:A,0)) -> 1.2055738
A7: SGD | B7: Singapore Dollar | C7: 0.77478879 | D7: 1.2906743 | E7: SGD | F7: Singapore Dollar | G7: =1/INDEX(C:C,MATCH(E7,A:A,0)) -> 1.2906743
A8: CHF | B8: Swiss Franc | C8: 0.48353014 | D8: 2.0681234 | E8: CHF | F8: Swiss Franc | G8: =1/INDEX(C:C,MATCH(E8,A:A,0)) -> 2.0681234
A9: MYR | B9: Malaysian Ringgit | C9: 2.5656351 | D9: 0.38976705 | E9: MYR | F9: Malaysian Ringgit | G9: =1/INDEX(C:C,MATCH(E9,A:A,0)) -> 0.38976705
A10: JPY | B10: Japanese Yen | C10: 87.804376 | D10: 0.011388954 | E10: JPY | F10: Japanese Yen | G10: =1/INDEX(C:C,MATCH(E10,A:A,0)) -> 0.011388954
A11: CNY | B11: Chinese Yuan Renminbi | C11: 4.3628898 | D11: 0.22920588 | E11: CNY | F11: Chinese Yuan Renminbi | G11: =1/INDEX(C:C,MATCH(E11,A:A,0)) -> 0.22920588
A12: NZD | B12: New Zealand Dollar | C12: 1 | D12: 1 | E12: NZD | F12: New Zealand Dollar | G12: =1/INDEX(C:C,MATCH(E12,A:A,0)) -> 1
... A162: TVD | B162: Tuvaluan Dollar | C162: 0.92666376 | D162: 1.0791401 | E162: TMT | F162: Guernsey Pound | G162: =1/INDEX(C:C,MATCH(E162,A:A,0)) -> 0.46793021
A163: ZMW | B163: Zambian Kwacha | C163: 14.597657 | D163: 0.068504144 | E163: TVD | G163: =1/INDEX(C:C,MATCH(E163,A:A,0)) -> 1.0791401
A164: ADA | B164: Cardano | C164: 1.0160711 | D164: 0.98418306 | E164: IMP | G164: =1/INDEX(C:C,MATCH(E164,A:A,0)) -> 2.2530079
A165: BCH | B165: Bitcoin Cash | C165: 0.0011852593 | D165: 843.69722 | E165: GGP | G165: =1/INDEX(C:C,MATCH(E165,A:A,0)) -> 2.2530079
A166: BTC | B166: Bitcoin | C166: 5.6554899e-06 | D166: 176819.34 | E166: ZMW | G166: =1/INDEX(C:C,MATCH(E166,A:A,0)) -> 0.068504144
A167: CLF | B167: CLF | C167: 0.014771204 | D167: 67.699288 | E167: BCH | G167: =1/INDEX(C:C,MATCH(E167,A:A,0)) -> 843.69722
A168: CNH | B168: Chinese Yuan Renminbi Offshore | C168: 4.3606347 | D168: 0.22932441 | E168: CLF | G168: =1/INDEX(C:C,MATCH(E168,A:A,0)) -> 67.699288
A169: DOGE | B169: Dogecoin | C169: 3.6896245 | D169: 0.27103029 | E169: CNH | G169: =1/INDEX(C:C,MATCH(E169,A:A,0)) -> 0.22932441
A170: DOT | B170: Polkadot | C170: 0.17920767 | D170: 5.5801184 | E170: ETH | G170: =1/INDEX(C:C,MATCH(E170,A:A,0)) -> 4066.7663
A171: ETH | B171: Ethereum | C171: 0.00024589562 | D171: 4066.7663 | E171: LINK | G171: =1/INDEX(C:C,MATCH(E171,A:A,0)) -> 21.980528
A172: EURC | B172: EURC | C172: 0.51848771 | D172: 1.928686 | E172: LTC | G172: =1/INDEX(C:C,MATCH(E172,A:A,0)) -> 141.23046
A173: LINK | B173: Chainlink | C173: 0.045494813 | D173: 21.980528 | E173: MXV | G173: =1/INDEX(C:C,MATCH(E173,A:A,0)) -> 0.74089293
A174: LTC | B174: Litecoin | C174: 0.0070806255 | D174: 141.23046 | E174: XBT | G174: =1/INDEX(C:C,MATCH(E174,A:A,0)) -> 176819.34
... A181: USDP | B181: USDP | C181: 0.60911126 | D181: 1.6417362 | E181: DOT | G181: =1/INDEX(C:C,MATCH(E181,A:A,0)) -> 5.5801184
A182: VED | B182: VED | C182: 64.850303 | D182: 0.015420129
A183: XBT | B183: XBT | C183: 5.6554899e-06 | D183: 176819.34
A184: XCG | B184: Caribbean Guilder | C184: 1.0970888 | D184: 0.91150321
A185: XLM | B185: Stellar Lumen | C185: 2.585882 | D185: 0.38671525
A186: XRP | B186: Ripple | C186: 0.27757599 | D186: 3.602617
A187: ZWG | B187: Zimbabwean Dollar | C187: 16.413995 | D187: 0.060923622

Sheet Streams
A1: StreamID | B1: StreamName
A2: S1 | B2: Peas
A3: S2 | B3: Dehulled peas
A4: S3 | B4: Hulls
A5: S4 | B5: Dehulled pea flour
A6: S5 | B6: NaOH solution
A7: S6 | B7: Water 1
A8: S7 | B8: Heat treated slurry
A9: S8 | B9: Cooled slurry
A10: S9 | B10: Sludge
A11: S10 | B11: Supernatant 1
A12: S11 | B12: Sediment 1
... A34: S33 | B34: Water vapour 2

Sheet SystemStreams
A1: StreamName | B1: StreamID | C1: Role | D1: Input/Output | E1: Price model | Q1: No. | R1: Stream type | S1: Input/Output | U1: No. | V1: Cost model description | W1: cost model name
A2: Peas | B2: =IF(A2="","",IFERROR(INDEX(Streams!$A:$A, MATCH(A2, Streams!$B:$B, 0)), "enter the stream name")) -> S1 | C2: Feedstock | D2: =IF(C2="","",IFERROR(INDEX($S:$S, MATCH(C2, $R:$R, 0)), "enter input or output")) -> Input | E2: static | Q2: 1 | R2: Feedstock | S2: Input | U2: 1 | V2: TBD | W2: static
A3: Hulls | B3: =IF(A3="","",IFERROR(INDEX(Streams!$A:$A, MATCH(A3, Streams!$B:$B, 0)), "enter the stream name")) -> S3 | C3: Byproduct | D3: =IF(C3="","",IFERROR(INDEX($S:$S, MATCH(C3, $R:$R, 0)), "enter input or output")) -> Output | E3: static | Q3: 2 | R3: Water | S3: Input | U3: 2 | V3: TBD | W3: linear_protein
A4: NaOH solution | B4: =IF(A4="","",IFERROR(INDEX(Streams!$A:$A, MATCH(A4, Streams!$B:$B, 0)), "enter the stream name")) -> S5 | C4: Solvent | D4: =IF(C4="","",IFERROR(INDEX($S:$S, MATCH(C4, $R:$R, 0)), "enter input or output")) -> Input | E4: static | Q4: 3 | R4: Solvent | S4: Input | U4: 3 | V4: TBD | W4: performance_index
A5: Water 1 | B5: =IF(A5="","",IFERROR(INDEX(Streams!$A:$A, MATCH(A5, Streams!$B:$B, 0)), "enter the stream name")) -> S6 | C5: Water | D5: =IF(C5="","",IFERROR(INDEX($S:$S, MATCH(C5, $R:$R, 0)), "enter input or output")) -> Input | E5: static | Q5: 4 | R5: Waste | S5: Output | U5: 4 | V5: TBD | W5: yield_adjusted
A6: Water 2 | B6: =IF(A6="","",IFERROR(INDEX(Streams!$A:$A, MATCH(A6, Streams!$B:$B, 0)), "enter the stream name")) -> S13 | C6: Water | D6: =IF(C6="","",IFERROR(INDEX($S:$S, MATCH(C6, $R:$R, 0)), "enter input or output")) -> Input | E6: static | Q6: 5 | R6: Product | S6: Output
A7: Whey 1 | B7: =IF(A7="","",IFERROR(INDEX(Streams!$A:$A, MATCH(A7, Streams!$B:$B, 0)), "enter the stream name")) -> S12 | C7: Waste | D7: =IF(C7="","",IFERROR(INDEX($S:$S, MATCH(C7, $R:$R, 0)), "enter input or output")) -> Output | E7: static | Q7: 6 | R7: Byproduct | S7: Output
A8: Whey 2 | B8: =IF(A8="","",IFERROR(INDEX(Streams!$A:$A, MATCH(A8, Streams!$B:$B, 0)), "enter the stream name")) -> S16 | C8: Waste | D8: =IF(C8="","",IFERROR(INDEX($S:$S, MATCH(C8, $R:$R, 0)), "enter input or output")) -> Output | E8: static
A9: Water 3 | B9: =IF(A9="","",IFERROR(INDEX(Streams!$A:$A, MATCH(A9, Streams!$B:$B, 0)), "enter the stream name")) -> S17 | C9: Water | D9: =IF(C9="","",IFERROR(INDEX($S:$S, MATCH(C9, $R:$R, 0)), "enter input or output")) -> Input | E9: static
A10: Dried sediment | B10: =IF(A10="","",IFERROR(INDEX(Streams!$A:$A, MATCH(A10, Streams!$B:$B, 0)), "enter the stream name")) -> S21 | C10: Byproduct | D10: =IF(C10="","",IFERROR(INDEX($S:$S, MATCH(C10, $R:$R, 0)), "enter input or output")) -> Output | E10: static
A11: Water vapour 1 | B11: =IF(A11="","",IFERROR(INDEX(Streams!$A:$A, MATCH(A11, Streams!$B:$B, 0)), "enter the stream name")) -> S22 | C11: Waste | D11: =IF(C11="","",IFERROR(INDEX($S:$S, MATCH(C11, $R:$R, 0)), "enter input or output")) -> Output | E11: static
A12: Water 4 | B12: =IF(A12="","",IFERROR(INDEX(Streams!$A:$A, MATCH(A12, Streams!$B:$B, 0)), "enter the stream name")) -> S25 | C12: Water | D12: =IF(C12="","",IFERROR(INDEX($S:$S, MATCH(C12, $R:$R, 0)), "enter input or output")) -> Input | E12: static
A13: Permeate 1 | B13: =IF(A13="","",IFERROR(INDEX(Streams!$A:$A, MATCH(A13, Streams!$B:$B, 0)), "enter the stream name")) -> S24 | C13: Waste | D13: =IF(C13="","",IFERROR(INDEX($S:$S, MATCH(C13, $R:$R, 0)), "enter input or output")) -> Output | E13: static
A14: Permeate 2 | B14: =IF(A14="","",IFERROR(INDEX(Streams!$A:$A, MATCH(A14, Streams!$B:$B, 0)), "enter the stream name")) -> S27 | C14: Waste | D14: =IF(C14="","",IFERROR(INDEX($S:$S, MATCH(C14, $R:$R, 0)), "enter input or output")) -> Output | E14: static
A15: Permeate 3 | B15: =IF(A15="","",IFERROR(INDEX(Streams!$A:$A, MATCH(A15, Streams!$B:$B, 0)), "enter the stream name")) -> S31 | C15: Waste | D15: =IF(C15="","",IFERROR(INDEX($S:$S, MATCH(C15, $R:$R, 0)), "enter input or output")) -> Output | E15: static
A16: Spray dried powder | B16: =IF(A16="","",IFERROR(INDEX(Streams!$A:$A, MATCH(A16, Streams!$B:$B, 0)), "enter the stream name")) -> S32 | C16: Product | D16: =IF(C16="","",IFERROR(INDEX($S:$S, MATCH(C16, $R:$R, 0)), "enter input or output")) -> Output | E16: linear_protein
A17: Water vapour 2 | B17: =IF(A17="","",IFERROR(INDEX(Streams!$A:$A, MATCH(A17, Streams!$B:$B, 0)), "enter the stream name")) -> S33 | C17: Waste | D17: =IF(C17="","",IFERROR(INDEX($S:$S, MATCH(C17, $R:$R, 0)), "enter input or output")) -> Output | E17: static
B18: =IF(A18="","",IFERROR(INDEX(Streams!$A:$A, MATCH(A18, Streams!$B:$B, 0)), "enter the stream name")) | D18: =IF(C18="","",IFERROR(INDEX($S:$S, MATCH(C18, $R:$R, 0)), "enter input or output"))
B19: =IF(A19="","",IFERROR(INDEX(Streams!$A:$A, MATCH(A19, Streams!$B:$B, 0)), "enter the stream name")) | D19: =IF(C19="","",IFERROR(INDEX($S:$S, MATCH(C19, $R:$R, 0)), "enter input or output"))
B20: =IF(A20="","",IFERROR(INDEX(Streams!$A:$A, MATCH(A20, Streams!$B:$B, 0)), "enter the stream name")) | D20: =IF(C20="","",IFERROR(INDEX($S:$S, MATCH(C20, $R:$R, 0)), "enter input or output"))
B21: =IF(A21="","",IFERROR(INDEX(Streams!$A:$A, MATCH(A21, Streams!$B:$B, 0)), "enter the stream name")) | D21: =IF(C21="","",IFERROR(INDEX($S:$S, MATCH(C21, $R:$R, 0)), "enter input or output"))
B22: =IF(A22="","",IFERROR(INDEX(Streams!$A:$A, MATCH(A22, Streams!$B:$B, 0)), "enter the stream name")) | D22: =IF(C22="","",IFERROR(INDEX($S:$S, MATCH(C22, $R:$R, 0)), "enter input or output"))
B23: =IF(A23="","",IFERROR(INDEX(Streams!$A:$A, MATCH(A23, Streams!$B:$B, 0)), "enter the stream name")) | D23: =IF(C23="","",IFERROR(INDEX($S:$S, MATCH(C23, $R:$R, 0)), "enter input or output"))
B24: =IF(A24="","",IFERROR(INDEX(Streams!$A:$A, MATCH(A24, Streams!$B:$B, 0)), "enter the stream name")) | D24: =IF(C24="","",IFERROR(INDEX($S:$S, MATCH(C24, $R:$R, 0)), "enter input or output"))
B25: =IF(A25="","",IFERROR(INDEX(Streams!$A:$A, MATCH(A25, Streams!$B:$B, 0)), "enter the stream name")) | D25: =IF(C25="","",IFERROR(INDEX($S:$S, MATCH(C25, $R:$R, 0)), "enter input or output"))
B26: =IF(A26="","",IFERROR(INDEX(Streams!$A:$A, MATCH(A26, Streams!$B:$B, 0)), "enter the stream name")) | D26: =IF(C26="","",IFERROR(INDEX($S:$S, MATCH(C26, $R:$R, 0)), "enter input or output"))
B27: =IF(A27="","",IFERROR(INDEX(Streams!$A:$A, MATCH(A27, Streams!$B:$B, 0)), "enter the stream name")) | D27: =IF(C27="","",IFERROR(INDEX($S:$S, MATCH(C27, $R:$R, 0)), "enter input or output"))
B28: =IF(A28="","",IFERROR(INDEX(Streams!$A:$A, MATCH(A28, Streams!$B:$B, 0)), "enter the stream name")) | D28: =IF(C28="","",IFERROR(INDEX($S:$S, MATCH(C28, $R:$R, 0)), "enter input or output"))
B29: =IF(A29="","",IFERROR(INDEX(Streams!$A:$A, MATCH(A29, Streams!$B:$B, 0)), "enter the stream name")) | D29: =IF(C29="","",IFERROR(INDEX($S:$S, MATCH(C29, $R:$R, 0)), "enter input or output"))
... B101: =IF(A101="","",IFERROR(INDEX(Streams!$A:$A, MATCH(A101, Streams!$B:$B, 0)), "enter the stream name")) | D101: =IF(C101="","",IFERROR(INDEX($S:$S, MATCH(C101, $R:$R, 0)), "enter input or output"))

Sheet Components
A1: StreamName | B1: StreamID | C1: Component | D1: Category | E1: Unit | O1: No. | P1: Tiers_of_components
A2: Peas | B2: =IF(A2="","",IFERROR(INDEX(Streams!$A:$A, MATCH(A2, Streams!$B:$B, 0)), "enter the stream name")) -> S1 | C2: Total mass | D2: Total | E2: kg | O2: 1 | P2: Total
A3: Peas | B3: =IF(A3="","",IFERROR(INDEX(Streams!$A:$A, MATCH(A3, Streams!$B:$B, 0)), "enter the stream name")) -> S1 | C3: Total Solids | D3: Solids | E3: kg | O3: 2 | P3: Solids
A4: Peas | B4: =IF(A4="","",IFERROR(INDEX(Streams!$A:$A, MATCH(A4, Streams!$B:$B, 0)), "enter the stream name")) -> S1 | C4: Ash | D4: Component | E4: kg | O4: 3 | P4: Component
A5: Peas | B5: =IF(A5="","",IFERROR(INDEX(Streams!$A:$A, MATCH(A5, Streams!$B:$B, 0)), "enter the stream name")) -> S1 | C5: Protein | D5: Component | E5: kg | O5: 4 | P5: Moisture
A6: Peas | B6: =IF(A6="","",IFERROR(INDEX(Streams!$A:$A, MATCH(A6, Streams!$B:$B, 0)), "enter the stream name")) -> S1 | C6: Fat | D6: Component | E6: kg
A7: Peas | B7: =IF(A7="","",IFERROR(INDEX(Streams!$A:$A, MATCH(A7, Streams!$B:$B, 0)), "enter the stream name")) -> S1 | C7: Starch | D7: Component | E7: kg
A8: Peas | B8: =IF(A8="","",IFERROR(INDEX(Streams!$A:$A, MATCH(A8, Streams!$B:$B, 0)), "enter the stream name")) -> S1 | C8: Sugars | D8: Component | E8: kg
A9: Peas | B9: =IF(A9="","",IFERROR(INDEX(Streams!$A:$A, MATCH(A9, Streams!$B:$B, 0)), "enter the stream name")) -> S1 | C9: Fibre | D9: Component | E9: kg
A10: Peas | B10: =IF(A10="","",IFERROR(INDEX(Streams!$A:$A, MATCH(A10, Streams!$B:$B, 0)), "enter the stream name")) -> S1 | C10: Other | D10: Component | E10: kg
A11: Peas | B11: =IF(A11="","",IFERROR(INDEX(Streams!$A:$A, MATCH(A11, Streams!$B:$B, 0)), "enter the stream name")) -> S1 | C11: Water | D11: Moisture | E11: kg
A12: NaOH solution | B12: =IF(A12="","",IFERROR(INDEX(Streams!$A:$A, MATCH(A12, Streams!$B:$B, 0)), "enter the stream name")) -> S5 | C12: Total mass | D12: Total | E12: kg
A13: NaOH solution | B13: =IF(A13="","",IFERROR(INDEX(Streams!$A:$A, MATCH(A13, Streams!$B:$B, 0)), "enter the stream name")) -> S5 | C13: Total Solids | D13: Solids | E13: kg
A14: NaOH solution | B14: =IF(A14="","",IFERROR(INDEX(Streams!$A:$A, MATCH(A14, Streams!$B:$B, 0)), "enter the stream name")) -> S5 | C14: NaOH | D14: Component | E14: kg
A15: NaOH solution | B15: =IF(A15="","",IFERROR(INDEX(Streams!$A:$A, MATCH(A15, Streams!$B:$B, 0)), "enter the stream name")) -> S5 | C15: Water | D15: Moisture | E15: kg
A16: Water 1 | B16: =IF(A16="","",IFERROR(INDEX(Streams!$A:$A, MATCH(A16, Streams!$B:$B, 0)), "enter the stream name")) -> S6 | C16: Total mass | D16: Total | E16: kg
A17: Water 1 | B17: =IF(A17="","",IFERROR(INDEX(Streams!$A:$A, MATCH(A17, Streams!$B:$B, 0)), "enter the stream name")) -> S6 | C17: Water | D17: Moisture | E17: kg
... A23: Water 4 | B23: =IF(A23="","",IFERROR(INDEX(Streams!$A:$A, MATCH(A23, Streams!$B:$B, 0)), "enter the stream name")) -> S25 | C23: Water | D23: Moisture | E23: kg

Sheet UnitOperations
A1: UnitID | B1: UnitName | C1: UnitClass | D1: PartitioningType | E1: Notes
A2: U1 | B2: Dehulling | C2: MyDehulling | D2: =IF(C2="","",IFERROR(INDEX(PythonUnitOps!$B$2:$B$98, MATCH(C2, PythonUnitOps!$A$2:$A$98, 0)), "enter the partitioning type")) -> Overall, Component
A3: U2 | B3: Milling | C3: MyImpactMilling | D3: =IF(C3="","",IFERROR(INDEX(PythonUnitOps!$B$2:$B$98, MATCH(C3, PythonUnitOps!$A$2:$A$98, 0)), "enter the partitioning type")) -> None
A4: U3 | B4: Wet extraction | C4: MyWetExtraction | D4: =IF(C4="","",IFERROR(INDEX(PythonUnitOps!$B$2:$B$98, MATCH(C4, PythonUnitOps!$A$2:$A$98, 0)), "enter the partitioning type")) -> None
A5: U4 | B5: Cooling | C5: MyCooling | D5: =IF(C5="","",IFERROR(INDEX(PythonUnitOps!$B$2:$B$98, MATCH(C5, PythonUnitOps!$A$2:$A$98, 0)), "enter the partitioning type")) -> None
A6: U5 | B6: Decanter centrifuge | C6: MyDecanterCentrifuge | D6: =IF(C6="","",IFERROR(INDEX(PythonUnitOps!$B$2:$B$98, MATCH(C6, PythonUnitOps!$A$2:$A$98, 0)), "enter the partitioning type")) -> Overall, Component
A7: U6 | B7: Clarification 1 | C7: MyClarifier | D7: =IF(C7="","",IFERROR(INDEX(PythonUnitOps!$B$2:$B$98, MATCH(C7, PythonUnitOps!$A$2:$A$98, 0)), "enter the partitioning type")) -> Overall, Component
A8: U7 | B8: Mixing 1 | C8: MyMixingTank | D8: =IF(C8="","",IFERROR(INDEX(PythonUnitOps!$B$2:$B$98, MATCH(C8, PythonUnitOps!$A$2:$A$98, 0)), "enter the partitioning type")) -> None
A9: U8 | B9: Clarification 2 | C9: MyClarifier | D9: =IF(C9="","",IFERROR(INDEX(PythonUnitOps!$B$2:$B$98, MATCH(C9, PythonUnitOps!$A$2:$A$98, 0)), "enter the partitioning type")) -> Overall, Component
A10: U9 | B10: Mixing 2 | C10: MyMixingTank | D10: =IF(C10="","",IFERROR(INDEX(PythonUnitOps!$B$2:$B$98, MATCH(C10, PythonUnitOps!$A$2:$A$98, 0)), "enter the partitioning type")) -> None
A11: U10 | B11: Clarification 3 | C11: MyClarifier | D11: =IF(C11="","",IFERROR(INDEX(PythonUnitOps!$B$2:$B$98, MATCH(C11, PythonUnitOps!$A$2:$A$98, 0)), "enter the partitioning type")) -> Overall, Component
A12: U11 | B12: Drum drying | C12: MyDrumDryer | D12: =IF(C12="","",IFERROR(INDEX(PythonUnitOps!$B$2:$B$98, MATCH(C12, PythonUnitOps!$A$2:$A$98, 0)), "enter the partitioning type")) -> Drying
A13: U12 | B13: Ultrafiltration | C13: MyUltrafiltration | D13: =IF(C13="","",IFERROR(INDEX(PythonUnitOps!$B$2:$B$98, MATCH(C13, PythonUnitOps!$A$2:$A$98, 0)), "enter the partitioning type")) -> MCF, RC
... A18: U17 | B18: Spray drying | C18: MySprayDryer | D18: =IF(C18="","",IFERROR(INDEX(PythonUnitOps!$B$2:$B$98, MATCH(C18, PythonUnitOps!$A$2:$A$98, 0)), "enter the partitioning type")) -> Drying
D19: =IF(C19="","",IFERROR(INDEX(PythonUnitOps!$B$2:$B$98, MATCH(C19, PythonUnitOps!$A$2:$A$98, 0)), "enter the partitioning type"))
D20: =IF(C20="","",IFERROR(INDEX(PythonUnitOps!$B$2:$B$98, MATCH(C20, PythonUnitOps!$A$2:$A$98, 0)), "enter the partitioning type"))
D21: =IF(C21="","",IFERROR(INDEX(PythonUnitOps!$B$2:$B$98, MATCH(C21, PythonUnitOps!$A$2:$A$98, 0)), "enter the partitioning type"))
D22: =IF(C22="","",IFERROR(INDEX(PythonUnitOps!$B$2:$B$98, MATCH(C22, PythonUnitOps!$A$2:$A$98, 0)), "enter the partitioning type"))
D23: =IF(C23="","",IFERROR(INDEX(PythonUnitOps!$B$2:$B$98, MATCH(C23, PythonUnitOps!$A$2:$A$98, 0)), "enter the partitioning type"))
D24: =IF(C24="","",IFERROR(INDEX(PythonUnitOps!$B$2:$B$98, MATCH(C24, PythonUnitOps!$A$2:$A$98, 0)), "enter the partitioning type"))
D25: =IF(C25="","",IFERROR(INDEX(PythonUnitOps!$B$2:$B$98, MATCH(C25, PythonUnitOps!$A$2:$A$98, 0)), "enter the partitioning type"))
D26: =IF(C26="","",IFERROR(INDEX(PythonUnitOps!$B$2:$B$98, MATCH(C26, PythonUnitOps!$A$2:$A$98, 0)), "enter the partitioning type"))
D27: =IF(C27="","",IFERROR(INDEX(PythonUnitOps!$B$2:$B$98, MATCH(C27, PythonUnitOps!$A$2:$A$98, 0)), "enter the partitioning type"))
D28: =IF(C28="","",IFERROR(INDEX(PythonUnitOps!$B$2:$B$98, MATCH(C28, PythonUnitOps!$A$2:$A$98, 0)), "enter the partitioning type"))
D29: =IF(C29="","",IFERROR(INDEX(PythonUnitOps!$B$2:$B$98, MATCH(C29, PythonUnitOps!$A$2:$A$98, 0)), "enter the partitioning type"))
D30: =IF(C30="","",IFERROR(INDEX(PythonUnitOps!$B$2:$B$98, MATCH(C30, PythonUnitOps!$A$2:$A$98, 0)), "enter the partitioning type"))
... D92: =IF(C92="","",IFERROR(INDEX(PythonUnitOps!$B$2:$B$98, MATCH(C92, PythonUnitOps!$A$2:$A$98, 0)), "enter the partitioning type"))
D93: =IF(C93="","",IFERROR(INDEX(PythonUnitOps!$B$2:$B$100, MATCH(C93, PythonUnitOps!$A$2:$A$100, 0)), "enter the partitioning type"))
D94: =IF(C94="","",IFERROR(INDEX(PythonUnitOps!$B$2:$B$100, MATCH(C94, PythonUnitOps!$A$2:$A$100, 0)), "enter the partitioning type"))
D95: =IF(C95="","",IFERROR(INDEX(PythonUnitOps!$B$2:$B$100, MATCH(C95, PythonUnitOps!$A$2:$A$100, 0)), "enter the partitioning type"))
D96: =IF(C96="","",IFERROR(INDEX(PythonUnitOps!$B$2:$B$100, MATCH(C96, PythonUnitOps!$A$2:$A$100, 0)), "enter the partitioning type"))
D97: =IF(C97="","",IFERROR(INDEX(PythonUnitOps!$B$2:$B$100, MATCH(C97, PythonUnitOps!$A$2:$A$100, 0)), "enter the partitioning type"))
D98: =IF(C98="","",IFERROR(INDEX(PythonUnitOps!$B$2:$B$100, MATCH(C98, PythonUnitOps!$A$2:$A$100, 0)), "enter the partitioning type"))
D99: =IF(C99="","",IFERROR(INDEX(PythonUnitOps!$B$2:$B$100, MATCH(C99, PythonUnitOps!$A$2:$A$100, 0)), "enter the partitioning type"))
D100: =IF(C100="","",IFERROR(INDEX(PythonUnitOps!$B$2:$B$100, MATCH(C100, PythonUnitOps!$A$2:$A$100, 0)), "enter the partitioning type"))
D101: =IF(C101="","",IFERROR(INDEX(PythonUnitOps!$B$2:$B$100, MATCH(C101, PythonUnitOps!$A$2:$A$100, 0)), "enter the partitioning type"))

Sheet Flowsheet
A1: Step | B1: UnitID | C1: UnitName | D1: PartitioningType | E1: Number of inlets | F1: Number of outlets | G1: Inlet 1 Name | H1: Inlet 1 StreamID | I1: Inlet 2 Name | J1: Inlet 2 StreamID | K1: Inlet 3 Name | L1: Inlet 3 StreamID | M1: Outlet 1 Name | N1: Outlet 1 StreamID | O1: Outlet 2 Name | P1: Outlet 2 StreamID
A2: 1 | B2: U1 | C2: =IF(B2="","",IFERROR(INDEX(UnitOperations!B:B, MATCH(B2, UnitOperations!A:A, 0)), "enter the unit name")) -> Dehulling | D2: =IF(B2="","",IFERROR(INDEX(UnitOperations!D:D, MATCH(B2, UnitOperations!A:A, 0)), "enter the unit name")) -> Overall, Component | E2: 1 | F2: 2 | G2: Peas | H2: =IF(G2="","",IFERROR(INDEX(Streams!$A:$A, MATCH(G2, Streams!$B:$B, 0)), "enter the stream name")) -> S1 | J2: =IF(I2="","",IFERROR(INDEX(Streams!$A:$A, MATCH(I2, Streams!$B:$B, 0)), "enter the stream name")) | L2: =IF(K2="","",IFERROR(INDEX(Streams!$A:$A, MATCH(K2, Streams!$B:$B, 0)), "enter the stream name")) | M2: Dehulled peas | N2: =IF(M2="","",IFERROR(INDEX(Streams!$A:$A, MATCH(M2, Streams!$B:$B, 0)), "enter the stream name")) -> S2 | O2: Hulls | P2: =IF(O2="","",IFERROR(INDEX(Streams!$A:$A, MATCH(O2, Streams!$B:$B, 0)), "enter the stream name")) -> S3
A3: 2 | B3: U2 | C3: =IF(B3="","",IFERROR(INDEX(UnitOperations!B:B, MATCH(B3, UnitOperations!A:A, 0)), "enter the unit name")) -> Milling | D3: =IF(B3="","",IFERROR(INDEX(UnitOperations!D:D, MATCH(B3, UnitOperations!A:A, 0)), "enter the unit name")) -> None | E3: 1 | F3: 1 | G3: Dehulled peas | H3: =IF(G3="","",IFERROR(INDEX(Streams!$A:$A, MATCH(G3, Streams!$B:$B, 0)), "enter the stream name")) -> S2 | J3: =IF(I3="","",IFERROR(INDEX(Streams!$A:$A, MATCH(I3, Streams!$B:$B, 0)), "enter the stream name")) | L3: =IF(K3="","",IFERROR(INDEX(Streams!$A:$A, MATCH(K3, Streams!$B:$B, 0)), "enter the stream name")) | M3: Dehulled pea flour | N3: =IF(M3="","",IFERROR(INDEX(Streams!$A:$A, MATCH(M3, Streams!$B:$B, 0)), "enter the stream name")) -> S4 | P3: =IF(O3="","",IFERROR(INDEX(Streams!$A:$A, MATCH(O3, Streams!$B:$B, 0)), "enter the stream name"))
A4: 3 | B4: U3 | C4: =IF(B4="","",IFERROR(INDEX(UnitOperations!B:B, MATCH(B4, UnitOperations!A:A, 0)), "enter the unit name")) -> Wet extraction | D4: =IF(B4="","",IFERROR(INDEX(UnitOperations!D:D, MATCH(B4, UnitOperations!A:A, 0)), "enter the unit name")) -> None | E4: 3 | F4: 1 | G4: Dehulled pea flour | H4: =IF(G4="","",IFERROR(INDEX(Streams!$A:$A, MATCH(G4, Streams!$B:$B, 0)), "enter the stream name")) -> S4 | I4: NaOH solution | J4: =IF(I4="","",IFERROR(INDEX(Streams!$A:$A, MATCH(I4, Streams!$B:$B, 0)), "enter the stream name")) -> S5 | K4: Water 1 | L4: =IF(K4="","",IFERROR(INDEX(Streams!$A:$A, MATCH(K4, Streams!$B:$B, 0)), "enter the stream name")) -> S6 | M4: Heat treated slurry | N4: =IF(M4="","",IFERROR(INDEX(Streams!$A:$A, MATCH(M4, Streams!$B:$B, 0)), "enter the stream name")) -> S7 | P4: =IF(O4="","",IFERROR(INDEX(Streams!$A:$A, MATCH(O4, Streams!$B:$B, 0)), "enter the stream name"))
A5: 4 | B5: U4 | C5: =IF(B5="","",IFERROR(INDEX(UnitOperations!B:B, MATCH(B5, UnitOperations!A:A, 0)), "enter the unit name")) -> Cooling | D5: =IF(B5="","",IFERROR(INDEX(UnitOperations!D:D, MATCH(B5, UnitOperations!A:A, 0)), "enter the unit name")) -> None | E5: 1 | F5: 1 | G5: Heat treated slurry | H5: =IF(G5="","",IFERROR(INDEX(Streams!$A:$A, MATCH(G5, Streams!$B:$B, 0)), "enter the stream name")) -> S7 | J5: =IF(I5="","",IFERROR(INDEX(Streams!$A:$A, MATCH(I5, Streams!$B:$B, 0)), "enter the stream name")) | L5: =IF(K5="","",IFERROR(INDEX(Streams!$A:$A, MATCH(K5, Streams!$B:$B, 0)), "enter the stream name")) | M5: Cooled slurry | N5: =IF(M5="","",IFERROR(INDEX(Streams!$A:$A, MATCH(M5, Streams!$B:$B, 0)), "enter the stream name")) -> S8 | P5: =IF(O5="","",IFERROR(INDEX(Streams!$A:$A, MATCH(O5, Streams!$B:$B, 0)), "enter the stream name"))
A6: 5 | B6: U5 | C6: =IF(B6="","",IFERROR(INDEX(UnitOperations!B:B, MATCH(B6, UnitOperations!A:A, 0)), "enter the unit name")) -> Decanter centrifuge | D6: =IF(B6="","",IFERROR(INDEX(UnitOperations!D:D, MATCH(B6, UnitOperations!A:A, 0)), "enter the unit name")) -> Overall, Component | E6: 1 | F6: 2 | G6: Cooled slurry | H6: =IF(G6="","",IFERROR(INDEX(Streams!$A:$A, MATCH(G6, Streams!$B:$B, 0)), "enter the stream name")) -> S8 | J6: =IF(I6="","",IFERROR(INDEX(Streams!$A:$A, MATCH(I6, Streams!$B:$B, 0)), "enter the stream name")) | L6: =IF(K6="","",IFERROR(INDEX(Streams!$A:$A, MATCH(K6, Streams!$B:$B, 0)), "enter the stream name")) | M6: Supernatant 1 | N6: =IF(M6="","",IFERROR(INDEX(Streams!$A:$A, MATCH(M6, Streams!$B:$B, 0)), "enter the stream name")) -> S10 | O6: Sludge | P6: =IF(O6="","",IFERROR(INDEX(Streams!$A:$A, MATCH(O6, Streams!$B:$B, 0)), "enter the stream name")) -> S9
A7: 6 | B7: U6 | C7: =IF(B7="","",IFERROR(INDEX(UnitOperations!B:B, MATCH(B7, UnitOperations!A:A, 0)), "enter the unit name")) -> Clarification 1 | D7: =IF(B7="","",IFERROR(INDEX(UnitOperations!D:D, MATCH(B7, UnitOperations!A:A, 0)), "enter the unit name")) -> Overall, Component | E7: 1 | F7: 2 | G7: Sludge | H7: =IF(G7="","",IFERROR(INDEX(Streams!$A:$A, MATCH(G7, Streams!$B:$B, 0)), "enter the stream name")) -> S9 | J7: =IF(I7="","",IFERROR(INDEX(Streams!$A:$A, MATCH(I7, Streams!$B:$B, 0)), "enter the stream name")) | L7: =IF(K7="","",IFERROR(INDEX(Streams!$A:$A, MATCH(K7, Streams!$B:$B, 0)), "enter the stream name")) | M7: Sediment 1 | N7: =IF(M7="","",IFERROR(INDEX(Streams!$A:$A, MATCH(M7, Streams!$B:$B, 0)), "enter the stream name")) -> S11 | O7: Whey 1 | P7: =IF(O7="","",IFERROR(INDEX(Streams!$A:$A, MATCH(O7, Streams!$B:$B, 0)), "enter the stream name")) -> S12
A8: 7 | B8: U7 | C8: =IF(B8="","",IFERROR(INDEX(UnitOperations!B:B, MATCH(B8, UnitOperations!A:A, 0)), "enter the unit name")) -> Mixing 1 | D8: =IF(B8="","",IFERROR(INDEX(UnitOperations!D:D, MATCH(B8, UnitOperations!A:A, 0)), "enter the unit name")) -> None | E8: 2 | F8: 1 | G8: Sediment 1 | H8: =IF(G8="","",IFERROR(INDEX(Streams!$A:$A, MATCH(G8, Streams!$B:$B, 0)), "enter the stream name")) -> S11 | I8: Water 2 | J8: =IF(I8="","",IFERROR(INDEX(Streams!$A:$A, MATCH(I8, Streams!$B:$B, 0)), "enter the stream name")) -> S13 | L8: =IF(K8="","",IFERROR(INDEX(Streams!$A:$A, MATCH(K8, Streams!$B:$B, 0)), "enter the stream name")) | M8: Suspension 1 | N8: =IF(M8="","",IFERROR(INDEX(Streams!$A:$A, MATCH(M8, Streams!$B:$B, 0)), "enter the stream name")) -> S14 | P8: =IF(O8="","",IFERROR(INDEX(Streams!$A:$A, MATCH(O8, Streams!$B:$B, 0)), "enter the stream name"))
A9: 8 | B9: U8 | C9: =IF(B9="","",IFERROR(INDEX(UnitOperations!B:B, MATCH(B9, UnitOperations!A:A, 0)), "enter the unit name")) -> Clarification 2 | D9: =IF(B9="","",IFERROR(INDEX(UnitOperations!D:D, MATCH(B9, UnitOperations!A:A, 0)), "enter the unit name")) -> Overall, Component | E9: 1 | F9: 2 | G9: Suspension 1 | H9: =IF(G9="","",IFERROR(INDEX(Streams!$A:$A, MATCH(G9, Streams!$B:$B, 0)), "enter the stream name")) -> S14 | J9: =IF(I9="","",IFERROR(INDEX(Streams!$A:$A, MATCH(I9, Streams!$B:$B, 0)), "enter the stream name")) | L9: =IF(K9="","",IFERROR(INDEX(Streams!$A:$A, MATCH(K9, Streams!$B:$B, 0)), "enter the stream name")) | M9: Sediment 2 | N9: =IF(M9="","",IFERROR(INDEX(Streams!$A:$A, MATCH(M9, Streams!$B:$B, 0)), "enter the stream name")) -> S15 | O9: Whey 2 | P9: =IF(O9="","",IFERROR(INDEX(Streams!$A:$A, MATCH(O9, Streams!$B:$B, 0)), "enter the stream name")) -> S16
A10: 9 | B10: U9 | C10: =IF(B10="","",IFERROR(INDEX(UnitOperations!B:B, MATCH(B10, UnitOperations!A:A, 0)), "enter the unit name")) -> Mixing 2 | D10: =IF(B10="","",IFERROR(INDEX(UnitOperations!D:D, MATCH(B10, UnitOperations!A:A, 0)), "enter the unit name")) -> None | E10: 2 | F10: 1 | G10: Sediment 2 | H10: =IF(G10="","",IFERROR(INDEX(Streams!$A:$A, MATCH(G10, Streams!$B:$B, 0)), "enter the stream name")) -> S15 | I10: Water 3 | J10: =IF(I10="","",IFERROR(INDEX(Streams!$A:$A, MATCH(I10, Streams!$B:$B, 0)), "enter the stream name")) -> S17 | L10: =IF(K10="","",IFERROR(INDEX(Streams!$A:$A, MATCH(K10, Streams!$B:$B, 0)), "enter the stream name")) | M10: Suspension 2 | N10: =IF(M10="","",IFERROR(INDEX(Streams!$A:$A, MATCH(M10, Streams!$B:$B, 0)), "enter the stream name")) -> S18 | P10: =IF(O10="","",IFERROR(INDEX(Streams!$A:$A, MATCH(O10, Streams!$B:$B, 0)), "enter the stream name"))
A11: 10 | B11: U10 | C11: =IF(B11="","",IFERROR(INDEX(UnitOperations!B:B, MATCH(B11, UnitOperations!A:A, 0)), "enter the unit name")) -> Clarification 3 | D11: =IF(B11="","",IFERROR(INDEX(UnitOperations!D:D, MATCH(B11, UnitOperations!A:A, 0)), "enter the unit name")) -> Overall, Component | E11: 1 | F11: 2 | G11: Suspension 2 | H11: =IF(G11="","",IFERROR(INDEX(Streams!$A:$A, MATCH(G11, Streams!$B:$B, 0)), "enter the stream name")) -> S18 | J11: =IF(I11="","",IFERROR(INDEX(Streams!$A:$A, MATCH(I11, Streams!$B:$B, 0)), "enter the stream name")) | L11: =IF(K11="","",IFERROR(INDEX(Streams!$A:$A, MATCH(K11, Streams!$B:$B, 0)), "enter the stream name")) | M11: Sediment 3 | N11: =IF(M11="","",IFERROR(INDEX(Streams!$A:$A, MATCH(M11, Streams!$B:$B, 0)), "enter the stream name")) -> S19 | O11: Whey 3 | P11: =IF(O11="","",IFERROR(INDEX(Streams!$A:$A, MATCH(O11, Streams!$B:$B, 0)), "enter the stream name")) -> S20
A12: 11 | B12: U11 | C12: =IF(B12="","",IFERROR(INDEX(UnitOperations!B:B, MATCH(B12, UnitOperations!A:A, 0)), "enter the unit name")) -> Drum drying | D12: =IF(B12="","",IFERROR(INDEX(UnitOperations!D:D, MATCH(B12, UnitOperations!A:A, 0)), "enter the unit name")) -> Drying | E12: 1 | F12: 2 | G12: Sediment 3 | H12: =IF(G12="","",IFERROR(INDEX(Streams!$A:$A, MATCH(G12, Streams!$B:$B, 0)), "enter the stream name")) -> S19 | J12: =IF(I12="","",IFERROR(INDEX(Streams!$A:$A, MATCH(I12, Streams!$B:$B, 0)), "enter the stream name")) | L12: =IF(K12="","",IFERROR(INDEX(Streams!$A:$A, MATCH(K12, Streams!$B:$B, 0)), "enter the stream name")) | M12: Dried sediment | N12: =IF(M12="","",IFERROR(INDEX(Streams!$A:$A, MATCH(M12, Streams!$B:$B, 0)), "enter the stream name")) -> S21 | O12: Water vapour 1 | P12: =IF(O12="","",IFERROR(INDEX(Streams!$A:$A, MATCH(O12, Streams!$B:$B, 0)), "enter the stream name")) -> S22
A13: 12 | B13: U12 | C13: =IF(B13="","",IFERROR(INDEX(UnitOperations!B:B, MATCH(B13, UnitOperations!A:A, 0)), "enter the unit name")) -> Ultrafiltration | D13: =IF(B13="","",IFERROR(INDEX(UnitOperations!D:D, MATCH(B13, UnitOperations!A:A, 0)), "enter the unit name")) -> MCF, RC | E13: 1 | F13: 2 | G13: Supernatant 1 | H13: =IF(G13="","",IFERROR(INDEX(Streams!$A:$A, MATCH(G13, Streams!$B:$B, 0)), "enter the stream name")) -> S10 | J13: =IF(I13="","",IFERROR(INDEX(Streams!$A:$A, MATCH(I13, Streams!$B:$B, 0)), "enter the stream name")) | L13: =IF(K13="","",IFERROR(INDEX(Streams!$A:$A, MATCH(K13, Streams!$B:$B, 0)), "enter the stream name")) | M13: Retentate 1 | N13: =IF(M13="","",IFERROR(INDEX(Streams!$A:$A, MATCH(M13, Streams!$B:$B, 0)), "enter the stream name")) -> S23 | O13: Permeate 1 | P13: =IF(O13="","",IFERROR(INDEX(Streams!$A:$A, MATCH(O13, Streams!$B:$B, 0)), "enter the stream name")) -> S24
A14: 13 | B14: U13 | C14: =IF(B14="","",IFERROR(INDEX(UnitOperations!B:B, MATCH(B14, UnitOperations!A:A, 0)), "enter the unit name")) -> Diafiltration | D14: =IF(B14="","",IFERROR(INDEX(UnitOperations!D:D, MATCH(B14, UnitOperations!A:A, 0)), "enter the unit name")) -> DF, RC | E14: 2 | F14: 2 | G14: Retentate 1 | H14: =IF(G14="","",IFERROR(INDEX(Streams!$A:$A, MATCH(G14, Streams!$B:$B, 0)), "enter the stream name")) -> S23 | I14: Water 4 | J14: =IF(I14="","",IFERROR(INDEX(Streams!$A:$A, MATCH(I14, Streams!$B:$B, 0)), "enter the stream name")) -> S25 | L14: =IF(K14="","",IFERROR(INDEX(Streams!$A:$A, MATCH(K14, Streams!$B:$B, 0)), "enter the stream name")) | M14: Retentate 2 | N14: =IF(M14="","",IFERROR(INDEX(Streams!$A:$A, MATCH(M14, Streams!$B:$B, 0)), "enter the stream name")) -> S26 | O14: Permeate 2 | P14: =IF(O14="","",IFERROR(INDEX(Streams!$A:$A, MATCH(O14, Streams!$B:$B, 0)), "enter the stream name")) -> S27
A15: 14 | B15: U14 | C15: =IF(B15="","",IFERROR(INDEX(UnitOperations!B:B, MATCH(B15, UnitOperations!A:A, 0)), "enter the unit name")) -> Pasteurisation | D15: =IF(B15="","",IFERROR(INDEX(UnitOperations!D:D, MATCH(B15, UnitOperations!A:A, 0)), "enter the unit name")) -> None | E15: 1 | F15: 1 | G15: Retentate 2 | H15: =IF(G15="","",IFERROR(INDEX(Streams!$A:$A, MATCH(G15, Streams!$B:$B, 0)), "enter the stream name")) -> S26 | J15: =IF(I15="","",IFERROR(INDEX(Streams!$A:$A, MATCH(I15, Streams!$B:$B, 0)), "enter the stream name")) | L15: =IF(K15="","",IFERROR(INDEX(Streams!$A:$A, MATCH(K15, Streams!$B:$B, 0)), "enter the stream name")) | M15: Pasteurised retentate | N15: =IF(M15="","",IFERROR(INDEX(Streams!$A:$A, MATCH(M15, Streams!$B:$B, 0)), "enter the stream name")) -> S28 | P15: =IF(O15="","",IFERROR(INDEX(Streams!$A:$A, MATCH(O15, Streams!$B:$B, 0)), "enter the stream name"))
A16: 15 | B16: U15 | C16: =IF(B16="","",IFERROR(INDEX(UnitOperations!B:B, MATCH(B16, UnitOperations!A:A, 0)), "enter the unit name")) -> Holding Tube | D16: =IF(B16="","",IFERROR(INDEX(UnitOperations!D:D, MATCH(B16, UnitOperations!A:A, 0)), "enter the unit name")) -> None | E16: 1 | F16: 1 | G16: Pasteurised retentate | H16: =IF(G16="","",IFERROR(INDEX(Streams!$A:$A, MATCH(G16, Streams!$B:$B, 0)), "enter the stream name")) -> S28 | J16: =IF(I16="","",IFERROR(INDEX(Streams!$A:$A, MATCH(I16, Streams!$B:$B, 0)), "enter the stream name")) | L16: =IF(K16="","",IFERROR(INDEX(Streams!$A:$A, MATCH(K16, Streams!$B:$B, 0)), "enter the stream name")) | M16: Hold retentate | N16: =IF(M16="","",IFERROR(INDEX(Streams!$A:$A, MATCH(M16, Streams!$B:$B, 0)), "enter the stream name")) -> S29 | P16: =IF(O16="","",IFERROR(INDEX(Streams!$A:$A, MATCH(O16, Streams!$B:$B, 0)), "enter the stream name"))
A17: 16 | B17: U16 | C17: =IF(B17="","",IFERROR(INDEX(UnitOperations!B:B, MATCH(B17, UnitOperations!A:A, 0)), "enter the unit name")) -> Reverse osmosis | D17: =IF(B17="","",IFERROR(INDEX(UnitOperations!D:D, MATCH(B17, UnitOperations!A:A, 0)), "enter the unit name")) -> MCF, RC | E17: 1 | F17: 2 | G17: Hold retentate | H17: =IF(G17="","",IFERROR(INDEX(Streams!$A:$A, MATCH(G17, Streams!$B:$B, 0)), "enter the stream name")) -> S29 | J17: =IF(I17="","",IFERROR(INDEX(Streams!$A:$A, MATCH(I17, Streams!$B:$B, 0)), "enter the stream name")) | L17: =IF(K17="","",IFERROR(INDEX(Streams!$A:$A, MATCH(K17, Streams!$B:$B, 0)), "enter the stream name")) | M17: Retentate 3 | N17: =IF(M17="","",IFERROR(INDEX(Streams!$A:$A, MATCH(M17, Streams!$B:$B, 0)), "enter the stream name")) -> S30 | O17: Permeate 3 | P17: =IF(O17="","",IFERROR(INDEX(Streams!$A:$A, MATCH(O17, Streams!$B:$B, 0)), "enter the stream name")) -> S31
A18: 17 | B18: U17 | C18: =IF(B18="","",IFERROR(INDEX(UnitOperations!B:B, MATCH(B18, UnitOperations!A:A, 0)), "enter the unit name")) -> Spray drying | D18: =IF(B18="","",IFERROR(INDEX(UnitOperations!D:D, MATCH(B18, UnitOperations!A:A, 0)), "enter the unit name")) -> Drying | E18: 1 | F18: 2 | G18: Retentate 3 | H18: =IF(G18="","",IFERROR(INDEX(Streams!$A:$A, MATCH(G18, Streams!$B:$B, 0)), "enter the stream name")) -> S30 | J18: =IF(I18="","",IFERROR(INDEX(Streams!$A:$A, MATCH(I18, Streams!$B:$B, 0)), "enter the stream name")) | L18: =IF(K18="","",IFERROR(INDEX(Streams!$A:$A, MATCH(K18, Streams!$B:$B, 0)), "enter the stream name")) | M18: Spray dried powder | N18: =IF(M18="","",IFERROR(INDEX(Streams!$A:$A, MATCH(M18, Streams!$B:$B, 0)), "enter the stream name")) -> S32 | O18: Water vapour 2 | P18: =IF(O18="","",IFERROR(INDEX(Streams!$A:$A, MATCH(O18, Streams!$B:$B, 0)), "enter the stream name")) -> S33

Sheet ProcessInputs
A1: StreamID | B1: Parameter | C1: Identifier | D1: Category | E1: Value | F1: Unit
A2: S1 | B2: Basismass | C2: S1.Basismass | D2: Total | E2: 100
A3: S1 | B3: Total mass | C3: S1.Total mass | D3: Total | E3: 1 | F3: kg/kg
A4: S1 | B4: Total Solids | C4: S1.Total Solids | D4: Solids | E4: 0.884 | F4: kg/kg
A5: S1 | B5: Ash | C5: S1.Ash | D5: Component | E5: 0.034 | F5: kg/kg
A6: S1 | B6: Protein | C6: S1.Protein | D6: Component | E6: 0.232 | F6: kg/kg
A7: S1 | B7: Fat | C7: S1.Fat | D7: Component | E7: 0.016 | F7: kg/kg
A8: S1 | B8: Starch | C8: S1.Starch | D8: Component | E8: 0.224 | F8: kg/kg
A9: S1 | B9: Sugars | C9: S1.Sugars | D9: Component | E9: 0.056 | F9: kg/kg
A10: S1 | B10: Fibre | C10: S1.Fibre | D10: Component | E10: 0.322 | F10: kg/kg
A11: S1 | B11: Other | C11: S1.Other | D11: Component | F11: kg/kg
A12: S1 | B12: Water | C12: S1.Water | D12: Moisture | E12: 0.116 | F12: kg/kg
A13: S5 | B13: Basismass | C13: S5.Basismass | D13: Total | E13: 5.052529
A14: S5 | B14: Total mass | C14: S5.Total mass | D14: Total | E14: 1 | F14: kg/kg
A15: S5 | B15: Total Solids | C15: S5.Total Solids | D15: Solids | E15: 0.08 | F15: kg/kg
A16: S5 | B16: NaOH | C16: S5.NaOH | D16: Component | E16: 0.08 | F16: kg/kg
A17: S5 | B17: Water | C17: S5.Water | D17: Moisture | E17: 0.92 | F17: kg/kg
A18: S6 | B18: Basismass | C18: S6.Basismass | D18: Total | E18: 1121.36
A19: S6 | B19: Total mass | C19: S6.Total mass | D19: Total | E19: 1 | F19: kg/kg
A20: S6 | B20: Water | C20: S6.Water | D20: Moisture | E20: 1 | F20: kg/kg
A21: S13 | B21: Basismass | C21: S13.Basismass | D21: Total | E21: 127.807
A22: S13 | B22: Total mass | C22: S13.Total mass | D22: Total | E22: 1 | F22: kg/kg
A23: S13 | B23: Water | C23: S13.Water | D23: Moisture | E23: 1 | F23: kg/kg
A24: S17 | B24: Basismass | C24: S17.Basismass | D24: Total | E24: 121.77
A25: S17 | B25: Total mass | C25: S17.Total mass | D25: Total | E25: 1 | F25: kg/kg
A26: S17 | B26: Water | C26: S17.Water | D26: Moisture | E26: 1 | F26: kg/kg
A27: S25 | B27: Basismass | C27: S25.Basismass | D27: Total | E27: 0
A28: S25 | B28: Total mass | C28: S25.Total mass | D28: Total | E28: 1 | F28: kg/kg
A29: S25 | B29: Water | C29: S25.Water | D29: Moisture | E29: 1 | F29: kg/kg

Sheet PartitioningCoefficients
A1: Unit ID | B1: Unit Name | C1: Component | D1: Category | E1: PartitioningType | F1: UniqueID | G1: Parameter | H1: MCF/RC | I1: Final Moisture | J1: Outlet 1 Parameter | K1: Outlet 2 Parameter
A2: U1 | B2: Dehulling | C2: Total mass | D2: Total | E2: overall | F2: U1.Total mass | G2: Outlet 1 Parameter;Outlet 2 Parameter | J2: 0.90881824 | K2: 0.091181764
A3: U1 | B3: Dehulling | C3: Total Solids | D3: Solids | E3: component | F3: U1.Total Solids | G3: Outlet 1 Parameter;Outlet 2 Parameter
A4: U1 | B4: Dehulling | C4: Ash | D4: Component | E4: component | F4: U1.Ash | G4: Outlet 1 Parameter;Outlet 2 Parameter | J4: 0.022392431 | K4: 0.03309939
A5: U1 | B5: Dehulling | C5: Protein | D5: Component | E5: component | F5: U1.Protein | G5: Outlet 1 Parameter;Outlet 2 Parameter | J5: 0.2447833 | K5: 0.076999276
A6: U1 | B6: Dehulling | C6: Fat | D6: Component | E6: component | F6: U1.Fat | G6: Outlet 1 Parameter;Outlet 2 Parameter | J6: 0.042999993 | K6: 0.0099999984
A7: U1 | B7: Dehulling | C7: Starch | D7: Component | E7: component | F7: U1.Starch | G7: Outlet 1 Parameter;Outlet 2 Parameter | J7: 0.269 | K7: 0
A8: U1 | B8: Dehulling | C8: Sugars | D8: Component | E8: component | F8: U1.Sugars | G8: Outlet 1 Parameter;Outlet 2 Parameter | J8: 1 | K8: 1
A9: U1 | B9: Dehulling | C9: Fibre | D9: Component | E9: component | F9: U1.Fibre | G9: Outlet 1 Parameter;Outlet 2 Parameter | J9: 0.31104804 | K9: 0.7115744
A10: U1 | B10: Dehulling | C10: Other | D10: Component | E10: component | F10: U1.Other | G10: Outlet 1 Parameter;Outlet 2 Parameter | J10: 0 | K10: 0.06
A11: U1 | B11: Dehulling | C11: NaOH | D11: Component | E11: component | F11: U1.NaOH | G11: Outlet 1 Parameter;Outlet 2 Parameter
A12: U5 | B12: Decanter centrifuge | C12: Total mass | D12: Total | E12: overall | F12: U5.Total mass | G12: Outlet 1 Parameter;Outlet 2 Parameter | J12: 0.7535376 | K12: 0.2464624
A13: U5 | B13: Decanter centrifuge | C13: Total Solids | D13: Solids | E13: component | F13: U5.Total Solids | G13: Outlet 1 Parameter;Outlet 2 Parameter
A14: U5 | B14: Decanter centrifuge | C14: Ash | D14: Component | E14: component | F14: U5.Ash | G14: Outlet 1 Parameter;Outlet 2 Parameter | J14: 0.0030696532 | K14: 0.0019529349
A15: U5 | B15: Decanter centrifuge | C15: Protein | D15: Component | E15: component | F15: U5.Protein | G15: Outlet 1 Parameter;Outlet 2 Parameter | J15: 0.016960113 | K15: 0.01912837
A16: U5 | B16: Decanter centrifuge | C16: Fat | D16: Component | E16: component | F16: U5.Fat | G16: Outlet 1 Parameter;Outlet 2 Parameter | J16: 0.0012714643 | K16: 0.0041719549
A17: U5 | B17: Decanter centrifuge | C17: Starch | D17: Component | E17: component | F17: U5.Starch | G17: Outlet 1 Parameter;Outlet 2 Parameter | J17: 0.0010373626 | K17: 0.0050311255
A18: U5 | B18: Decanter centrifuge | C18: Sugars | D18: Component | E18: component | F18: U5.Sugars | G18: Outlet 1 Parameter;Outlet 2 Parameter | J18: 0.004 | K18: 0.001
A19: U5 | B19: Decanter centrifuge | C19: Fibre | D19: Component | E19: component | F19: U5.Fibre | G19: Outlet 1 Parameter;Outlet 2 Parameter | J19: 0.013162367 | K19: 0.067212539
A20: U5 | B20: Decanter centrifuge | C20: Other | D20: Component | E20: component | F20: U5.Other | G20: Outlet 1 Parameter;Outlet 2 Parameter | J20: 1 | K20: 1
A21: U5 | B21: Decanter centrifuge | C21: NaOH | D21: Component | E21: component | F21: U5.NaOH | G21: Outlet 1 Parameter;Outlet 2 Parameter
A22: U6 | B22: Clarification 1 | C22: Total mass | D22: Total | E22: overall | F22: U6.Total mass | G22: Outlet 1 Parameter;Outlet 2 Parameter | J22: 0.42597337 | K22: 0.57402663
A23: U6 | B23: Clarification 1 | C23: Total Solids | D23: Solids | E23: component | F23: U6.Total Solids | G23: Outlet 1 Parameter;Outlet 2 Parameter
A24: U6 | B24: Clarification 1 | C24: Ash | D24: Component | E24: component | F24: U6.Ash | G24: Outlet 1 Parameter;Outlet 2 Parameter | J24: 0.0035842234 | K24: 0.00082931546
A25: U6 | B25: Clarification 1 | C25: Protein | D25: Component | E25: component | F25: U6.Protein | G25: Outlet 1 Parameter;Outlet 2 Parameter | J25: 0.034321718 | K25: 0.0085180408
A26: U6 | B26: Clarification 1 | C26: Fat | D26: Component | E26: component | F26: U6.Fat | G26: Outlet 1 Parameter;Outlet 2 Parameter | J26: 0.010235914 | K26: 0.0028716104
A27: U6 | B27: Clarification 1 | C27: Starch | D27: Component | E27: component | F27: U6.Starch | G27: Outlet 1 Parameter;Outlet 2 Parameter | J27: 0.10875128 | K27: 0
A28: U6 | B28: Clarification 1 | C28: Sugars | D28: Component | E28: component | F28: U6.Sugars | G28: Outlet 1 Parameter;Outlet 2 Parameter | J28: 0.0015337338 | K28: 0.00060648973
A29: U6 | B29: Clarification 1 | C29: Fibre | D29: Component | E29: component | F29: U6.Fibre | G29: Outlet 1 Parameter;Outlet 2 Parameter | J29: 0.10841016 | K29: 0.022859144
A30: U6 | B30: Clarification 1 | C30: Other | D30: Component | E30: component | F30: U6.Other | G30: Outlet 1 Parameter;Outlet 2 Parameter | J30: 1 | K30: 1
A31: U6 | B31: Clarification 1 | C31: NaOH | D31: Component | E31: component | F31: U6.NaOH | G31: Outlet 1 Parameter;Outlet 2 Parameter
A32: U8 | B32: Clarification 2 | C32: Total mass | D32: Total | E32: overall | F32: U8.Total mass | G32: Outlet 1 Parameter;Outlet 2 Parameter | J32: 0.47638979 | K32: 0.52361021
A33: U8 | B33: Clarification 2 | C33: Total Solids | D33: Solids | E33: component | F33: U8.Total Solids | G33: Outlet 1 Parameter;Outlet 2 Parameter
A34: U8 | B34: Clarification 2 | C34: Ash | D34: Component | E34: component | F34: U8.Ash | G34: Outlet 1 Parameter;Outlet 2 Parameter | J34: 0.0038941204 | K34: 0.0002297205
A35: U8 | B35: Clarification 2 | C35: Protein | D35: Component | E35: component | F35: U8.Protein | G35: Outlet 1 Parameter;Outlet 2 Parameter | J35: 0.037218634 | K35: 0.0023528188
A36: U8 | B36: Clarification 2 | C36: Fat | D36: Component | E36: component | F36: U8.Fat | G36: Outlet 1 Parameter;Outlet 2 Parameter | J36: 0.010970404 | K36: 0.00079523736
A37: U8 | B37: Clarification 2 | C37: Starch | D37: Component | E37: component | F37: U8.Starch | G37: Outlet 1 Parameter;Outlet 2 Parameter | J37: 0.12632717 | K37: 0
A38: U8 | B38: Clarification 2 | C38: Sugars | D38: Component | E38: component | F38: U8.Sugars | G38: Outlet 1 Parameter;Outlet 2 Parameter | J38: 0.001589662 | K38: 0.00016800269
A39: U8 | B39: Clarification 2 | C39: Fibre | D39: Component | E39: component | F39: U8.Fibre | G39: Outlet 1 Parameter;Outlet 2 Parameter | J39: 0.12141981 | K39: 0.006173817
A40: U8 | B40: Clarification 2 | C40: Other | D40: Component | E40: component | F40: U8.Other | G40: Outlet 1 Parameter;Outlet 2 Parameter | J40: 1 | K40: 1
A41: U8 | B41: Clarification 2 | C41: NaOH | D41: Component | E41: component | F41: U8.NaOH | G41: Outlet 1 Parameter;Outlet 2 Parameter
A42: U10 | B42: Clarification 3 | C42: Total mass | D42: Total | E42: overall | F42: U10.Total mass | G42: Outlet 1 Parameter;Outlet 2 Parameter | J42: 0.49823005 | K42: 0.50176995
A43: U10 | B43: Clarification 3 | C43: Total Solids | D43: Solids | E43: component | F43: U10.Total Solids | G43: Outlet 1 Parameter;Outlet 2 Parameter
A44: U10 | B44: Clarification 3 | C44: Ash | D44: Component | E44: component | F44: U10.Ash | G44: Outlet 1 Parameter;Outlet 2 Parameter | J44: 0.0059870857 | K44: 5.4280287e-05
A45: U10 | B45: Clarification 3 | C45: Protein | D45: Component | E45: component | F45: U10.Protein | G45: Outlet 1 Parameter;Outlet 2 Parameter | J45: 0.056055612 | K45: 0.00057887716
A46: U10 | B46: Clarification 3 | C46: Fat | D46: Component | E46: component | F46: U10.Fat | G46: Outlet 1 Parameter;Outlet 2 Parameter | J46: 0.016050991 | K46: 0.00020541758
A47: U10 | B47: Clarification 3 | C47: Starch | D47: Component | E47: component | F47: U10.Starch | G47: Outlet 1 Parameter;Outlet 2 Parameter | J47: 0.15622301 | K47: 0
A48: U10 | B48: Clarification 3 | C48: Sugars | D48: Component | E48: component | F48: U10.Sugars | G48: Outlet 1 Parameter;Outlet 2 Parameter | J48: 0.0019082428 | K48: 5.5157493e-05
A49: U10 | B49: Clarification 3 | C49: Fibre | D49: Component | E49: component | F49: U10.Fibre | G49: Outlet 1 Parameter;Outlet 2 Parameter | J49: 0.19455511 | K49: 0.0014682678
A50: U10 | B50: Clarification 3 | C50: Other | D50: Component | E50: component | F50: U10.Other | G50: Outlet 1 Parameter;Outlet 2 Parameter | J50: 0 | K50: 0
A51: U10 | B51: Clarification 3 | C51: NaOH | D51: Component | E51: component | F51: U10.NaOH | G51: Outlet 1 Parameter;Outlet 2 Parameter
A52: U11 | B52: Drum drying | C52: Water | D52: Moisture | E52: drying | F52: U11.Water | G52: Final Moisture | I52: 0.058
A53: U12 | B53: Ultrafiltration | C53: Total mass | D53: Total | E53: mcf | F53: U12.Total mass | G53: MCF/RC | H53: 2.8
A54: U12 | B54: Ultrafiltration | C54: Total Solids | D54: Solids | E54: rc | F54: U12.Total Solids | G54: MCF/RC | H54: 0.75
A55: U12 | B55: Ultrafiltration | C55: Ash | D55: Component | E55: rc | F55: U12.Ash | G55: MCF/RC | H55: 0.75
A56: U12 | B56: Ultrafiltration | C56: Protein | D56: Component | E56: rc | F56: U12.Protein | G56: MCF/RC | H56: 0.92
A57: U12 | B57: Ultrafiltration | C57: Fat | D57: Component | E57: rc | F57: U12.Fat | G57: MCF/RC | H57: 1
A58: U12 | B58: Ultrafiltration | C58: Starch | D58: Component | E58: rc | F58: U12.Starch | G58: MCF/RC | H58: 0.84
A59: U12 | B59: Ultrafiltration | C59: Sugars | D59: Component | E59: rc | F59: U12.Sugars | G59: MCF/RC | H59: 0.25
A60: U12 | B60: Ultrafiltration | C60: Fibre | D60: Component | E60: rc | F60: U12.Fibre | G60: MCF/RC | H60: 0
A61: U12 | B61: Ultrafiltration | C61: Other | D61: Component | E61: rc | F61: U12.Other | G61: MCF/RC | H61: 0.45
A62: U12 | B62: Ultrafiltration | C62: Water | D62: Moisture | E62: rc | F62: U12.Water | G62: MCF/RC
A63: U12 | B63: Ultrafiltration | C63: NaOH | D63: Component | E63: rc | F63: U12.NaOH | G63: MCF/RC
A64: U13 | B64: Diafiltration | C64: Total mass | D64: Total | E64: df | F64: U13.Total mass | G64: MCF/RC | H64: 1.9
A65: U13 | B65: Diafiltration | C65: Total Solids | D65: Solids | E65: rc | F65: U13.Total Solids | G65: MCF/RC | H65: 0.75
A66: U13 | B66: Diafiltration | C66: Ash | D66: Component | E66: rc | F66: U13.Ash | G66: MCF/RC | H66: 0.75
A67: U13 | B67: Diafiltration | C67: Protein | D67: Component | E67: rc | F67: U13.Protein | G67: MCF/RC | H67: 0.92
A68: U13 | B68: Diafiltration | C68: Fat | D68: Component | E68: rc | F68: U13.Fat | G68: MCF/RC | H68: 1
A69: U13 | B69: Diafiltration | C69: Starch | D69: Component | E69: rc | F69: U13.Starch | G69: MCF/RC | H69: 0.84
A70: U13 | B70: Diafiltration | C70: Sugars | D70: Component | E70: rc | F70: U13.Sugars | G70: MCF/RC | H70: 0.25
A71: U13 | B71: Diafiltration | C71: Fibre | D71: Component | E71: rc | F71: U13.Fibre | G71: MCF/RC | H71: 0
A72: U13 | B72: Diafiltration | C72: Other | D72: Component | E72: rc | F72: U13.Other | G72: MCF/RC | H72: 0.45
A73: U13 | B73: Diafiltration | C73: Water | D73: Moisture | E73: rc | F73: U13.Water | G73: MCF/RC
A74: U13 | B74: Diafiltration | C74: NaOH | D74: Component | E74: rc | F74: U13.NaOH | G74: MCF/RC
A75: U16 | B75: Reverse osmosis | C75: Total mass | D75: Total | E75: mcf | F75: U16.Total mass | G75: MCF/RC | H75: 4
A76: U16 | B76: Reverse osmosis | C76: Total Solids | D76: Solids | E76: rc | F76: U16.Total Solids | G76: MCF/RC | H76: 1
A77: U16 | B77: Reverse osmosis | C77: Ash | D77: Component | E77: rc | F77: U16.Ash | G77: MCF/RC | H77: 1
A78: U16 | B78: Reverse osmosis | C78: Protein | D78: Component | E78: rc | F78: U16.Protein | G78: MCF/RC | H78: 1
A79: U16 | B79: Reverse osmosis | C79: Fat | D79: Component | E79: rc | F79: U16.Fat | G79: MCF/RC | H79: 1
A80: U16 | B80: Reverse osmosis | C80: Starch | D80: Component | E80: rc | F80: U16.Starch | G80: MCF/RC | H80: 1
A81: U16 | B81: Reverse osmosis | C81: Sugars | D81: Component | E81: rc | F81: U16.Sugars | G81: MCF/RC | H81: 1
A82: U16 | B82: Reverse osmosis | C82: Fibre | D82: Component | E82: rc | F82: U16.Fibre | G82: MCF/RC | H82: 1
A83: U16 | B83: Reverse osmosis | C83: Other | D83: Component | E83: rc | F83: U16.Other | G83: MCF/RC | H83: 1
A84: U16 | B84: Reverse osmosis | C84: Water | D84: Moisture | E84: rc | F84: U16.Water | G84: MCF/RC | H84: 1
A85: U16 | B85: Reverse osmosis | C85: NaOH | D85: Component | E85: rc | F85: U16.NaOH | G85: MCF/RC
A86: U17 | B86: Spray drying | C86: Water | D86: Moisture | E86: drying | F86: U17.Water | G86: Final Moisture | I86: 0.058

Sheet UnitParameters
A1: UnitID | B1: UnitClass | C1: ParameterName | D1: BaseValue | E1: Unit | F1: Identifier | G1: Description | H1: References
A2: U1 | B2: MyDehulling | C2: energy_slope | D2: 0.0144 | E2: kW/(kg/hr) | F2: U1.energy_slope | G2: Slope of the energy consumption curve
A3: U1 | B3: MyDehulling | C3: energy_intercept | D3: 0.3565 | E3: kW | F3: U1.energy_intercept | G3: Intercept of the energy consumption curve
A4: U2 | B4: MyImpactMilling | C4: kd | D4: 0.01 | E4: no unit | F4: U2.kd | G4: Size reduction power coefficient
A5: U2 | B5: MyImpactMilling | C5: w | D5: 40 | E5: kJ/kg | F5: U2.w | G5: Work index
A6: U2 | B6: MyImpactMilling | C6: D1 | D6: 0.0077 | E6: m | F6: U2.D1 | G6: Initial particle size
A7: U2 | B7: MyImpactMilling | C7: D2 | D7: 6.5e-05 | E7: m | F7: U2.D2 | G7: Final particle size
A8: U3 | B8: MyWetExtraction | C8: slurry_density | D8: 1183.67 | E8: kg/m3 | F8: U3.slurry_density | G8: Density of the slurry
A9: U3 | B9: MyWetExtraction | C9: cp_feedstock | D9: 3.75 | E9: kJ/kg-K | F9: U3.cp_feedstock | G9: Heat capacity of the feedstock
A10: U3 | B10: MyWetExtraction | C10: cp_water | D10: 4.18 | E10: kJ/kg-K | F10: U3.cp_water | G10: Heat capacity of water
A11: U3 | B11: MyWetExtraction | C11: cp_feedstock_slurry | D11: 4.15 | E11: kJ/kg-K | F11: U3.cp_feedstock_slurry | G11: Heat capacity of the feedstock slurry
A12: U3 | B12: MyWetExtraction | C12: k_G | D12: 2 | E12: dimensionless | F12: U3.k_G | G12: Power coefficient for agitation
A13: U3 | B13: MyWetExtraction | C13: tau | D13: 0.3 | E13: hr | F13: U3.tau | G13: residence time
... A40: U12 | B40: MyUltrafiltration | C40: transmembrane_pressure | D40: 1.3 | E40: bar | F40: U12.transmembrane_pressure | G40: Transmembrane pressure
A41: U12 | B41: MyUltrafiltration | C41: pump_efficiency | D41: 0.8 | F41: U12.pump_efficiency | G41: Pump efficiency
A42: U12 | B42: MyUltrafiltration | C42: tau | D42: 0.3 | E42: hr | F42: U12.tau | G42: residence time
A43: U13 | B43: MyDiafiltration | C43: retentate_density | D43: 1183.67 | E43: kg/m3 | F43: U13.retentate_density | G43: Density of the incoming retentate
A44: U13 | B44: MyDiafiltration | C44: transmembrane_pressure | D44: 1.3 | E44: bar | F44: U13.transmembrane_pressure | G44: Transmembrane pressure
A45: U13 | B45: MyDiafiltration | C45: tau | D45: 0.3 | E45: hr | F45: U13.tau | G45: residence time
A46: U13 | B46: MyDiafiltration | C46: pump_efficiency | D46: 0.8 | F46: U13.pump_efficiency | G46: Pump efficiency
A47: U14 | B47: MyPasteurisation | C47: cp_ret | D47: 4.5 | E47: kJ/kg-K | F47: U14.cp_ret | G47: Heat capacity of the retentate
A48: U14 | B48: MyPasteurisation | C48: T_in | D48: 50 | E48: °C | F48: U14.T_in | G48: Inlet temperature
A49: U14 | B49: MyPasteurisation | C49: T_out | D49: 75 | E49: °C | F49: U14.T_out | G49: Outlet temperature
A50: U14 | B50: MyPasteurisation | C50: T_deltamin | D50: 10 | E50: °C | F50: U14.T_deltamin | G50: Minimum approach temperature for water
A51: U14 | B51: MyPasteurisation | C51: U | D51: 0.75 | E51: kW/m2-K | F51: U14.U | G51: Overall heat transfer coefficient
A52: U15 | B52: MyHoldingTube | C52: slurry_density | D52: 1183.67 | E52: kg/m3 | F52: U15.slurry_density | G52: Density of the slurry
A53: U15 | B53: MyHoldingTube | C53: tau | D53: 0.008 | E53: hr | F53: U15.tau | G53: residence time
A54: U16 | B54: MyReverseOsmosis | C54: pea_slurry_density | D54: 1183.67 | E54: kg/m3 | F54: U16.pea_slurry_density | G54: Density of the pea slurry
A55: U16 | B55: MyReverseOsmosis | C55: transmembrane_pressure | D55: 1 | E55: bar | F55: U16.transmembrane_pressure | G55: Transmembrane pressure
A56: U16 | B56: MyReverseOsmosis | C56: pump_efficiency | D56: 0.75 | F56: U16.pump_efficiency | G56: Pump efficiency
A57: U16 | B57: MyReverseOsmosis | C57: tau | D57: 0.3 | E57: hr | F57: U16.tau | G57: residence time
A58: U17 | B58: MySprayDryer | C58: latent_heat_vaporization | D58: 2257 | E58: kJ/kg | F58: U17.latent_heat_vaporization | G58: Latent heat of vaporization for water
A59: U17 | B59: MySprayDryer | C59: thermal_efficiency | D59: 0.85 | E59: dimensionless | F59: U17.thermal_efficiency | G59: Thermal efficiency of the spray dryer
A60: U17 | B60: MySprayDryer | C60: average_kW_per_tonne_hr | D60: 75 | E60: kW/tonne | F60: U17.average_kW_per_tonne_hr | G60: Average power consumption per tonne of product

Sheet FinancialInputs
A1: Variables | B1: Value | C1: Units | D1: Definition | E1: Reference
A2: Lang factor | B2: 2.75 | C2: dimensionless
A3: Labour cost per hour | B3: 44.2 | C3: $/hr
A4: Packaging cost per kg | B4: 0.5 | C4: $/kg
A5: Maintenance cost factor | B5: 0.06 | C5: dimensionless
A6: Depreciation rate | B6: 0.085 | C6: %
A7: Tax rate | B7: 0.28 | C7: %
A8: Internal discount rate | B8: 0.1675 | C8: %
A9: Project life years | B9: 15.5 | C9: years
A10: Power price | B10: 0.1846 | C10: NZD/kWh
A11: Process heat price | B11: 0.01422 | C11: $/MJ

Sheet CostAdjustment
A1: UnitID | B1: Unit Operation | C1: UnitClass | D1: Inflation factor | E1: Exchange factor | F1: Calibration factor | G1: ref date | H1: ref currency
A2: U1 | B2: Dehulling | C2: MyDehulling | D2: 1.0290679 | E2: 1.6419825 | F2: 1 | G2: 2025 | H2: USD
A3: U2 | B3: Milling | C3: MyImpactMilling | D3: 1.7514747 | E3: 1 | F3: 1 | G3: 2004 | H3: NZD
A4: U3 | B4: Wet extraction | C4: MyWetExtraction | D4: 1.5451646 | E4: 1.3133595 | F4: 1 | G4: 2008 | H4: USD
A5: U4 | B5: Cooling | C5: MyCooling | D5: 1.7514747 | E5: 1 | F5: 1 | G5: 2004 | H5: NZD
A6: U5 | B6: Decanter centrifuge | C6: MyDecanterCentrifuge | D6: 1.7514747 | E6: 1 | F6: 1 | G6: 2004 | H6: NZD
A7: U6 | B7: Clarification 1 | C7: MyClarifier | D7: 1.7514747 | E7: 1 | F7: 1 | G7: 2004 | H7: NZD
A8: U7 | B8: Mixing 1 | C8: MyMixingTank | D8: 1.5451646 | E8: 1.3133595 | F8: 1 | G8: 2008 | H8: USD
A9: U8 | B9: Clarification 2 | C9: MyClarifier | D9: 1.7514747 | E9: 1 | F9: 1 | G9: 2004 | H9: NZD
A10: U9 | B10: Mixing 2 | C10: MyMixingTank | D10: 1.5451646 | E10: 1.3133595 | F10: 1 | G10: 2008 | H10: USD
A11: U10 | B11: Clarification 3 | C11: MyClarifier | D11: 1.7514747 | E11: 1 | F11: 1 | G11: 2004 | H11: NZD
A12: U11 | B12: Drum drying | C12: MyDrumDryer | D12: 1.5451646 | E12: 1.3133595 | F12: 1 | G12: 2008 | H12: USD
A13: U12 | B13: Ultrafiltration | C13: MyUltrafiltration | D13: 1.7514747 | E13: 1 | F13: 1 | G13: 2004 | H13: NZD
... A18: U17 | B18: Spray drying | C18: MySprayDryer | D18: 1 | E18: 1 | F18: 1 | G18: 2026 | H18: NZD

Sheet EconomicStreams
A1: StreamName | B1: StreamID | C1: Role | D1: ModelType | E1: Parameter | F1: base | G1: alpha | H1: price_per_kg | I1: protein_fraction
A2: Peas | B2: S1 | C2: Feedstock | D2: static | E2: price_per_kg | H2: 1.2
A3: Hulls | B3: S3 | C3: Byproduct | D3: static | E3: price_per_kg | H3: 0.52
A4: NaOH solution | B4: S5 | C4: Solvent | D4: static | E4: price_per_kg | H4: 2.36
A5: Water 1 | B5: S6 | C5: Water | D5: static | E5: price_per_kg | H5: 0.00152
A6: Water 2 | B6: S13 | C6: Water | D6: static | E6: price_per_kg | H6: 0.00152
A7: Whey 1 | B7: S12 | C7: Waste | D7: static | E7: price_per_kg | H7: 0.00096
A8: Whey 2 | B8: S16 | C8: Waste | D8: static | E8: price_per_kg | H8: 0.00096
A9: Water 3 | B9: S17 | C9: Water | D9: static | E9: price_per_kg | H9: 0.00152
A10: Dried sediment | B10: S21 | C10: Byproduct | D10: static | E10: price_per_kg | H10: 1.25
A11: Water vapour 1 | B11: S22 | C11: Waste | D11: static | E11: price_per_kg | H11: 0
A12: Water 4 | B12: S25 | C12: Water | D12: static | E12: price_per_kg | H12: 0.00152
A13: Permeate 1 | B13: S24 | C13: Waste | D13: static | E13: price_per_kg | H13: 0.00096
... A15: Permeate 3 | B15: S31 | C15: Waste | D15: static | E15: price_per_kg | H15: 0.00096
A16: Spray dried powder | B16: S32 | C16: Product | D16: linear_protein | E16: base;alpha | F16: -27.08 | G16: 59.948 | I16: MB.S32.C3.fraction.Spray dried powder.Protein
A17: Water vapour 2 | B17: S33 | C17: Waste | D17: static | E17: price_per_kg | H17: 0

Sheet OperatingInputs
A1: Variables | B1: Value | C1: Units | D1: Definition | E1: Reference
A2: Shift hours per day | B2: 24 | C2: hours
A3: Months per year | B3: 12 | C3: months
A4: Days per year | B4: 240 | C4: days
A5: Working days per month | B5: 20 | C5: days
A6: Target feed | B6: 1000 | C6: tonnes/year

Sheet DecisionVariables
A1: VariableName | B1: SourceSheet | C1: Identifier | D1: CurrentValue | E1: LowerBound | F1: UpperBound | G1: Active | H1: Sensitivity
A2: Lang factor | B2: FinancialInputs | C2: Lang factor | D2: =INDEX(FinancialInputs!$B:$B, MATCH(C2, FinancialInputs!$A:$A, 0)) -> 2.75 | G2: FALSE | H2: FALSE
A3: Labour cost per hour | B3: FinancialInputs | C3: Labour cost per hour | D3: =INDEX(FinancialInputs!$B:$B, MATCH(C3, FinancialInputs!$A:$A, 0)) -> 44.2 | G3: FALSE | H3: FALSE
A4: Packaging cost per kg | B4: FinancialInputs | C4: Packaging cost per kg | D4: =INDEX(FinancialInputs!$B:$B, MATCH(C4, FinancialInputs!$A:$A, 0)) -> 0.5 | G4: FALSE | H4: FALSE
A5: Maintenance cost factor | B5: FinancialInputs | C5: Maintenance cost factor | D5: =INDEX(FinancialInputs!$B:$B, MATCH(C5, FinancialInputs!$A:$A, 0)) -> 0.06 | G5: FALSE | H5: FALSE
A6: Depreciation rate | B6: FinancialInputs | C6: Depreciation rate | D6: =INDEX(FinancialInputs!$B:$B, MATCH(C6, FinancialInputs!$A:$A, 0)) -> 0.085 | G6: FALSE | H6: FALSE
A7: Tax rate | B7: FinancialInputs | C7: Tax rate | D7: =INDEX(FinancialInputs!$B:$B, MATCH(C7, FinancialInputs!$A:$A, 0)) -> 0.28 | G7: FALSE | H7: FALSE
A8: Internal discount rate | B8: FinancialInputs | C8: Internal discount rate | D8: =INDEX(FinancialInputs!$B:$B, MATCH(C8, FinancialInputs!$A:$A, 0)) -> 0.1675 | G8: FALSE | H8: FALSE
A9: Project life years | B9: FinancialInputs | C9: Project life years | D9: =INDEX(FinancialInputs!$B:$B, MATCH(C9, FinancialInputs!$A:$A, 0)) -> 15.5 | G9: FALSE | H9: FALSE
A10: Power price | B10: FinancialInputs | C10: Power price | D10: =INDEX(FinancialInputs!$B:$B, MATCH(C10, FinancialInputs!$A:$A, 0)) -> 0.1846 | G10: FALSE | H10: FALSE
A11: Process heat price | B11: FinancialInputs | C11: Process heat price | D11: =INDEX(FinancialInputs!$B:$B, MATCH(C11, FinancialInputs!$A:$A, 0)) -> 0.01422 | G11: FALSE | H11: FALSE
A12: Water price | B12: FinancialInputs | C12: Water price | D12: =INDEX(FinancialInputs!$B:$B, MATCH(C12, FinancialInputs!$A:$A, 0)) -> #N/A | G12: FALSE | H12: FALSE
A13: Waste price | B13: FinancialInputs | C13: Waste price | D13: =INDEX(FinancialInputs!$B:$B, MATCH(C13, FinancialInputs!$A:$A, 0)) -> #N/A | G13: FALSE | H13: FALSE
A14: Solvent price | B14: FinancialInputs | C14: Solvent price | D14: =INDEX(FinancialInputs!$B:$B, MATCH(C14, FinancialInputs!$A:$A, 0)) -> #N/A | G14: FALSE | H14: FALSE
A15: Shift hours per day | B15: OperatingInputs | C15: Shift hours per day | D15: =INDEX(OperatingInputs!$B:$B, MATCH(C15, OperatingInputs!$A:$A, 0)) -> 24 | G15: FALSE | H15: FALSE
A16: Months per year | B16: OperatingInputs | C16: Months per year | D16: =INDEX(OperatingInputs!$B:$B, MATCH(C16, OperatingInputs!$A:$A, 0)) -> 12 | G16: FALSE | H16: FALSE
A17: Days per year | B17: OperatingInputs | C17: Days per year | D17: =INDEX(OperatingInputs!$B:$B, MATCH(C17, OperatingInputs!$A:$A, 0)) -> 240 | G17: FALSE | H17: FALSE
A18: Working days per month | B18: OperatingInputs | C18: Working days per month | D18: =INDEX(OperatingInputs!$B:$B, MATCH(C18, OperatingInputs!$A:$A, 0)) -> 20 | G18: FALSE | H18: FALSE
A19: Target feed | B19: OperatingInputs | C19: Target feed | D19: =INDEX(OperatingInputs!$B:$B, MATCH(C19, OperatingInputs!$A:$A, 0)) -> 1000 | G19: FALSE | H19: FALSE
A20: S1.Basismass | B20: ProcessInputs | C20: S1.Basismass | D20: =INDEX(ProcessInputs!$E:$E, MATCH(C20, ProcessInputs!$C:$C, 0)) -> 100 | G20: FALSE | H20: FALSE
A21: S1.Total mass | B21: ProcessInputs | C21: S1.Total mass | D21: =INDEX(ProcessInputs!$E:$E, MATCH(C21, ProcessInputs!$C:$C, 0)) -> 1 | G21: FALSE | H21: FALSE
A22: S1.Total Solids | B22: ProcessInputs | C22: S1.Total Solids | D22: =INDEX(ProcessInputs!$E:$E, MATCH(C22, ProcessInputs!$C:$C, 0)) -> 0.884 | G22: FALSE | H22: FALSE
A23: S1.Ash | B23: ProcessInputs | C23: S1.Ash | D23: =INDEX(ProcessInputs!$E:$E, MATCH(C23, ProcessInputs!$C:$C, 0)) -> 0.034 | G23: FALSE | H23: FALSE
A24: S1.Protein | B24: ProcessInputs | C24: S1.Protein | D24: =INDEX(ProcessInputs!$E:$E, MATCH(C24, ProcessInputs!$C:$C, 0)) -> 0.232 | G24: FALSE | H24: FALSE
A25: S1.Fat | B25: ProcessInputs | C25: S1.Fat | D25: =INDEX(ProcessInputs!$E:$E, MATCH(C25, ProcessInputs!$C:$C, 0)) -> 0.016 | G25: FALSE | H25: FALSE
A26: S1.Starch | B26: ProcessInputs | C26: S1.Starch | D26: =INDEX(ProcessInputs!$E:$E, MATCH(C26, ProcessInputs!$C:$C, 0)) -> 0.224 | G26: FALSE | H26: FALSE
A27: S1.Sugars | B27: ProcessInputs | C27: S1.Sugars | D27: =INDEX(ProcessInputs!$E:$E, MATCH(C27, ProcessInputs!$C:$C, 0)) -> 0.056 | G27: FALSE | H27: FALSE
A28: S1.Fibre | B28: ProcessInputs | C28: S1.Fibre | D28: =INDEX(ProcessInputs!$E:$E, MATCH(C28, ProcessInputs!$C:$C, 0)) -> 0.322 | G28: FALSE | H28: FALSE
A29: S1.Other | B29: ProcessInputs | C29: S1.Other | D29: =INDEX(ProcessInputs!$E:$E, MATCH(C29, ProcessInputs!$C:$C, 0)) -> 0 | G29: FALSE | H29: FALSE
A30: S1.Water | B30: ProcessInputs | C30: S1.Water | D30: =INDEX(ProcessInputs!$E:$E, MATCH(C30, ProcessInputs!$C:$C, 0)) -> 0.116 | G30: FALSE | H30: FALSE
A31: S5.Basismass | B31: ProcessInputs | C31: S5.Basismass | D31: =INDEX(ProcessInputs!$E:$E, MATCH(C31, ProcessInputs!$C:$C, 0)) -> 5.052529 | G31: FALSE | H31: FALSE
... A47: S25.Water | B47: ProcessInputs | C47: S25.Water | D47: =INDEX(ProcessInputs!$E:$E, MATCH(C47, ProcessInputs!$C:$C, 0)) -> 1 | G47: FALSE | H47: FALSE
A48: U1.Total mass.Outlet 1 Parameter | B48: PartitioningCoefficients | C48: U1.Total mass.Outlet 1 Parameter | D48: =INDEX(PartitioningCoefficients!$A:$O,MATCH(LEFT(C48,FIND(".",C48,FIND(".",C48)+1)-1),PartitioningCoefficients!$F:$F,0),MATCH(MID(C48,FIND(".",C48,FIND(".",C48)+1)+1,255),PartitioningCoefficients!$1:$1,0)) -> 0.90881824 | G48: FALSE | H48: FALSE
A49: U1.Total mass.Outlet 2 Parameter | B49: PartitioningCoefficients | C49: U1.Total mass.Outlet 2 Parameter | D49: =INDEX(PartitioningCoefficients!$A:$O,MATCH(LEFT(C49,FIND(".",C49,FIND(".",C49)+1)-1),PartitioningCoefficients!$F:$F,0),MATCH(MID(C49,FIND(".",C49,FIND(".",C49)+1)+1,255),PartitioningCoefficients!$1:$1,0)) -> 0.091181764 | G49: FALSE | H49: FALSE
A50: U1.Total Solids.Outlet 1 Parameter | B50: PartitioningCoefficients | C50: U1.Total Solids.Outlet 1 Parameter | D50: =INDEX(PartitioningCoefficients!$A:$O,MATCH(LEFT(C50,FIND(".",C50,FIND(".",C50)+1)-1),PartitioningCoefficients!$F:$F,0),MATCH(MID(C50,FIND(".",C50,FIND(".",C50)+1)+1,255),PartitioningCoefficients!$1:$1,0)) -> 0 | G50: FALSE | H50: FALSE
A51: U1.Total Solids.Outlet 2 Parameter | B51: PartitioningCoefficients | C51: U1.Total Solids.Outlet 2 Parameter | D51: =INDEX(PartitioningCoefficients!$A:$O,MATCH(LEFT(C51,FIND(".",C51,FIND(".",C51)+1)-1),PartitioningCoefficients!$F:$F,0),MATCH(MID(C51,FIND(".",C51,FIND(".",C51)+1)+1,255),PartitioningCoefficients!$1:$1,0)) -> 0 | G51: FALSE | H51: FALSE
A52: U1.Ash.Outlet 1 Parameter | B52: PartitioningCoefficients | C52: U1.Ash.Outlet 1 Parameter | D52: =INDEX(PartitioningCoefficients!$A:$O,MATCH(LEFT(C52,FIND(".",C52,FIND(".",C52)+1)-1),PartitioningCoefficients!$F:$F,0),MATCH(MID(C52,FIND(".",C52,FIND(".",C52)+1)+1,255),PartitioningCoefficients!$1:$1,0)) -> 0.022392431 | G52: FALSE | H52: FALSE
A53: U1.Ash.Outlet 2 Parameter | B53: PartitioningCoefficients | C53: U1.Ash.Outlet 2 Parameter | D53: =INDEX(PartitioningCoefficients!$A:$O,MATCH(LEFT(C53,FIND(".",C53,FIND(".",C53)+1)-1),PartitioningCoefficients!$F:$F,0),MATCH(MID(C53,FIND(".",C53,FIND(".",C53)+1)+1,255),PartitioningCoefficients!$1:$1,0)) -> 0.03309939 | G53: FALSE | H53: FALSE
A54: U1.Protein.Outlet 1 Parameter | B54: PartitioningCoefficients | C54: U1.Protein.Outlet 1 Parameter | D54: =INDEX(PartitioningCoefficients!$A:$O,MATCH(LEFT(C54,FIND(".",C54,FIND(".",C54)+1)-1),PartitioningCoefficients!$F:$F,0),MATCH(MID(C54,FIND(".",C54,FIND(".",C54)+1)+1,255),PartitioningCoefficients!$1:$1,0)) -> 0.2447833 | G54: FALSE | H54: FALSE
A55: U1.Protein.Outlet 2 Parameter | B55: PartitioningCoefficients | C55: U1.Protein.Outlet 2 Parameter | D55: =INDEX(PartitioningCoefficients!$A:$O,MATCH(LEFT(C55,FIND(".",C55,FIND(".",C55)+1)-1),PartitioningCoefficients!$F:$F,0),MATCH(MID(C55,FIND(".",C55,FIND(".",C55)+1)+1,255),PartitioningCoefficients!$1:$1,0)) -> 0.076999276 | G55: FALSE | H55: FALSE
A56: U1.Fat.Outlet 1 Parameter | B56: PartitioningCoefficients | C56: U1.Fat.Outlet 1 Parameter | D56: =INDEX(PartitioningCoefficients!$A:$O,MATCH(LEFT(C56,FIND(".",C56,FIND(".",C56)+1)-1),PartitioningCoefficients!$F:$F,0),MATCH(MID(C56,FIND(".",C56,FIND(".",C56)+1)+1,255),PartitioningCoefficients!$1:$1,0)) -> 0.042999993 | G56: FALSE | H56: FALSE
A57: U1.Fat.Outlet 2 Parameter | B57: PartitioningCoefficients | C57: U1.Fat.Outlet 2 Parameter | D57: =INDEX(PartitioningCoefficients!$A:$O,MATCH(LEFT(C57,FIND(".",C57,FIND(".",C57)+1)-1),PartitioningCoefficients!$F:$F,0),MATCH(MID(C57,FIND(".",C57,FIND(".",C57)+1)+1,255),PartitioningCoefficients!$1:$1,0)) -> 0.0099999984 | G57: FALSE | H57: FALSE
A58: U1.Starch.Outlet 1 Parameter | B58: PartitioningCoefficients | C58: U1.Starch.Outlet 1 Parameter | D58: =INDEX(PartitioningCoefficients!$A:$O,MATCH(LEFT(C58,FIND(".",C58,FIND(".",C58)+1)-1),PartitioningCoefficients!$F:$F,0),MATCH(MID(C58,FIND(".",C58,FIND(".",C58)+1)+1,255),PartitioningCoefficients!$1:$1,0)) -> 0.269 | G58: FALSE | H58: FALSE
A59: U1.Starch.Outlet 2 Parameter | B59: PartitioningCoefficients | C59: U1.Starch.Outlet 2 Parameter | D59: =INDEX(PartitioningCoefficients!$A:$O,MATCH(LEFT(C59,FIND(".",C59,FIND(".",C59)+1)-1),PartitioningCoefficients!$F:$F,0),MATCH(MID(C59,FIND(".",C59,FIND(".",C59)+1)+1,255),PartitioningCoefficients!$1:$1,0)) -> 0 | G59: FALSE | H59: FALSE
... A182: U17.Water.Final Moisture | B182: PartitioningCoefficients | C182: U17.Water.Final Moisture | D182: =INDEX(PartitioningCoefficients!$A:$O,MATCH(LEFT(C182,FIND(".",C182,FIND(".",C182)+1)-1),PartitioningCoefficients!$F:$F,0),MATCH(MID(C182,FIND(".",C182,FIND(".",C182)+1)+1,255),PartitioningCoefficients!$1:$1,0)) -> 0.058 | G182: FALSE | H182: FALSE
A183: U1.energy_slope | B183: UnitParameters | C183: U1.energy_slope | D183: =INDEX(UnitParameters!$D:$D, MATCH(C183, UnitParameters!$F:$F, 0)) -> 0.0144 | G183: FALSE | H183: FALSE
A184: U1.energy_intercept | B184: UnitParameters | C184: U1.energy_intercept | D184: =INDEX(UnitParameters!$D:$D, MATCH(C184, UnitParameters!$F:$F, 0)) -> 0.3565 | G184: FALSE | H184: FALSE
A185: U2.kd | B185: UnitParameters | C185: U2.kd | D185: =INDEX(UnitParameters!$D:$D, MATCH(C185, UnitParameters!$F:$F, 0)) -> 0.01 | G185: FALSE | H185: FALSE
A186: U2.w | B186: UnitParameters | C186: U2.w | D186: =INDEX(UnitParameters!$D:$D, MATCH(C186, UnitParameters!$F:$F, 0)) -> 40 | G186: FALSE | H186: FALSE
A187: U2.D1 | B187: UnitParameters | C187: U2.D1 | D187: =INDEX(UnitParameters!$D:$D, MATCH(C187, UnitParameters!$F:$F, 0)) -> 0.0077 | G187: FALSE | H187: FALSE
A188: U2.D2 | B188: UnitParameters | C188: U2.D2 | D188: =INDEX(UnitParameters!$D:$D, MATCH(C188, UnitParameters!$F:$F, 0)) -> 6.5e-05 | G188: FALSE | H188: FALSE
A189: U3.slurry_density | B189: UnitParameters | C189: U3.slurry_density | D189: =INDEX(UnitParameters!$D:$D, MATCH(C189, UnitParameters!$F:$F, 0)) -> 1183.67 | G189: FALSE | H189: FALSE
A190: U3.cp_feedstock | B190: UnitParameters | C190: U3.cp_feedstock | D190: =INDEX(UnitParameters!$D:$D, MATCH(C190, UnitParameters!$F:$F, 0)) -> 3.75 | G190: FALSE | H190: FALSE
A191: U3.cp_water | B191: UnitParameters | C191: U3.cp_water | D191: =INDEX(UnitParameters!$D:$D, MATCH(C191, UnitParameters!$F:$F, 0)) -> 4.18 | G191: FALSE | H191: FALSE
A192: U3.cp_feedstock_slurry | B192: UnitParameters | C192: U3.cp_feedstock_slurry | D192: =INDEX(UnitParameters!$D:$D, MATCH(C192, UnitParameters!$F:$F, 0)) -> 4.15 | G192: FALSE | H192: FALSE
A193: U3.k_G | B193: UnitParameters | C193: U3.k_G | D193: =INDEX(UnitParameters!$D:$D, MATCH(C193, UnitParameters!$F:$F, 0)) -> 2 | G193: FALSE | H193: FALSE
A194: U3.tau | B194: UnitParameters | C194: U3.tau | D194: =INDEX(UnitParameters!$D:$D, MATCH(C194, UnitParameters!$F:$F, 0)) -> 0.3 | G194: FALSE | H194: FALSE
... A241: U17.average_kW_per_tonne_hr | B241: UnitParameters | C241: U17.average_kW_per_tonne_hr | D241: =INDEX(UnitParameters!$D:$D, MATCH(C241, UnitParameters!$F:$F, 0)) -> 75 | G241: FALSE | H241: FALSE
A242: S1.price_per_kg | B242: EconomicStreams | C242: S1.price_per_kg | D242: =INDEX(EconomicStreams!$A:$Z,MATCH(LEFT(C242, FIND(".", C242) - 1), EconomicStreams!$B:$B, 0),MATCH(MID(C242, FIND(".", C242) + 1, 255), EconomicStreams!$1:$1, 0)) -> 1.2 | G242: FALSE | H242: FALSE
A243: S3.price_per_kg | B243: EconomicStreams | C243: S3.price_per_kg | D243: =INDEX(EconomicStreams!$A:$Z,MATCH(LEFT(C243, FIND(".", C243) - 1), EconomicStreams!$B:$B, 0),MATCH(MID(C243, FIND(".", C243) + 1, 255), EconomicStreams!$1:$1, 0)) -> 0.52 | G243: FALSE | H243: FALSE
A244: S5.price_per_kg | B244: EconomicStreams | C244: S5.price_per_kg | D244: =INDEX(EconomicStreams!$A:$Z,MATCH(LEFT(C244, FIND(".", C244) - 1), EconomicStreams!$B:$B, 0),MATCH(MID(C244, FIND(".", C244) + 1, 255), EconomicStreams!$1:$1, 0)) -> 2.36 | G244: FALSE | H244: FALSE
A245: S6.price_per_kg | B245: EconomicStreams | C245: S6.price_per_kg | D245: =INDEX(EconomicStreams!$A:$Z,MATCH(LEFT(C245, FIND(".", C245) - 1), EconomicStreams!$B:$B, 0),MATCH(MID(C245, FIND(".", C245) + 1, 255), EconomicStreams!$1:$1, 0)) -> 0.00152 | G245: FALSE | H245: FALSE
A246: S13.price_per_kg | B246: EconomicStreams | C246: S13.price_per_kg | D246: =INDEX(EconomicStreams!$A:$Z,MATCH(LEFT(C246, FIND(".", C246) - 1), EconomicStreams!$B:$B, 0),MATCH(MID(C246, FIND(".", C246) + 1, 255), EconomicStreams!$1:$1, 0)) -> 0.00152 | G246: FALSE | H246: FALSE
A247: S12.price_per_kg | B247: EconomicStreams | C247: S12.price_per_kg | D247: =INDEX(EconomicStreams!$A:$Z,MATCH(LEFT(C247, FIND(".", C247) - 1), EconomicStreams!$B:$B, 0),MATCH(MID(C247, FIND(".", C247) + 1, 255), EconomicStreams!$1:$1, 0)) -> 0.00096 | G247: FALSE | H247: FALSE
A248: S16.price_per_kg | B248: EconomicStreams | C248: S16.price_per_kg | D248: =INDEX(EconomicStreams!$A:$Z,MATCH(LEFT(C248, FIND(".", C248) - 1), EconomicStreams!$B:$B, 0),MATCH(MID(C248, FIND(".", C248) + 1, 255), EconomicStreams!$1:$1, 0)) -> 0.00096 | G248: FALSE | H248: FALSE
A249: S17.price_per_kg | B249: EconomicStreams | C249: S17.price_per_kg | D249: =INDEX(EconomicStreams!$A:$Z,MATCH(LEFT(C249, FIND(".", C249) - 1), EconomicStreams!$B:$B, 0),MATCH(MID(C249, FIND(".", C249) + 1, 255), EconomicStreams!$1:$1, 0)) -> 0.00152 | G249: FALSE | H249: FALSE
A250: S21.price_per_kg | B250: EconomicStreams | C250: S21.price_per_kg | D250: =INDEX(EconomicStreams!$A:$Z,MATCH(LEFT(C250, FIND(".", C250) - 1), EconomicStreams!$B:$B, 0),MATCH(MID(C250, FIND(".", C250) + 1, 255), EconomicStreams!$1:$1, 0)) -> 1.25 | G250: FALSE | H250: FALSE
A251: S22.price_per_kg | B251: EconomicStreams | C251: S22.price_per_kg | D251: =INDEX(EconomicStreams!$A:$Z,MATCH(LEFT(C251, FIND(".", C251) - 1), EconomicStreams!$B:$B, 0),MATCH(MID(C251, FIND(".", C251) + 1, 255), EconomicStreams!$1:$1, 0)) -> 0 | G251: FALSE | H251: FALSE
A252: S25.price_per_kg | B252: EconomicStreams | C252: S25.price_per_kg | D252: =INDEX(EconomicStreams!$A:$Z,MATCH(LEFT(C252, FIND(".", C252) - 1), EconomicStreams!$B:$B, 0),MATCH(MID(C252, FIND(".", C252) + 1, 255), EconomicStreams!$1:$1, 0)) -> 0.00152 | G252: FALSE | H252: FALSE
A253: S24.price_per_kg | B253: EconomicStreams | C253: S24.price_per_kg | D253: =INDEX(EconomicStreams!$A:$Z,MATCH(LEFT(C253, FIND(".", C253) - 1), EconomicStreams!$B:$B, 0),MATCH(MID(C253, FIND(".", C253) + 1, 255), EconomicStreams!$1:$1, 0)) -> 0.00096 | G253: FALSE | H253: FALSE
... A258: S33.price_per_kg | B258: EconomicStreams | C258: S33.price_per_kg | D258: =INDEX(EconomicStreams!$A:$Z,MATCH(LEFT(C258, FIND(".", C258) - 1), EconomicStreams!$B:$B, 0),MATCH(MID(C258, FIND(".", C258) + 1, 255), EconomicStreams!$1:$1, 0)) -> 0 | G258: FALSE | H258: FALSE

Sheet _AccessibleVariables
A1: DV.Days per year
A2: DV.Depreciation rate
A3: DV.Internal discount rate
A4: DV.Labour cost per hour
A5: DV.Lang factor
A6: DV.Maintenance cost factor
A7: DV.Months per year
A8: DV.Packaging cost per kg
A9: DV.Power price
A10: DV.Process heat price
A11: DV.Project life years
A12: DV.S1.Ash
... A620: MB.S9.C9.fraction.Sludge.Water

Sheet OptimisationSettings
A1: Setting | B1: Value
A2: Objective | B2: NPV
A3: Direction | B3: Maximise

Sheet MassBalance
D1: S1 | E1: S2 | F1: S3 | G1: S4 | H1: S5 | I1: S6 | J1: S7 | K1: S8 | L1: S9 | M1: S10 | N1: S11 | O1: S12 | P1: S13 | Q1: S14 | R1: S15 | S1: S16 | T1: S17 | U1: S18 | V1: S19 | W1: S20 | X1: S21 | Y1: S22 | Z1: S23 | AA1: S24 | AB1: S25 | AC1: S26 | AD1: S27 | AE1: S28 | AF1: S29 | AG1: S30 | AH1: S31 | AI1: S32 | AJ1: S33 | AL1: In | AM1: S1 | AN1: S5 | AO1: S6 | AP1: S13 | AQ1: S17 | AR1: S25 | AS1: total In | AU1: Out | AV1: S3 | AW1: S12 | AX1: S16 | AY1: S20 | AZ1: S21 | BA1: S22 | BB1: S24 | BC1: S27 | BD1: S31 | BE1: S32 | BF1: S33 | BG1: Total Out | BH1: Residual | BJ1: S1 | BK1: S2 | BL1: S3 | BN1: S2 | BO1: S4 | BQ1: S4 | BR1: S5 | BS1: S6 | BT1: S7 | BV1: S7 | BW1: S8 | BY1: S8 | BZ1: S9 | CA1: S10 | CC1: S9 | CD1: S11 | CE1: S12 | CG1: S11 | CH1: S13 | CI1: S14 | CK1: S14 | CL1: S15 | CM1: S16 | CO1: S15 | CP1: S17 | CQ1: S18 | CS1: S18 | CT1: S19 | CU1: S20 | CW1: S19 | CX1: S21 | CY1: S22 | DA1: S10 | DB1: S23 | DC1: S24 | DE1: S23 | DF1: S25 | DG1: S26 | DH1: S27 | DJ1: S26 | DK1: S28 | DM1: S28 | DN1: S29 | DP1: S29 | DQ1: S30 | DR1: S31 | DT1: S30 | DU1: S32 | DV1: S33
A2: Component ID | B2: Unit | C2: stream name | D2: Peas | E2: Dehulled peas | F2: Hulls | G2: Dehulled pea flour | H2: NaOH solution | I2: Water 1 | J2: Heat treated slurry | K2: Cooled slurry | L2: Sludge | M2: Supernatant 1 | N2: Sediment 1 | O2: Whey 1 | P2: Water 2 | Q2: Suspension 1 | R2: Sediment 2 | S2: Whey 2 | T2: Water 3 | U2: Suspension 2 | V2: Sediment 3 | W2: Whey 3 | X2: Dried sediment | Y2: Water vapour 1 | Z2: Retentate 1 | AA2: Permeate 1 | AB2: Water 4 | AC2: Retentate 2 | AD2: Permeate 2 | AE2: Pasteurised retentate | AF2: Hold retentate | AG2: Retentate 3 | AH2: Permeate 3 | AI2: Spray dried powder | AJ2: Water vapour 2
A3: 0 | B3: kg | C3: Total Mass | D3: 100 | E3: 90.881824 | F3: 9.1181764 | G3: 90.881824 | H3: 5.052529 | I3: 1121.36 | J3: 1217.2944 | K3: 1217.2944 | L3: 300.01729 | M3: 917.27706 | N3: 127.79938 | O3: 172.21791 | P3: 127.807 | Q3: 255.60638 | R3: 121.76827 | S3: 133.83811 | T3: 121.77 | U3: 243.53827 | V3: 121.33808 | W3: 122.20019 | X3: 32.971728 | Y3: 88.366354 | Z3: 327.59895 | AA3: 589.67811 | AB3: 294.83906 | AC3: 327.59895 | AD3: 294.83906 | AE3: 327.59895 | AF3: 327.59895 | AG3: 81.899738 | AH3: 245.69921 | AI3: 25.968186 | AJ3: 55.931552 | AL3: =C3 -> Total Mass | AM3: =_xlfn.XLOOKUP(AM$1,$D$1:$AJ$1,$D3:$AJ3) -> 100 | AN3: =_xlfn.XLOOKUP(AN$1,$D$1:$AJ$1,$D3:$AJ3) -> 5.052529 | AO3: =_xlfn.XLOOKUP(AO$1,$D$1:$AJ$1,$D3:$AJ3) -> 1121.36 | AP3: =_xlfn.XLOOKUP(AP$1,$D$1:$AJ$1,$D3:$AJ3) -> 127.807 | AQ3: =_xlfn.XLOOKUP(AQ$1,$D$1:$AJ$1,$D3:$AJ3) -> 121.77 | AR3: =_xlfn.XLOOKUP(AR$1,$D$1:$AJ$1,$D3:$AJ3) -> 294.83906 | AS3: =SUM(AM3:AR3) -> 1770.8286 | AV3: =_xlfn.XLOOKUP(AV$1,$D$1:$AJ$1,$D3:$AJ3) -> 9.1181764 | AW3: =_xlfn.XLOOKUP(AW$1,$D$1:$AJ$1,$D3:$AJ3) -> 172.21791 | AX3: =_xlfn.XLOOKUP(AX$1,$D$1:$AJ$1,$D3:$AJ3) -> 133.83811 | AY3: =_xlfn.XLOOKUP(AY$1,$D$1:$AJ$1,$D3:$AJ3) -> 122.20019 | AZ3: =_xlfn.XLOOKUP(AZ$1,$D$1:$AJ$1,$D3:$AJ3) -> 32.971728 | BA3: =_xlfn.XLOOKUP(BA$1,$D$1:$AJ$1,$D3:$AJ3) -> 88.366354 | BB3: =_xlfn.XLOOKUP(BB$1,$D$1:$AJ$1,$D3:$AJ3) -> 589.67811 | BC3: =_xlfn.XLOOKUP(BC$1,$D$1:$AJ$1,$D3:$AJ3) -> 294.83906 | ... BF3: =_xlfn.XLOOKUP(BF$1,$D$1:$AJ$1,$D3:$AJ3) -> 55.931552 | BG3: =SUM(AV3:BF3) -> 1770.8286 | BH3: =BG3-AS3 -> 0 | BJ3: =_xlfn.XLOOKUP(BJ$1,$D$1:$AJ$1,$D3:$AJ3) -> 100 | BK3: =_xlfn.XLOOKUP(BK$1,$D$1:$AJ$1,$D3:$AJ3) -> 90.881824 | BL3: =_xlfn.XLOOKUP(BL$1,$D$1:$AJ$1,$D3:$AJ3) -> 9.1181764 | BM3: =BJ3-BK3-BL3 -> 0 | BN3: =_xlfn.XLOOKUP(BN$1,$D$1:$AJ$1,$D3:$AJ3) -> 90.881824 | BO3: =_xlfn.XLOOKUP(BO$1,$D$1:$AJ$1,$D3:$AJ3) -> 90.881824 | BP3: =BN3-BO3 -> 0 | BQ3: =_xlfn.XLOOKUP(BQ$1,$D$1:$AJ$1,$D3:$AJ3) -> 90.881824 | BR3: =_xlfn.XLOOKUP(BR$1,$D$1:$AJ$1,$D3:$AJ3) -> 5.052529 | BS3: =_xlfn.XLOOKUP(BS$1,$D$1:$AJ$1,$D3:$AJ3) -> 1121.36 | BT3: =_xlfn.XLOOKUP(BT$1,$D$1:$AJ$1,$D3:$AJ3) -> 1217.2944 | BU3: =BQ3+BR3+BS3-BT3 -> 0 | BV3: =_xlfn.XLOOKUP(BV$1,$D$1:$AJ$1,$D3:$AJ3) -> 1217.2944 | BW3: =_xlfn.XLOOKUP(BW$1,$D$1:$AJ$1,$D3:$AJ3) -> 1217.2944 | BX3: =BW3-BV3 -> 0 | BY3: =_xlfn.XLOOKUP(BY$1,$D$1:$AJ$1,$D3:$AJ3) -> 1217.2944 | BZ3: =_xlfn.XLOOKUP(BZ$1,$D$1:$AJ$1,$D3:$AJ3) -> 300.01729 | CA3: =_xlfn.XLOOKUP(CA$1,$D$1:$AJ$1,$D3:$AJ3) -> 917.27706 | CB3: =BZ3+CA3-BY3 -> 0 | CC3: =_xlfn.XLOOKUP(CC$1,$D$1:$AJ$1,$D3:$AJ3) -> 300.01729 | CD3: =_xlfn.XLOOKUP(CD$1,$D$1:$AJ$1,$D3:$AJ3) -> 127.79938 | CE3: =_xlfn.XLOOKUP(CE$1,$D$1:$AJ$1,$D3:$AJ3) -> 172.21791 | CF3: =CD3+CE3-CC3 -> 0 | CG3: =_xlfn.XLOOKUP(CG$1,$D$1:$AJ$1,$D3:$AJ3) -> 127.79938 | CH3: =_xlfn.XLOOKUP(CH$1,$D$1:$AJ$1,$D3:$AJ3) -> 127.807 | CI3: =_xlfn.XLOOKUP(CI$1,$D$1:$AJ$1,$D3:$AJ3) -> 255.60638 | CJ3: =CG3+CH3-CI3 -> 0 | CK3: =_xlfn.XLOOKUP(CK$1,$D$1:$AJ$1,$D3:$AJ3) -> 255.60638 | CL3: =_xlfn.XLOOKUP(CL$1,$D$1:$AJ$1,$D3:$AJ3) -> 121.76827 | CM3: =_xlfn.XLOOKUP(CM$1,$D$1:$AJ$1,$D3:$AJ3) -> 133.83811 | CN3: =CL3+CM3-CK3 -> 0 | CO3: =_xlfn.XLOOKUP(CO$1,$D$1:$AJ$1,$D3:$AJ3) -> 121.76827 | CP3: =_xlfn.XLOOKUP(CP$1,$D$1:$AJ$1,$D3:$AJ3) -> 121.77 | CQ3: =_xlfn.XLOOKUP(CQ$1,$D$1:$AJ$1,$D3:$AJ3) -> 243.53827 | CR3: =CO3+CP3-CQ3 -> 0 | CS3: =_xlfn.XLOOKUP(CS$1,$D$1:$AJ$1,$D3:$AJ3) -> 243.53827 | CT3: =_xlfn.XLOOKUP(CT$1,$D$1:$AJ$1,$D3:$AJ3) -> 121.33808 | CU3: =_xlfn.XLOOKUP(CU$1,$D$1:$AJ$1,$D3:$AJ3) -> 122.20019 | CV3: =CT3+CU3-CS3 -> 0 | CW3: =_xlfn.XLOOKUP(CW$1,$D$1:$AJ$1,$D3:$AJ3) -> 121.33808 | CX3: =_xlfn.XLOOKUP(CX$1,$D$1:$AJ$1,$D3:$AJ3) -> 32.971728 | CY3: =_xlfn.XLOOKUP(CY$1,$D$1:$AJ$1,$D3:$AJ3) -> 88.366354 | CZ3: =CX3+CY3-CW3 -> 0 | DA3: =_xlfn.XLOOKUP(DA$1,$D$1:$AJ$1,$D3:$AJ3) -> 917.27706 | DB3: =_xlfn.XLOOKUP(DB$1,$D$1:$AJ$1,$D3:$AJ3) -> 327.59895 | DC3: =_xlfn.XLOOKUP(DC$1,$D$1:$AJ$1,$D3:$AJ3) -> 589.67811 | DD3: =DC3+DB3-DA3 -> 0 | DE3: =_xlfn.XLOOKUP(DE$1,$D$1:$AJ$1,$D3:$AJ3) -> 327.59895 | DF3: =_xlfn.XLOOKUP(DF$1,$D$1:$AJ$1,$D3:$AJ3) -> 294.83906 | DG3: =_xlfn.XLOOKUP(DG$1,$D$1:$AJ$1,$D3:$AJ3) -> 327.59895 | DH3: =_xlfn.XLOOKUP(DH$1,$D$1:$AJ$1,$D3:$AJ3) -> 294.83906 | DI3: =DG3+DH3-DF3-DE3 -> 0 | DJ3: =_xlfn.XLOOKUP(DJ$1,$D$1:$AJ$1,$D3:$AJ3) -> 327.59895 | DK3: =_xlfn.XLOOKUP(DK$1,$D$1:$AJ$1,$D3:$AJ3) -> 327.59895 | DL3: =DK3-DJ3 -> 0 | DM3: =_xlfn.XLOOKUP(DM$1,$D$1:$AJ$1,$D3:$AJ3) -> 327.59895 | DN3: =_xlfn.XLOOKUP(DN$1,$D$1:$AJ$1,$D3:$AJ3) -> 327.59895 | DO3: =DN3-DM3 -> 0 | DP3: =_xlfn.XLOOKUP(DP$1,$D$1:$AJ$1,$D3:$AJ3) -> 327.59895 | DQ3: =_xlfn.XLOOKUP(DQ$1,$D$1:$AJ$1,$D3:$AJ3) -> 81.899738 | DR3: =_xlfn.XLOOKUP(DR$1,$D$1:$AJ$1,$D3:$AJ3) -> 245.69921 | DS3: =DQ3+DR3-DP3 -> 0 | DT3: =_xlfn.XLOOKUP(DT$1,$D$1:$AJ$1,$D3:$AJ3) -> 81.899738 | DU3: =_xlfn.XLOOKUP(DU$1,$D$1:$AJ$1,$D3:$AJ3) -> 25.968186 | DV3: =_xlfn.XLOOKUP(DV$1,$D$1:$AJ$1,$D3:$AJ3) -> 55.931552 | DW3: =DU3+DV3-DT3 -> 0
A4: 1 | B4: kg | C4: Total Solids | D4: 88.4 | E4: 80.693048 | F4: 7.7069516 | G4: 80.693048 | H4: 0.40420232 | I4: 0 | J4: 81.097251 | K4: 81.097251 | L4: 37.984319 | M4: 43.112932 | N4: 32.30654 | O4: 5.6777787 | P4: 0 | Q4: 32.30654 | R4: 31.220939 | S4: 1.0856011 | T4: 0 | U4: 31.220939 | V4: 31.059368 | W4: 0.16157059 | X4: 31.059368 | Y4: 0 | Z4: 29.143986 | AA4: 13.968946 | AB4: 0 | AC4: 24.50497 | AD4: 4.6390158 | AE4: 24.50497 | AF4: 24.50497 | AG4: 24.462031 | AH4: 0.042939142 | AI4: 24.462031 | AJ4: 0 | AL4: =C4 -> Total Solids | AM4: =_xlfn.XLOOKUP(AM$1,$D$1:$AJ$1,$D4:$AJ4) -> 88.4 | AN4: =_xlfn.XLOOKUP(AN$1,$D$1:$AJ$1,$D4:$AJ4) -> 0.40420232 | AO4: =_xlfn.XLOOKUP(AO$1,$D$1:$AJ$1,$D4:$AJ4) -> 0 | AP4: =_xlfn.XLOOKUP(AP$1,$D$1:$AJ$1,$D4:$AJ4) -> 0 | AQ4: =_xlfn.XLOOKUP(AQ$1,$D$1:$AJ$1,$D4:$AJ4) -> 0 | AR4: =_xlfn.XLOOKUP(AR$1,$D$1:$AJ$1,$D4:$AJ4) -> 0 | AS4: =SUM(AM4:AR4) -> 88.804202 | AV4: =_xlfn.XLOOKUP(AV$1,$D$1:$AJ$1,$D4:$AJ4) -> 7.7069516 | AW4: =_xlfn.XLOOKUP(AW$1,$D$1:$AJ$1,$D4:$AJ4) -> 5.6777787 | AX4: =_xlfn.XLOOKUP(AX$1,$D$1:$AJ$1,$D4:$AJ4) -> 1.0856011 | AY4: =_xlfn.XLOOKUP(AY$1,$D$1:$AJ$1,$D4:$AJ4) -> 0.16157059 | AZ4: =_xlfn.XLOOKUP(AZ$1,$D$1:$AJ$1,$D4:$AJ4) -> 31.059368 | BA4: =_xlfn.XLOOKUP(BA$1,$D$1:$AJ$1,$D4:$AJ4) -> 0 | BB4: =_xlfn.XLOOKUP(BB$1,$D$1:$AJ$1,$D4:$AJ4) -> 13.968946 | BC4: =_xlfn.XLOOKUP(BC$1,$D$1:$AJ$1,$D4:$AJ4) -> 4.6390158 | ... BF4: =_xlfn.XLOOKUP(BF$1,$D$1:$AJ$1,$D4:$AJ4) -> 0 | BG4: =SUM(AV4:BF4) -> 88.804202 | BH4: =BG4-AS4 -> 0 | BJ4: =_xlfn.XLOOKUP(BJ$1,$D$1:$AJ$1,$D4:$AJ4) -> 88.4 | BK4: =_xlfn.XLOOKUP(BK$1,$D$1:$AJ$1,$D4:$AJ4) -> 80.693048 | BL4: =_xlfn.XLOOKUP(BL$1,$D$1:$AJ$1,$D4:$AJ4) -> 7.7069516 | BM4: =BJ4-BK4-BL4 -> -1.2434498e-14 | BN4: =_xlfn.XLOOKUP(BN$1,$D$1:$AJ$1,$D4:$AJ4) -> 80.693048 | BO4: =_xlfn.XLOOKUP(BO$1,$D$1:$AJ$1,$D4:$AJ4) -> 80.693048 | BP4: =BN4-BO4 -> 0 | BQ4: =_xlfn.XLOOKUP(BQ$1,$D$1:$AJ$1,$D4:$AJ4) -> 80.693048 | BR4: =_xlfn.XLOOKUP(BR$1,$D$1:$AJ$1,$D4:$AJ4) -> 0.40420232 | BS4: =_xlfn.XLOOKUP(BS$1,$D$1:$AJ$1,$D4:$AJ4) -> 0 | BT4: =_xlfn.XLOOKUP(BT$1,$D$1:$AJ$1,$D4:$AJ4) -> 81.097251 | BU4: =BQ4+BR4+BS4-BT4 -> 0 | BV4: =_xlfn.XLOOKUP(BV$1,$D$1:$AJ$1,$D4:$AJ4) -> 81.097251 | BW4: =_xlfn.XLOOKUP(BW$1,$D$1:$AJ$1,$D4:$AJ4) -> 81.097251 | BX4: =BW4-BV4 -> 0 | BY4: =_xlfn.XLOOKUP(BY$1,$D$1:$AJ$1,$D4:$AJ4) -> 81.097251 | BZ4: =_xlfn.XLOOKUP(BZ$1,$D$1:$AJ$1,$D4:$AJ4) -> 37.984319 | CA4: =_xlfn.XLOOKUP(CA$1,$D$1:$AJ$1,$D4:$AJ4) -> 43.112932 | CB4: =BZ4+CA4-BY4 -> 0 | CC4: =_xlfn.XLOOKUP(CC$1,$D$1:$AJ$1,$D4:$AJ4) -> 37.984319 | CD4: =_xlfn.XLOOKUP(CD$1,$D$1:$AJ$1,$D4:$AJ4) -> 32.30654 | CE4: =_xlfn.XLOOKUP(CE$1,$D$1:$AJ$1,$D4:$AJ4) -> 5.6777787 | CF4: =CD4+CE4-CC4 -> 0 | CG4: =_xlfn.XLOOKUP(CG$1,$D$1:$AJ$1,$D4:$AJ4) -> 32.30654 | CH4: =_xlfn.XLOOKUP(CH$1,$D$1:$AJ$1,$D4:$AJ4) -> 0 | CI4: =_xlfn.XLOOKUP(CI$1,$D$1:$AJ$1,$D4:$AJ4) -> 32.30654 | CJ4: =CG4+CH4-CI4 -> 0 | CK4: =_xlfn.XLOOKUP(CK$1,$D$1:$AJ$1,$D4:$AJ4) -> 32.30654 | CL4: =_xlfn.XLOOKUP(CL$1,$D$1:$AJ$1,$D4:$AJ4) -> 31.220939 | CM4: =_xlfn.XLOOKUP(CM$1,$D$1:$AJ$1,$D4:$AJ4) -> 1.0856011 | CN4: =CL4+CM4-CK4 -> 0 | CO4: =_xlfn.XLOOKUP(CO$1,$D$1:$AJ$1,$D4:$AJ4) -> 31.220939 | CP4: =_xlfn.XLOOKUP(CP$1,$D$1:$AJ$1,$D4:$AJ4) -> 0 | CQ4: =_xlfn.XLOOKUP(CQ$1,$D$1:$AJ$1,$D4:$AJ4) -> 31.220939 | CR4: =CO4+CP4-CQ4 -> 0 | CS4: =_xlfn.XLOOKUP(CS$1,$D$1:$AJ$1,$D4:$AJ4) -> 31.220939 | CT4: =_xlfn.XLOOKUP(CT$1,$D$1:$AJ$1,$D4:$AJ4) -> 31.059368 | CU4: =_xlfn.XLOOKUP(CU$1,$D$1:$AJ$1,$D4:$AJ4) -> 0.16157059 | CV4: =CT4+CU4-CS4 -> 0 | CW4: =_xlfn.XLOOKUP(CW$1,$D$1:$AJ$1,$D4:$AJ4) -> 31.059368 | CX4: =_xlfn.XLOOKUP(CX$1,$D$1:$AJ$1,$D4:$AJ4) -> 31.059368 | CY4: =_xlfn.XLOOKUP(CY$1,$D$1:$AJ$1,$D4:$AJ4) -> 0 | CZ4: =CX4+CY4-CW4 -> 0 | DA4: =_xlfn.XLOOKUP(DA$1,$D$1:$AJ$1,$D4:$AJ4) -> 43.112932 | DB4: =_xlfn.XLOOKUP(DB$1,$D$1:$AJ$1,$D4:$AJ4) -> 29.143986 | DC4: =_xlfn.XLOOKUP(DC$1,$D$1:$AJ$1,$D4:$AJ4) -> 13.968946 | DD4: =DC4+DB4-DA4 -> 0 | DE4: =_xlfn.XLOOKUP(DE$1,$D$1:$AJ$1,$D4:$AJ4) -> 29.143986 | DF4: =_xlfn.XLOOKUP(DF$1,$D$1:$AJ$1,$D4:$AJ4) -> 0 | DG4: =_xlfn.XLOOKUP(DG$1,$D$1:$AJ$1,$D4:$AJ4) -> 24.50497 | DH4: =_xlfn.XLOOKUP(DH$1,$D$1:$AJ$1,$D4:$AJ4) -> 4.6390158 | DI4: =DG4+DH4-DF4-DE4 -> 0 | DJ4: =_xlfn.XLOOKUP(DJ$1,$D$1:$AJ$1,$D4:$AJ4) -> 24.50497 | DK4: =_xlfn.XLOOKUP(DK$1,$D$1:$AJ$1,$D4:$AJ4) -> 24.50497 | DL4: =DK4-DJ4 -> 0 | DM4: =_xlfn.XLOOKUP(DM$1,$D$1:$AJ$1,$D4:$AJ4) -> 24.50497 | DN4: =_xlfn.XLOOKUP(DN$1,$D$1:$AJ$1,$D4:$AJ4) -> 24.50497 | DO4: =DN4-DM4 -> 0 | DP4: =_xlfn.XLOOKUP(DP$1,$D$1:$AJ$1,$D4:$AJ4) -> 24.50497 | DQ4: =_xlfn.XLOOKUP(DQ$1,$D$1:$AJ$1,$D4:$AJ4) -> 24.462031 | DR4: =_xlfn.XLOOKUP(DR$1,$D$1:$AJ$1,$D4:$AJ4) -> 0.042939142 | DS4: =DQ4+DR4-DP4 -> 0 | DT4: =_xlfn.XLOOKUP(DT$1,$D$1:$AJ$1,$D4:$AJ4) -> 24.462031 | DU4: =_xlfn.XLOOKUP(DU$1,$D$1:$AJ$1,$D4:$AJ4) -> 24.462031 | DV4: =_xlfn.XLOOKUP(DV$1,$D$1:$AJ$1,$D4:$AJ4) -> 0 | DW4: =DU4+DV4-DT4 -> 0
A5: 2 | B5: kg | C5: Ash | D5: 3.4 | E5: 2.9608912 | F5: 0.4391088 | G5: 2.9608912 | H5: 0 | I5: 0 | J5: 2.9608912 | K5: 2.9608912 | L5: 0.50999811 | M5: 2.4508931 | N5: 0.38877773 | O5: 0.12122038 | P5: 0 | Q5: 0.38877773 | R5: 0.36510472 | S5: 0.02367301 | T5: 0 | U5: 0.36510472 | V5: 0.36180124 | W5: 0.0033034782 | X5: 0.36180124 | Y5: 0 | Z5: 1.6902711 | AA5: 0.76062199 | AB5: 0 | AC5: 1.3798131 | AD5: 0.31045796 | AE5: 1.3798131 | AF5: 1.3798131 | AG5: 1.3798131 | AH5: 0 | AI5: 1.3798131 | AJ5: 0 | AL5: =C5 -> Ash | AM5: =_xlfn.XLOOKUP(AM$1,$D$1:$AJ$1,$D5:$AJ5) -> 3.4 | AN5: =_xlfn.XLOOKUP(AN$1,$D$1:$AJ$1,$D5:$AJ5) -> 0 | AO5: =_xlfn.XLOOKUP(AO$1,$D$1:$AJ$1,$D5:$AJ5) -> 0 | AP5: =_xlfn.XLOOKUP(AP$1,$D$1:$AJ$1,$D5:$AJ5) -> 0 | AQ5: =_xlfn.XLOOKUP(AQ$1,$D$1:$AJ$1,$D5:$AJ5) -> 0 | AR5: =_xlfn.XLOOKUP(AR$1,$D$1:$AJ$1,$D5:$AJ5) -> 0 | AS5: =SUM(AM5:AR5) -> 3.4 | AV5: =_xlfn.XLOOKUP(AV$1,$D$1:$AJ$1,$D5:$AJ5) -> 0.4391088 | AW5: =_xlfn.XLOOKUP(AW$1,$D$1:$AJ$1,$D5:$AJ5) -> 0.12122038 | AX5: =_xlfn.XLOOKUP(AX$1,$D$1:$AJ$1,$D5:$AJ5) -> 0.02367301 | AY5: =_xlfn.XLOOKUP(AY$1,$D$1:$AJ$1,$D5:$AJ5) -> 0.0033034782 | AZ5: =_xlfn.XLOOKUP(AZ$1,$D$1:$AJ$1,$D5:$AJ5) -> 0.36180124 | BA5: =_xlfn.XLOOKUP(BA$1,$D$1:$AJ$1,$D5:$AJ5) -> 0 | BB5: =_xlfn.XLOOKUP(BB$1,$D$1:$AJ$1,$D5:$AJ5) -> 0.76062199 | BC5: =_xlfn.XLOOKUP(BC$1,$D$1:$AJ$1,$D5:$AJ5) -> 0.31045796 | ... BF5: =_xlfn.XLOOKUP(BF$1,$D$1:$AJ$1,$D5:$AJ5) -> 0 | BG5: =SUM(AV5:BF5) -> 3.4 | BH5: =BG5-AS5 -> 0 | BJ5: =_xlfn.XLOOKUP(BJ$1,$D$1:$AJ$1,$D5:$AJ5) -> 3.4 | BK5: =_xlfn.XLOOKUP(BK$1,$D$1:$AJ$1,$D5:$AJ5) -> 2.9608912 | BL5: =_xlfn.XLOOKUP(BL$1,$D$1:$AJ$1,$D5:$AJ5) -> 0.4391088 | BM5: =BJ5-BK5-BL5 -> -8.3266727e-16 | BN5: =_xlfn.XLOOKUP(BN$1,$D$1:$AJ$1,$D5:$AJ5) -> 2.9608912 | BO5: =_xlfn.XLOOKUP(BO$1,$D$1:$AJ$1,$D5:$AJ5) -> 2.9608912 | BP5: =BN5-BO5 -> 0 | BQ5: =_xlfn.XLOOKUP(BQ$1,$D$1:$AJ$1,$D5:$AJ5) -> 2.9608912 | BR5: =_xlfn.XLOOKUP(BR$1,$D$1:$AJ$1,$D5:$AJ5) -> 0 | BS5: =_xlfn.XLOOKUP(BS$1,$D$1:$AJ$1,$D5:$AJ5) -> 0 | BT5: =_xlfn.XLOOKUP(BT$1,$D$1:$AJ$1,$D5:$AJ5) -> 2.9608912 | BU5: =BQ5+BR5+BS5-BT5 -> 0 | BV5: =_xlfn.XLOOKUP(BV$1,$D$1:$AJ$1,$D5:$AJ5) -> 2.9608912 | BW5: =_xlfn.XLOOKUP(BW$1,$D$1:$AJ$1,$D5:$AJ5) -> 2.9608912 | BX5: =BW5-BV5 -> 0 | BY5: =_xlfn.XLOOKUP(BY$1,$D$1:$AJ$1,$D5:$AJ5) -> 2.9608912 | BZ5: =_xlfn.XLOOKUP(BZ$1,$D$1:$AJ$1,$D5:$AJ5) -> 0.50999811 | CA5: =_xlfn.XLOOKUP(CA$1,$D$1:$AJ$1,$D5:$AJ5) -> 2.4508931 | CB5: =BZ5+CA5-BY5 -> 0 | CC5: =_xlfn.XLOOKUP(CC$1,$D$1:$AJ$1,$D5:$AJ5) -> 0.50999811 | CD5: =_xlfn.XLOOKUP(CD$1,$D$1:$AJ$1,$D5:$AJ5) -> 0.38877773 | CE5: =_xlfn.XLOOKUP(CE$1,$D$1:$AJ$1,$D5:$AJ5) -> 0.12122038 | CF5: =CD5+CE5-CC5 -> 0 | CG5: =_xlfn.XLOOKUP(CG$1,$D$1:$AJ$1,$D5:$AJ5) -> 0.38877773 | CH5: =_xlfn.XLOOKUP(CH$1,$D$1:$AJ$1,$D5:$AJ5) -> 0 | CI5: =_xlfn.XLOOKUP(CI$1,$D$1:$AJ$1,$D5:$AJ5) -> 0.38877773 | CJ5: =CG5+CH5-CI5 -> 0 | CK5: =_xlfn.XLOOKUP(CK$1,$D$1:$AJ$1,$D5:$AJ5) -> 0.38877773 | CL5: =_xlfn.XLOOKUP(CL$1,$D$1:$AJ$1,$D5:$AJ5) -> 0.36510472 | CM5: =_xlfn.XLOOKUP(CM$1,$D$1:$AJ$1,$D5:$AJ5) -> 0.02367301 | CN5: =CL5+CM5-CK5 -> 0 | CO5: =_xlfn.XLOOKUP(CO$1,$D$1:$AJ$1,$D5:$AJ5) -> 0.36510472 | CP5: =_xlfn.XLOOKUP(CP$1,$D$1:$AJ$1,$D5:$AJ5) -> 0 | CQ5: =_xlfn.XLOOKUP(CQ$1,$D$1:$AJ$1,$D5:$AJ5) -> 0.36510472 | CR5: =CO5+CP5-CQ5 -> 0 | CS5: =_xlfn.XLOOKUP(CS$1,$D$1:$AJ$1,$D5:$AJ5) -> 0.36510472 | CT5: =_xlfn.XLOOKUP(CT$1,$D$1:$AJ$1,$D5:$AJ5) -> 0.36180124 | CU5: =_xlfn.XLOOKUP(CU$1,$D$1:$AJ$1,$D5:$AJ5) -> 0.0033034782 | CV5: =CT5+CU5-CS5 -> 0 | CW5: =_xlfn.XLOOKUP(CW$1,$D$1:$AJ$1,$D5:$AJ5) -> 0.36180124 | CX5: =_xlfn.XLOOKUP(CX$1,$D$1:$AJ$1,$D5:$AJ5) -> 0.36180124 | CY5: =_xlfn.XLOOKUP(CY$1,$D$1:$AJ$1,$D5:$AJ5) -> 0 | CZ5: =CX5+CY5-CW5 -> 0 | DA5: =_xlfn.XLOOKUP(DA$1,$D$1:$AJ$1,$D5:$AJ5) -> 2.4508931 | DB5: =_xlfn.XLOOKUP(DB$1,$D$1:$AJ$1,$D5:$AJ5) -> 1.6902711 | DC5: =_xlfn.XLOOKUP(DC$1,$D$1:$AJ$1,$D5:$AJ5) -> 0.76062199 | DD5: =DC5+DB5-DA5 -> 0 | DE5: =_xlfn.XLOOKUP(DE$1,$D$1:$AJ$1,$D5:$AJ5) -> 1.6902711 | DF5: =_xlfn.XLOOKUP(DF$1,$D$1:$AJ$1,$D5:$AJ5) -> 0 | DG5: =_xlfn.XLOOKUP(DG$1,$D$1:$AJ$1,$D5:$AJ5) -> 1.3798131 | DH5: =_xlfn.XLOOKUP(DH$1,$D$1:$AJ$1,$D5:$AJ5) -> 0.31045796 | DI5: =DG5+DH5-DF5-DE5 -> 0 | DJ5: =_xlfn.XLOOKUP(DJ$1,$D$1:$AJ$1,$D5:$AJ5) -> 1.3798131 | DK5: =_xlfn.XLOOKUP(DK$1,$D$1:$AJ$1,$D5:$AJ5) -> 1.3798131 | DL5: =DK5-DJ5 -> 0 | DM5: =_xlfn.XLOOKUP(DM$1,$D$1:$AJ$1,$D5:$AJ5) -> 1.3798131 | DN5: =_xlfn.XLOOKUP(DN$1,$D$1:$AJ$1,$D5:$AJ5) -> 1.3798131 | DO5: =DN5-DM5 -> 0 | DP5: =_xlfn.XLOOKUP(DP$1,$D$1:$AJ$1,$D5:$AJ5) -> 1.3798131 | DQ5: =_xlfn.XLOOKUP(DQ$1,$D$1:$AJ$1,$D5:$AJ5) -> 1.3798131 | DR5: =_xlfn.XLOOKUP(DR$1,$D$1:$AJ$1,$D5:$AJ5) -> 0 | DS5: =DQ5+DR5-DP5 -> 0 | DT5: =_xlfn.XLOOKUP(DT$1,$D$1:$AJ$1,$D5:$AJ5) -> 1.3798131 | DU5: =_xlfn.XLOOKUP(DU$1,$D$1:$AJ$1,$D5:$AJ5) -> 1.3798131 | DV5: =_xlfn.XLOOKUP(DV$1,$D$1:$AJ$1,$D5:$AJ5) -> 0 | DW5: =DU5+DV5-DT5 -> 0
A6: 3 | B6: kg | C6: Protein | D6: 23.2 | E6: 22.490211 | F6: 0.70978913 | G6: 22.490211 | H6: 0 | I6: 0 | J6: 22.490211 | K6: 22.490211 | L6: 6.0606677 | M6: 16.429543 | N6: 4.5417257 | O6: 1.518942 | P6: 0 | Q6: 4.5417257 | R6: 4.2466584 | S6: 0.29506727 | T6: 0 | U6: 4.2466584 | V6: 4.2029469 | W6: 0.043711524 | X6: 4.2029469 | Y6: 0 | Z6: 14.361489 | AA6: 2.0680544 | AB6: 0 | AC6: 13.396911 | AD6: 0.96457761 | AE6: 13.396911 | AF6: 13.396911 | AG6: 13.396911 | AH6: 0 | AI6: 13.396911 | AJ6: 0 | AL6: =C6 -> Protein | AM6: =_xlfn.XLOOKUP(AM$1,$D$1:$AJ$1,$D6:$AJ6) -> 23.2 | AN6: =_xlfn.XLOOKUP(AN$1,$D$1:$AJ$1,$D6:$AJ6) -> 0 | AO6: =_xlfn.XLOOKUP(AO$1,$D$1:$AJ$1,$D6:$AJ6) -> 0 | AP6: =_xlfn.XLOOKUP(AP$1,$D$1:$AJ$1,$D6:$AJ6) -> 0 | AQ6: =_xlfn.XLOOKUP(AQ$1,$D$1:$AJ$1,$D6:$AJ6) -> 0 | AR6: =_xlfn.XLOOKUP(AR$1,$D$1:$AJ$1,$D6:$AJ6) -> 0 | AS6: =SUM(AM6:AR6) -> 23.2 | AV6: =_xlfn.XLOOKUP(AV$1,$D$1:$AJ$1,$D6:$AJ6) -> 0.70978913 | AW6: =_xlfn.XLOOKUP(AW$1,$D$1:$AJ$1,$D6:$AJ6) -> 1.518942 | AX6: =_xlfn.XLOOKUP(AX$1,$D$1:$AJ$1,$D6:$AJ6) -> 0.29506727 | AY6: =_xlfn.XLOOKUP(AY$1,$D$1:$AJ$1,$D6:$AJ6) -> 0.043711524 | AZ6: =_xlfn.XLOOKUP(AZ$1,$D$1:$AJ$1,$D6:$AJ6) -> 4.2029469 | BA6: =_xlfn.XLOOKUP(BA$1,$D$1:$AJ$1,$D6:$AJ6) -> 0 | BB6: =_xlfn.XLOOKUP(BB$1,$D$1:$AJ$1,$D6:$AJ6) -> 2.0680544 | BC6: =_xlfn.XLOOKUP(BC$1,$D$1:$AJ$1,$D6:$AJ6) -> 0.96457761 | ... BF6: =_xlfn.XLOOKUP(BF$1,$D$1:$AJ$1,$D6:$AJ6) -> 0 | BG6: =SUM(AV6:BF6) -> 23.2 | BH6: =BG6-AS6 -> 0 | BJ6: =_xlfn.XLOOKUP(BJ$1,$D$1:$AJ$1,$D6:$AJ6) -> 23.2 | BK6: =_xlfn.XLOOKUP(BK$1,$D$1:$AJ$1,$D6:$AJ6) -> 22.490211 | BL6: =_xlfn.XLOOKUP(BL$1,$D$1:$AJ$1,$D6:$AJ6) -> 0.70978913 | BM6: =BJ6-BK6-BL6 -> -1.7763568e-15 | BN6: =_xlfn.XLOOKUP(BN$1,$D$1:$AJ$1,$D6:$AJ6) -> 22.490211 | BO6: =_xlfn.XLOOKUP(BO$1,$D$1:$AJ$1,$D6:$AJ6) -> 22.490211 | BP6: =BN6-BO6 -> 0 | BQ6: =_xlfn.XLOOKUP(BQ$1,$D$1:$AJ$1,$D6:$AJ6) -> 22.490211 | BR6: =_xlfn.XLOOKUP(BR$1,$D$1:$AJ$1,$D6:$AJ6) -> 0 | BS6: =_xlfn.XLOOKUP(BS$1,$D$1:$AJ$1,$D6:$AJ6) -> 0 | BT6: =_xlfn.XLOOKUP(BT$1,$D$1:$AJ$1,$D6:$AJ6) -> 22.490211 | BU6: =BQ6+BR6+BS6-BT6 -> 0 | BV6: =_xlfn.XLOOKUP(BV$1,$D$1:$AJ$1,$D6:$AJ6) -> 22.490211 | BW6: =_xlfn.XLOOKUP(BW$1,$D$1:$AJ$1,$D6:$AJ6) -> 22.490211 | BX6: =BW6-BV6 -> 0 | BY6: =_xlfn.XLOOKUP(BY$1,$D$1:$AJ$1,$D6:$AJ6) -> 22.490211 | BZ6: =_xlfn.XLOOKUP(BZ$1,$D$1:$AJ$1,$D6:$AJ6) -> 6.0606677 | CA6: =_xlfn.XLOOKUP(CA$1,$D$1:$AJ$1,$D6:$AJ6) -> 16.429543 | CB6: =BZ6+CA6-BY6 -> 0 | CC6: =_xlfn.XLOOKUP(CC$1,$D$1:$AJ$1,$D6:$AJ6) -> 6.0606677 | CD6: =_xlfn.XLOOKUP(CD$1,$D$1:$AJ$1,$D6:$AJ6) -> 4.5417257 | CE6: =_xlfn.XLOOKUP(CE$1,$D$1:$AJ$1,$D6:$AJ6) -> 1.518942 | CF6: =CD6+CE6-CC6 -> 0 | CG6: =_xlfn.XLOOKUP(CG$1,$D$1:$AJ$1,$D6:$AJ6) -> 4.5417257 | CH6: =_xlfn.XLOOKUP(CH$1,$D$1:$AJ$1,$D6:$AJ6) -> 0 | CI6: =_xlfn.XLOOKUP(CI$1,$D$1:$AJ$1,$D6:$AJ6) -> 4.5417257 | CJ6: =CG6+CH6-CI6 -> 0 | CK6: =_xlfn.XLOOKUP(CK$1,$D$1:$AJ$1,$D6:$AJ6) -> 4.5417257 | CL6: =_xlfn.XLOOKUP(CL$1,$D$1:$AJ$1,$D6:$AJ6) -> 4.2466584 | CM6: =_xlfn.XLOOKUP(CM$1,$D$1:$AJ$1,$D6:$AJ6) -> 0.29506727 | CN6: =CL6+CM6-CK6 -> 0 | CO6: =_xlfn.XLOOKUP(CO$1,$D$1:$AJ$1,$D6:$AJ6) -> 4.2466584 | CP6: =_xlfn.XLOOKUP(CP$1,$D$1:$AJ$1,$D6:$AJ6) -> 0 | CQ6: =_xlfn.XLOOKUP(CQ$1,$D$1:$AJ$1,$D6:$AJ6) -> 4.2466584 | CR6: =CO6+CP6-CQ6 -> 0 | CS6: =_xlfn.XLOOKUP(CS$1,$D$1:$AJ$1,$D6:$AJ6) -> 4.2466584 | CT6: =_xlfn.XLOOKUP(CT$1,$D$1:$AJ$1,$D6:$AJ6) -> 4.2029469 | CU6: =_xlfn.XLOOKUP(CU$1,$D$1:$AJ$1,$D6:$AJ6) -> 0.043711524 | CV6: =CT6+CU6-CS6 -> 0 | CW6: =_xlfn.XLOOKUP(CW$1,$D$1:$AJ$1,$D6:$AJ6) -> 4.2029469 | CX6: =_xlfn.XLOOKUP(CX$1,$D$1:$AJ$1,$D6:$AJ6) -> 4.2029469 | CY6: =_xlfn.XLOOKUP(CY$1,$D$1:$AJ$1,$D6:$AJ6) -> 0 | CZ6: =CX6+CY6-CW6 -> 0 | DA6: =_xlfn.XLOOKUP(DA$1,$D$1:$AJ$1,$D6:$AJ6) -> 16.429543 | DB6: =_xlfn.XLOOKUP(DB$1,$D$1:$AJ$1,$D6:$AJ6) -> 14.361489 | DC6: =_xlfn.XLOOKUP(DC$1,$D$1:$AJ$1,$D6:$AJ6) -> 2.0680544 | DD6: =DC6+DB6-DA6 -> 0 | DE6: =_xlfn.XLOOKUP(DE$1,$D$1:$AJ$1,$D6:$AJ6) -> 14.361489 | DF6: =_xlfn.XLOOKUP(DF$1,$D$1:$AJ$1,$D6:$AJ6) -> 0 | DG6: =_xlfn.XLOOKUP(DG$1,$D$1:$AJ$1,$D6:$AJ6) -> 13.396911 | DH6: =_xlfn.XLOOKUP(DH$1,$D$1:$AJ$1,$D6:$AJ6) -> 0.96457761 | DI6: =DG6+DH6-DF6-DE6 -> 0 | DJ6: =_xlfn.XLOOKUP(DJ$1,$D$1:$AJ$1,$D6:$AJ6) -> 13.396911 | DK6: =_xlfn.XLOOKUP(DK$1,$D$1:$AJ$1,$D6:$AJ6) -> 13.396911 | DL6: =DK6-DJ6 -> 0 | DM6: =_xlfn.XLOOKUP(DM$1,$D$1:$AJ$1,$D6:$AJ6) -> 13.396911 | DN6: =_xlfn.XLOOKUP(DN$1,$D$1:$AJ$1,$D6:$AJ6) -> 13.396911 | DO6: =DN6-DM6 -> 0 | DP6: =_xlfn.XLOOKUP(DP$1,$D$1:$AJ$1,$D6:$AJ6) -> 13.396911 | DQ6: =_xlfn.XLOOKUP(DQ$1,$D$1:$AJ$1,$D6:$AJ6) -> 13.396911 | DR6: =_xlfn.XLOOKUP(DR$1,$D$1:$AJ$1,$D6:$AJ6) -> 0 | DS6: =DQ6+DR6-DP6 -> 0 | DT6: =_xlfn.XLOOKUP(DT$1,$D$1:$AJ$1,$D6:$AJ6) -> 13.396911 | DU6: =_xlfn.XLOOKUP(DU$1,$D$1:$AJ$1,$D6:$AJ6) -> 13.396911 | DV6: =_xlfn.XLOOKUP(DV$1,$D$1:$AJ$1,$D6:$AJ6) -> 0 | DW6: =DU6+DV6-DT6 -> 0
A7: 4 | B7: kg | C7: Fat | D7: 1.6 | E7: 1.5635191 | F7: 0.036480912 | G7: 1.5635191 | H7: 0 | I7: 0 | J7: 1.5635191 | K7: 1.5635191 | L7: 0.80936216 | M7: 0.75415692 | N7: 0.58732453 | O7: 0.22203763 | P7: 0 | Q7: 0.58732453 | R7: 0.54398291 | S7: 0.043341616 | T7: 0 | U7: 0.54398291 | V7: 0.53706088 | W7: 0.0069220385 | X7: 0.53706088 | Y7: 0 | Z7: 0.75415692 | AA7: 0 | AB7: 0 | AC7: 0.75415692 | AD7: 0 | AE7: 0.75415692 | AF7: 0.75415692 | AG7: 0.75415692 | AH7: 0 | AI7: 0.75415692 | AJ7: 0 | AL7: =C7 -> Fat | AM7: =_xlfn.XLOOKUP(AM$1,$D$1:$AJ$1,$D7:$AJ7) -> 1.6 | AN7: =_xlfn.XLOOKUP(AN$1,$D$1:$AJ$1,$D7:$AJ7) -> 0 | AO7: =_xlfn.XLOOKUP(AO$1,$D$1:$AJ$1,$D7:$AJ7) -> 0 | AP7: =_xlfn.XLOOKUP(AP$1,$D$1:$AJ$1,$D7:$AJ7) -> 0 | AQ7: =_xlfn.XLOOKUP(AQ$1,$D$1:$AJ$1,$D7:$AJ7) -> 0 | AR7: =_xlfn.XLOOKUP(AR$1,$D$1:$AJ$1,$D7:$AJ7) -> 0 | AS7: =SUM(AM7:AR7) -> 1.6 | AV7: =_xlfn.XLOOKUP(AV$1,$D$1:$AJ$1,$D7:$AJ7) -> 0.036480912 | AW7: =_xlfn.XLOOKUP(AW$1,$D$1:$AJ$1,$D7:$AJ7) -> 0.22203763 | AX7: =_xlfn.XLOOKUP(AX$1,$D$1:$AJ$1,$D7:$AJ7) -> 0.043341616 | AY7: =_xlfn.XLOOKUP(AY$1,$D$1:$AJ$1,$D7:$AJ7) -> 0.0069220385 | AZ7: =_xlfn.XLOOKUP(AZ$1,$D$1:$AJ$1,$D7:$AJ7) -> 0.53706088 | BA7: =_xlfn.XLOOKUP(BA$1,$D$1:$AJ$1,$D7:$AJ7) -> 0 | BB7: =_xlfn.XLOOKUP(BB$1,$D$1:$AJ$1,$D7:$AJ7) -> 0 | BC7: =_xlfn.XLOOKUP(BC$1,$D$1:$AJ$1,$D7:$AJ7) -> 0 | ... BF7: =_xlfn.XLOOKUP(BF$1,$D$1:$AJ$1,$D7:$AJ7) -> 0 | BG7: =SUM(AV7:BF7) -> 1.6 | BH7: =BG7-AS7 -> 0 | BJ7: =_xlfn.XLOOKUP(BJ$1,$D$1:$AJ$1,$D7:$AJ7) -> 1.6 | BK7: =_xlfn.XLOOKUP(BK$1,$D$1:$AJ$1,$D7:$AJ7) -> 1.5635191 | BL7: =_xlfn.XLOOKUP(BL$1,$D$1:$AJ$1,$D7:$AJ7) -> 0.036480912 | BM7: =BJ7-BK7-BL7 -> 5.2735594e-16 | BN7: =_xlfn.XLOOKUP(BN$1,$D$1:$AJ$1,$D7:$AJ7) -> 1.5635191 | BO7: =_xlfn.XLOOKUP(BO$1,$D$1:$AJ$1,$D7:$AJ7) -> 1.5635191 | BP7: =BN7-BO7 -> 0 | BQ7: =_xlfn.XLOOKUP(BQ$1,$D$1:$AJ$1,$D7:$AJ7) -> 1.5635191 | BR7: =_xlfn.XLOOKUP(BR$1,$D$1:$AJ$1,$D7:$AJ7) -> 0 | BS7: =_xlfn.XLOOKUP(BS$1,$D$1:$AJ$1,$D7:$AJ7) -> 0 | BT7: =_xlfn.XLOOKUP(BT$1,$D$1:$AJ$1,$D7:$AJ7) -> 1.5635191 | BU7: =BQ7+BR7+BS7-BT7 -> 0 | BV7: =_xlfn.XLOOKUP(BV$1,$D$1:$AJ$1,$D7:$AJ7) -> 1.5635191 | BW7: =_xlfn.XLOOKUP(BW$1,$D$1:$AJ$1,$D7:$AJ7) -> 1.5635191 | BX7: =BW7-BV7 -> 0 | BY7: =_xlfn.XLOOKUP(BY$1,$D$1:$AJ$1,$D7:$AJ7) -> 1.5635191 | BZ7: =_xlfn.XLOOKUP(BZ$1,$D$1:$AJ$1,$D7:$AJ7) -> 0.80936216 | CA7: =_xlfn.XLOOKUP(CA$1,$D$1:$AJ$1,$D7:$AJ7) -> 0.75415692 | CB7: =BZ7+CA7-BY7 -> 0 | CC7: =_xlfn.XLOOKUP(CC$1,$D$1:$AJ$1,$D7:$AJ7) -> 0.80936216 | CD7: =_xlfn.XLOOKUP(CD$1,$D$1:$AJ$1,$D7:$AJ7) -> 0.58732453 | CE7: =_xlfn.XLOOKUP(CE$1,$D$1:$AJ$1,$D7:$AJ7) -> 0.22203763 | CF7: =CD7+CE7-CC7 -> 0 | CG7: =_xlfn.XLOOKUP(CG$1,$D$1:$AJ$1,$D7:$AJ7) -> 0.58732453 | CH7: =_xlfn.XLOOKUP(CH$1,$D$1:$AJ$1,$D7:$AJ7) -> 0 | CI7: =_xlfn.XLOOKUP(CI$1,$D$1:$AJ$1,$D7:$AJ7) -> 0.58732453 | CJ7: =CG7+CH7-CI7 -> 0 | CK7: =_xlfn.XLOOKUP(CK$1,$D$1:$AJ$1,$D7:$AJ7) -> 0.58732453 | CL7: =_xlfn.XLOOKUP(CL$1,$D$1:$AJ$1,$D7:$AJ7) -> 0.54398291 | CM7: =_xlfn.XLOOKUP(CM$1,$D$1:$AJ$1,$D7:$AJ7) -> 0.043341616 | CN7: =CL7+CM7-CK7 -> 0 | CO7: =_xlfn.XLOOKUP(CO$1,$D$1:$AJ$1,$D7:$AJ7) -> 0.54398291 | CP7: =_xlfn.XLOOKUP(CP$1,$D$1:$AJ$1,$D7:$AJ7) -> 0 | CQ7: =_xlfn.XLOOKUP(CQ$1,$D$1:$AJ$1,$D7:$AJ7) -> 0.54398291 | CR7: =CO7+CP7-CQ7 -> 0 | CS7: =_xlfn.XLOOKUP(CS$1,$D$1:$AJ$1,$D7:$AJ7) -> 0.54398291 | CT7: =_xlfn.XLOOKUP(CT$1,$D$1:$AJ$1,$D7:$AJ7) -> 0.53706088 | CU7: =_xlfn.XLOOKUP(CU$1,$D$1:$AJ$1,$D7:$AJ7) -> 0.0069220385 | CV7: =CT7+CU7-CS7 -> 0 | CW7: =_xlfn.XLOOKUP(CW$1,$D$1:$AJ$1,$D7:$AJ7) -> 0.53706088 | CX7: =_xlfn.XLOOKUP(CX$1,$D$1:$AJ$1,$D7:$AJ7) -> 0.53706088 | CY7: =_xlfn.XLOOKUP(CY$1,$D$1:$AJ$1,$D7:$AJ7) -> 0 | CZ7: =CX7+CY7-CW7 -> 0 | DA7: =_xlfn.XLOOKUP(DA$1,$D$1:$AJ$1,$D7:$AJ7) -> 0.75415692 | DB7: =_xlfn.XLOOKUP(DB$1,$D$1:$AJ$1,$D7:$AJ7) -> 0.75415692 | DC7: =_xlfn.XLOOKUP(DC$1,$D$1:$AJ$1,$D7:$AJ7) -> 0 | DD7: =DC7+DB7-DA7 -> 0 | DE7: =_xlfn.XLOOKUP(DE$1,$D$1:$AJ$1,$D7:$AJ7) -> 0.75415692 | DF7: =_xlfn.XLOOKUP(DF$1,$D$1:$AJ$1,$D7:$AJ7) -> 0 | DG7: =_xlfn.XLOOKUP(DG$1,$D$1:$AJ$1,$D7:$AJ7) -> 0.75415692 | DH7: =_xlfn.XLOOKUP(DH$1,$D$1:$AJ$1,$D7:$AJ7) -> 0 | DI7: =DG7+DH7-DF7-DE7 -> 0 | DJ7: =_xlfn.XLOOKUP(DJ$1,$D$1:$AJ$1,$D7:$AJ7) -> 0.75415692 | DK7: =_xlfn.XLOOKUP(DK$1,$D$1:$AJ$1,$D7:$AJ7) -> 0.75415692 | DL7: =DK7-DJ7 -> 0 | DM7: =_xlfn.XLOOKUP(DM$1,$D$1:$AJ$1,$D7:$AJ7) -> 0.75415692 | DN7: =_xlfn.XLOOKUP(DN$1,$D$1:$AJ$1,$D7:$AJ7) -> 0.75415692 | DO7: =DN7-DM7 -> 0 | DP7: =_xlfn.XLOOKUP(DP$1,$D$1:$AJ$1,$D7:$AJ7) -> 0.75415692 | DQ7: =_xlfn.XLOOKUP(DQ$1,$D$1:$AJ$1,$D7:$AJ7) -> 0.75415692 | DR7: =_xlfn.XLOOKUP(DR$1,$D$1:$AJ$1,$D7:$AJ7) -> 0 | DS7: =DQ7+DR7-DP7 -> 0 | DT7: =_xlfn.XLOOKUP(DT$1,$D$1:$AJ$1,$D7:$AJ7) -> 0.75415692 | DU7: =_xlfn.XLOOKUP(DU$1,$D$1:$AJ$1,$D7:$AJ7) -> 0.75415692 | DV7: =_xlfn.XLOOKUP(DV$1,$D$1:$AJ$1,$D7:$AJ7) -> 0 | DW7: =DU7+DV7-DT7 -> 0
A8: 5 | B8: kg | C8: Starch | D8: 22.4 | E8: 22.4 | F8: 0 | G8: 22.4 | H8: 0 | I8: 0 | J8: 22.4 | K8: 22.4 | L8: 13.738917 | M8: 8.6610828 | N8: 13.738917 | O8: 0 | P8: 0 | Q8: 13.738917 | R8: 13.738917 | S8: 0 | T8: 0 | U8: 13.738917 | V8: 13.738917 | W8: 0 | X8: 13.738917 | Y8: 0 | Z8: 6.7244432 | AA8: 1.9366396 | AB8: 0 | AC8: 5.8780098 | AD8: 0.84643341 | AE8: 5.8780098 | AF8: 5.8780098 | AG8: 5.8780098 | AH8: 0 | AI8: 5.8780098 | AJ8: 0 | AL8: =C8 -> Starch | AM8: =_xlfn.XLOOKUP(AM$1,$D$1:$AJ$1,$D8:$AJ8) -> 22.4 | AN8: =_xlfn.XLOOKUP(AN$1,$D$1:$AJ$1,$D8:$AJ8) -> 0 | AO8: =_xlfn.XLOOKUP(AO$1,$D$1:$AJ$1,$D8:$AJ8) -> 0 | AP8: =_xlfn.XLOOKUP(AP$1,$D$1:$AJ$1,$D8:$AJ8) -> 0 | AQ8: =_xlfn.XLOOKUP(AQ$1,$D$1:$AJ$1,$D8:$AJ8) -> 0 | AR8: =_xlfn.XLOOKUP(AR$1,$D$1:$AJ$1,$D8:$AJ8) -> 0 | AS8: =SUM(AM8:AR8) -> 22.4 | AV8: =_xlfn.XLOOKUP(AV$1,$D$1:$AJ$1,$D8:$AJ8) -> 0 | AW8: =_xlfn.XLOOKUP(AW$1,$D$1:$AJ$1,$D8:$AJ8) -> 0 | AX8: =_xlfn.XLOOKUP(AX$1,$D$1:$AJ$1,$D8:$AJ8) -> 0 | AY8: =_xlfn.XLOOKUP(AY$1,$D$1:$AJ$1,$D8:$AJ8) -> 0 | AZ8: =_xlfn.XLOOKUP(AZ$1,$D$1:$AJ$1,$D8:$AJ8) -> 13.738917 | BA8: =_xlfn.XLOOKUP(BA$1,$D$1:$AJ$1,$D8:$AJ8) -> 0 | BB8: =_xlfn.XLOOKUP(BB$1,$D$1:$AJ$1,$D8:$AJ8) -> 1.9366396 | BC8: =_xlfn.XLOOKUP(BC$1,$D$1:$AJ$1,$D8:$AJ8) -> 0.84643341 | ... BF8: =_xlfn.XLOOKUP(BF$1,$D$1:$AJ$1,$D8:$AJ8) -> 0 | BG8: =SUM(AV8:BF8) -> 22.4 | BH8: =BG8-AS8 -> 0 | BJ8: =_xlfn.XLOOKUP(BJ$1,$D$1:$AJ$1,$D8:$AJ8) -> 22.4 | BK8: =_xlfn.XLOOKUP(BK$1,$D$1:$AJ$1,$D8:$AJ8) -> 22.4 | BL8: =_xlfn.XLOOKUP(BL$1,$D$1:$AJ$1,$D8:$AJ8) -> 0 | BM8: =BJ8-BK8-BL8 -> 0 | BN8: =_xlfn.XLOOKUP(BN$1,$D$1:$AJ$1,$D8:$AJ8) -> 22.4 | BO8: =_xlfn.XLOOKUP(BO$1,$D$1:$AJ$1,$D8:$AJ8) -> 22.4 | BP8: =BN8-BO8 -> 0 | BQ8: =_xlfn.XLOOKUP(BQ$1,$D$1:$AJ$1,$D8:$AJ8) -> 22.4 | BR8: =_xlfn.XLOOKUP(BR$1,$D$1:$AJ$1,$D8:$AJ8) -> 0 | BS8: =_xlfn.XLOOKUP(BS$1,$D$1:$AJ$1,$D8:$AJ8) -> 0 | BT8: =_xlfn.XLOOKUP(BT$1,$D$1:$AJ$1,$D8:$AJ8) -> 22.4 | BU8: =BQ8+BR8+BS8-BT8 -> 0 | BV8: =_xlfn.XLOOKUP(BV$1,$D$1:$AJ$1,$D8:$AJ8) -> 22.4 | BW8: =_xlfn.XLOOKUP(BW$1,$D$1:$AJ$1,$D8:$AJ8) -> 22.4 | BX8: =BW8-BV8 -> 0 | BY8: =_xlfn.XLOOKUP(BY$1,$D$1:$AJ$1,$D8:$AJ8) -> 22.4 | BZ8: =_xlfn.XLOOKUP(BZ$1,$D$1:$AJ$1,$D8:$AJ8) -> 13.738917 | CA8: =_xlfn.XLOOKUP(CA$1,$D$1:$AJ$1,$D8:$AJ8) -> 8.6610828 | CB8: =BZ8+CA8-BY8 -> 0 | CC8: =_xlfn.XLOOKUP(CC$1,$D$1:$AJ$1,$D8:$AJ8) -> 13.738917 | CD8: =_xlfn.XLOOKUP(CD$1,$D$1:$AJ$1,$D8:$AJ8) -> 13.738917 | CE8: =_xlfn.XLOOKUP(CE$1,$D$1:$AJ$1,$D8:$AJ8) -> 0 | CF8: =CD8+CE8-CC8 -> 0 | CG8: =_xlfn.XLOOKUP(CG$1,$D$1:$AJ$1,$D8:$AJ8) -> 13.738917 | CH8: =_xlfn.XLOOKUP(CH$1,$D$1:$AJ$1,$D8:$AJ8) -> 0 | CI8: =_xlfn.XLOOKUP(CI$1,$D$1:$AJ$1,$D8:$AJ8) -> 13.738917 | CJ8: =CG8+CH8-CI8 -> 0 | CK8: =_xlfn.XLOOKUP(CK$1,$D$1:$AJ$1,$D8:$AJ8) -> 13.738917 | CL8: =_xlfn.XLOOKUP(CL$1,$D$1:$AJ$1,$D8:$AJ8) -> 13.738917 | CM8: =_xlfn.XLOOKUP(CM$1,$D$1:$AJ$1,$D8:$AJ8) -> 0 | CN8: =CL8+CM8-CK8 -> 0 | CO8: =_xlfn.XLOOKUP(CO$1,$D$1:$AJ$1,$D8:$AJ8) -> 13.738917 | CP8: =_xlfn.XLOOKUP(CP$1,$D$1:$AJ$1,$D8:$AJ8) -> 0 | CQ8: =_xlfn.XLOOKUP(CQ$1,$D$1:$AJ$1,$D8:$AJ8) -> 13.738917 | CR8: =CO8+CP8-CQ8 -> 0 | CS8: =_xlfn.XLOOKUP(CS$1,$D$1:$AJ$1,$D8:$AJ8) -> 13.738917 | CT8: =_xlfn.XLOOKUP(CT$1,$D$1:$AJ$1,$D8:$AJ8) -> 13.738917 | CU8: =_xlfn.XLOOKUP(CU$1,$D$1:$AJ$1,$D8:$AJ8) -> 0 | CV8: =CT8+CU8-CS8 -> 0 | CW8: =_xlfn.XLOOKUP(CW$1,$D$1:$AJ$1,$D8:$AJ8) -> 13.738917 | CX8: =_xlfn.XLOOKUP(CX$1,$D$1:$AJ$1,$D8:$AJ8) -> 13.738917 | CY8: =_xlfn.XLOOKUP(CY$1,$D$1:$AJ$1,$D8:$AJ8) -> 0 | CZ8: =CX8+CY8-CW8 -> 0 | DA8: =_xlfn.XLOOKUP(DA$1,$D$1:$AJ$1,$D8:$AJ8) -> 8.6610828 | DB8: =_xlfn.XLOOKUP(DB$1,$D$1:$AJ$1,$D8:$AJ8) -> 6.7244432 | DC8: =_xlfn.XLOOKUP(DC$1,$D$1:$AJ$1,$D8:$AJ8) -> 1.9366396 | DD8: =DC8+DB8-DA8 -> 0 | DE8: =_xlfn.XLOOKUP(DE$1,$D$1:$AJ$1,$D8:$AJ8) -> 6.7244432 | DF8: =_xlfn.XLOOKUP(DF$1,$D$1:$AJ$1,$D8:$AJ8) -> 0 | DG8: =_xlfn.XLOOKUP(DG$1,$D$1:$AJ$1,$D8:$AJ8) -> 5.8780098 | DH8: =_xlfn.XLOOKUP(DH$1,$D$1:$AJ$1,$D8:$AJ8) -> 0.84643341 | DI8: =DG8+DH8-DF8-DE8 -> 0 | DJ8: =_xlfn.XLOOKUP(DJ$1,$D$1:$AJ$1,$D8:$AJ8) -> 5.8780098 | DK8: =_xlfn.XLOOKUP(DK$1,$D$1:$AJ$1,$D8:$AJ8) -> 5.8780098 | DL8: =DK8-DJ8 -> 0 | DM8: =_xlfn.XLOOKUP(DM$1,$D$1:$AJ$1,$D8:$AJ8) -> 5.8780098 | DN8: =_xlfn.XLOOKUP(DN$1,$D$1:$AJ$1,$D8:$AJ8) -> 5.8780098 | DO8: =DN8-DM8 -> 0 | DP8: =_xlfn.XLOOKUP(DP$1,$D$1:$AJ$1,$D8:$AJ8) -> 5.8780098 | DQ8: =_xlfn.XLOOKUP(DQ$1,$D$1:$AJ$1,$D8:$AJ8) -> 5.8780098 | DR8: =_xlfn.XLOOKUP(DR$1,$D$1:$AJ$1,$D8:$AJ8) -> 0 | DS8: =DQ8+DR8-DP8 -> 0 | DT8: =_xlfn.XLOOKUP(DT$1,$D$1:$AJ$1,$D8:$AJ8) -> 5.8780098 | DU8: =_xlfn.XLOOKUP(DU$1,$D$1:$AJ$1,$D8:$AJ8) -> 5.8780098 | DV8: =_xlfn.XLOOKUP(DV$1,$D$1:$AJ$1,$D8:$AJ8) -> 0 | DW8: =DU8+DV8-DT8 -> 0
A9: 6 | B9: kg | C9: Sugars | D9: 5.6 | E9: 5.0893821 | F9: 0.51061788 | G9: 5.0893821 | H9: 0 | I9: 0 | J9: 5.0893821 | K9: 5.0893821 | L9: 0.38469497 | M9: 4.7046872 | N9: 0.2509635 | O9: 0.13373147 | P9: 0 | Q9: 0.2509635 | R9: 0.22484542 | S9: 0.026118076 | T9: 0 | U9: 0.22484542 | V9: 0.21848527 | W9: 0.0063601561 | X9: 0.21848527 | Y9: 0 | Z9: 2.0019945 | AA9: 2.7026926 | AB9: 0 | AC9: 1.1952206 | AD9: 0.80677392 | AE9: 1.1952206 | AF9: 1.1952206 | AG9: 1.1952206 | AH9: 0 | AI9: 1.1952206 | AJ9: 0 | AL9: =C9 -> Sugars | AM9: =_xlfn.XLOOKUP(AM$1,$D$1:$AJ$1,$D9:$AJ9) -> 5.6 | AN9: =_xlfn.XLOOKUP(AN$1,$D$1:$AJ$1,$D9:$AJ9) -> 0 | AO9: =_xlfn.XLOOKUP(AO$1,$D$1:$AJ$1,$D9:$AJ9) -> 0 | AP9: =_xlfn.XLOOKUP(AP$1,$D$1:$AJ$1,$D9:$AJ9) -> 0 | AQ9: =_xlfn.XLOOKUP(AQ$1,$D$1:$AJ$1,$D9:$AJ9) -> 0 | AR9: =_xlfn.XLOOKUP(AR$1,$D$1:$AJ$1,$D9:$AJ9) -> 0 | AS9: =SUM(AM9:AR9) -> 5.6 | AV9: =_xlfn.XLOOKUP(AV$1,$D$1:$AJ$1,$D9:$AJ9) -> 0.51061788 | AW9: =_xlfn.XLOOKUP(AW$1,$D$1:$AJ$1,$D9:$AJ9) -> 0.13373147 | AX9: =_xlfn.XLOOKUP(AX$1,$D$1:$AJ$1,$D9:$AJ9) -> 0.026118076 | AY9: =_xlfn.XLOOKUP(AY$1,$D$1:$AJ$1,$D9:$AJ9) -> 0.0063601561 | AZ9: =_xlfn.XLOOKUP(AZ$1,$D$1:$AJ$1,$D9:$AJ9) -> 0.21848527 | BA9: =_xlfn.XLOOKUP(BA$1,$D$1:$AJ$1,$D9:$AJ9) -> 0 | BB9: =_xlfn.XLOOKUP(BB$1,$D$1:$AJ$1,$D9:$AJ9) -> 2.7026926 | BC9: =_xlfn.XLOOKUP(BC$1,$D$1:$AJ$1,$D9:$AJ9) -> 0.80677392 | ... BF9: =_xlfn.XLOOKUP(BF$1,$D$1:$AJ$1,$D9:$AJ9) -> 0 | BG9: =SUM(AV9:BF9) -> 5.6 | BH9: =BG9-AS9 -> 0 | BJ9: =_xlfn.XLOOKUP(BJ$1,$D$1:$AJ$1,$D9:$AJ9) -> 5.6 | BK9: =_xlfn.XLOOKUP(BK$1,$D$1:$AJ$1,$D9:$AJ9) -> 5.0893821 | BL9: =_xlfn.XLOOKUP(BL$1,$D$1:$AJ$1,$D9:$AJ9) -> 0.51061788 | BM9: =BJ9-BK9-BL9 -> 1.3322676e-15 | BN9: =_xlfn.XLOOKUP(BN$1,$D$1:$AJ$1,$D9:$AJ9) -> 5.0893821 | BO9: =_xlfn.XLOOKUP(BO$1,$D$1:$AJ$1,$D9:$AJ9) -> 5.0893821 | BP9: =BN9-BO9 -> 0 | BQ9: =_xlfn.XLOOKUP(BQ$1,$D$1:$AJ$1,$D9:$AJ9) -> 5.0893821 | BR9: =_xlfn.XLOOKUP(BR$1,$D$1:$AJ$1,$D9:$AJ9) -> 0 | BS9: =_xlfn.XLOOKUP(BS$1,$D$1:$AJ$1,$D9:$AJ9) -> 0 | BT9: =_xlfn.XLOOKUP(BT$1,$D$1:$AJ$1,$D9:$AJ9) -> 5.0893821 | BU9: =BQ9+BR9+BS9-BT9 -> 0 | BV9: =_xlfn.XLOOKUP(BV$1,$D$1:$AJ$1,$D9:$AJ9) -> 5.0893821 | BW9: =_xlfn.XLOOKUP(BW$1,$D$1:$AJ$1,$D9:$AJ9) -> 5.0893821 | BX9: =BW9-BV9 -> 0 | BY9: =_xlfn.XLOOKUP(BY$1,$D$1:$AJ$1,$D9:$AJ9) -> 5.0893821 | BZ9: =_xlfn.XLOOKUP(BZ$1,$D$1:$AJ$1,$D9:$AJ9) -> 0.38469497 | CA9: =_xlfn.XLOOKUP(CA$1,$D$1:$AJ$1,$D9:$AJ9) -> 4.7046872 | CB9: =BZ9+CA9-BY9 -> 0 | CC9: =_xlfn.XLOOKUP(CC$1,$D$1:$AJ$1,$D9:$AJ9) -> 0.38469497 | CD9: =_xlfn.XLOOKUP(CD$1,$D$1:$AJ$1,$D9:$AJ9) -> 0.2509635 | CE9: =_xlfn.XLOOKUP(CE$1,$D$1:$AJ$1,$D9:$AJ9) -> 0.13373147 | CF9: =CD9+CE9-CC9 -> 0 | CG9: =_xlfn.XLOOKUP(CG$1,$D$1:$AJ$1,$D9:$AJ9) -> 0.2509635 | CH9: =_xlfn.XLOOKUP(CH$1,$D$1:$AJ$1,$D9:$AJ9) -> 0 | CI9: =_xlfn.XLOOKUP(CI$1,$D$1:$AJ$1,$D9:$AJ9) -> 0.2509635 | CJ9: =CG9+CH9-CI9 -> 0 | CK9: =_xlfn.XLOOKUP(CK$1,$D$1:$AJ$1,$D9:$AJ9) -> 0.2509635 | CL9: =_xlfn.XLOOKUP(CL$1,$D$1:$AJ$1,$D9:$AJ9) -> 0.22484542 | CM9: =_xlfn.XLOOKUP(CM$1,$D$1:$AJ$1,$D9:$AJ9) -> 0.026118076 | CN9: =CL9+CM9-CK9 -> 0 | CO9: =_xlfn.XLOOKUP(CO$1,$D$1:$AJ$1,$D9:$AJ9) -> 0.22484542 | CP9: =_xlfn.XLOOKUP(CP$1,$D$1:$AJ$1,$D9:$AJ9) -> 0 | CQ9: =_xlfn.XLOOKUP(CQ$1,$D$1:$AJ$1,$D9:$AJ9) -> 0.22484542 | CR9: =CO9+CP9-CQ9 -> 0 | CS9: =_xlfn.XLOOKUP(CS$1,$D$1:$AJ$1,$D9:$AJ9) -> 0.22484542 | CT9: =_xlfn.XLOOKUP(CT$1,$D$1:$AJ$1,$D9:$AJ9) -> 0.21848527 | CU9: =_xlfn.XLOOKUP(CU$1,$D$1:$AJ$1,$D9:$AJ9) -> 0.0063601561 | CV9: =CT9+CU9-CS9 -> 0 | CW9: =_xlfn.XLOOKUP(CW$1,$D$1:$AJ$1,$D9:$AJ9) -> 0.21848527 | CX9: =_xlfn.XLOOKUP(CX$1,$D$1:$AJ$1,$D9:$AJ9) -> 0.21848527 | CY9: =_xlfn.XLOOKUP(CY$1,$D$1:$AJ$1,$D9:$AJ9) -> 0 | CZ9: =CX9+CY9-CW9 -> 0 | DA9: =_xlfn.XLOOKUP(DA$1,$D$1:$AJ$1,$D9:$AJ9) -> 4.7046872 | DB9: =_xlfn.XLOOKUP(DB$1,$D$1:$AJ$1,$D9:$AJ9) -> 2.0019945 | DC9: =_xlfn.XLOOKUP(DC$1,$D$1:$AJ$1,$D9:$AJ9) -> 2.7026926 | DD9: =DC9+DB9-DA9 -> 0 | DE9: =_xlfn.XLOOKUP(DE$1,$D$1:$AJ$1,$D9:$AJ9) -> 2.0019945 | DF9: =_xlfn.XLOOKUP(DF$1,$D$1:$AJ$1,$D9:$AJ9) -> 0 | DG9: =_xlfn.XLOOKUP(DG$1,$D$1:$AJ$1,$D9:$AJ9) -> 1.1952206 | DH9: =_xlfn.XLOOKUP(DH$1,$D$1:$AJ$1,$D9:$AJ9) -> 0.80677392 | DI9: =DG9+DH9-DF9-DE9 -> 0 | DJ9: =_xlfn.XLOOKUP(DJ$1,$D$1:$AJ$1,$D9:$AJ9) -> 1.1952206 | DK9: =_xlfn.XLOOKUP(DK$1,$D$1:$AJ$1,$D9:$AJ9) -> 1.1952206 | DL9: =DK9-DJ9 -> 0 | DM9: =_xlfn.XLOOKUP(DM$1,$D$1:$AJ$1,$D9:$AJ9) -> 1.1952206 | DN9: =_xlfn.XLOOKUP(DN$1,$D$1:$AJ$1,$D9:$AJ9) -> 1.1952206 | DO9: =DN9-DM9 -> 0 | DP9: =_xlfn.XLOOKUP(DP$1,$D$1:$AJ$1,$D9:$AJ9) -> 1.1952206 | DQ9: =_xlfn.XLOOKUP(DQ$1,$D$1:$AJ$1,$D9:$AJ9) -> 1.1952206 | DR9: =_xlfn.XLOOKUP(DR$1,$D$1:$AJ$1,$D9:$AJ9) -> 0 | DS9: =DQ9+DR9-DP9 -> 0 | DT9: =_xlfn.XLOOKUP(DT$1,$D$1:$AJ$1,$D9:$AJ9) -> 1.1952206 | DU9: =_xlfn.XLOOKUP(DU$1,$D$1:$AJ$1,$D9:$AJ9) -> 1.1952206 | DV9: =_xlfn.XLOOKUP(DV$1,$D$1:$AJ$1,$D9:$AJ9) -> 0 | DW9: =DU9+DV9-DT9 -> 0
